Workbook
Name CapBase: Assumptions!$B$36
Name CapStress: Assumptions!$B$37
Name CapTarget: Assumptions!$B$35
Name Carry: Assumptions!$B$21
Name CatchUp: Assumptions!$B$23
Name ChecksStatus: Checks!$A$4
Name ClosingMonths: Assumptions!$B$8
Name Commitments: Assumptions!$B$5
Name CompanyCap: Assumptions!$B$10
Name CompanyCapPct: Assumptions!$B$9
Name CompanyMaxSPV: Assumptions!$B$11
Name EuropeMinPct: Assumptions!$B$12
Name FeeFirstClose: Assumptions!$B$18
Name FeeIP: Assumptions!$B$16
Name FeePost: Assumptions!$B$17
Name GPCommitMin: Assumptions!$B$25
Name GPCommitPct: Assumptions!$B$24
Name GrowthDirectMin: Assumptions!$D$48
Name Horizon: 'Cash flows'!$B$4
Name Hurdle: Assumptions!$B$22
Name IPYears: Assumptions!$B$7
Name QualifyingMinPct: Assumptions!$B$13
Name ResSeed_bridges: Assumptions!$B$55
Name ResSeed_graduation_pct: Assumptions!$B$52
Name ResSeed_next_round: Assumptions!$B$53
Name ResSeed_pro_rata_pct: Assumptions!$B$54
Name ResVenture_bridges: Assumptions!$C$55
Name ResVenture_graduation_pct: Assumptions!$C$52
Name ResVenture_next_round: Assumptions!$C$53
Name ResVenture_pro_rata_pct: Assumptions!$C$54
Name RunningCost: Assumptions!$B$20
Name SecCo1: Assumptions!$B$31
Name SecCo2: Assumptions!$B$32
Name SecPrice: Assumptions!$B$30
Name SecShare: Assumptions!$B$28
Name SecYear: Assumptions!$B$29
Name SetupCost: Assumptions!$B$19
Name TailCost: 'Cash flows'!$B$5
Name TermYears: Assumptions!$B$6

Sheet Read me
A1: ProFund Fund I — Fund model (v2)
A2: Model date 2026-10-29 · Seed to Growth · amounts in euros · contact alexandre@profund.vc
A4: PRE-MARKETING | B4: This document is a pre-marketing communication within the meaning of Article 4a of Regulation (EU) No 345/2013 (EuVECA). The fund is not yet established and no units may be subscribed at this stage. For professional and eligible investors only.
B5: All projections, targets, simulated portfolios, and return figures (IRR/DPI/MOIC) are indicative, hypothetical, and illustrative; actual results may differ materially.
B6: Fund expenses are an estimate pending the EuVECA manager's quote.
A8: Status | B8: =ChecksStatus -> ALL CHECKS PASS
A10: Tabs
A11: Assumptions | B11: Fund size, terms and fees, the partial secondary sale, the cap of each case, layer bounds and the follow-on reserve policy.
A12: Lines | B12: The simulation lines (Seed S-, Venture V-, Growth G-): entry, follow-on and exit inputs, then proceeds and MOIC per case, with layer subtotals.
A13: Construction | B13: Portfolio by layer, capital allocation, reserves vs policy, exposure per company and the fund returner.
A14: Cash flows | B14: Yearly flows per case: investments, exits incl. the year-6 secondary, fees, expenses, capital calls, the European waterfall step by step, LP and GP flows; net TVPI, IRR and DPI.
A15: Performance | B15: The Fund Performance table shown on profund.vc/pitch, linked to the tabs above.
A16: Checks | B16: Every output compared with the Python model the site and the fact sheet read (scripts/fund_model.py → src/data/fund.json). Change an input and they turn red: the workbook then shows your case, no longer the published one.
A18: Conventions
A19: Blue | B19: Input: change it and the whole workbook recalculates (Excel, LibreOffice, Google Sheets).
A20: Black | B20: Formula.
A21: Green | B21: Check against the Python model.
A22: Years | B22: Year 1 = year of the first closing; all flows at year end.
A23: Rounding | B23: Every amount is rounded to its display grain (EUR 10K below EUR 1M, EUR 100K above) before any sum, as in the Python model; ratios at their display precision.

Sheet Assumptions
A1: Assumptions
A2: Blue cells are inputs: change one and the whole workbook recalculates.
A4: Fund
A5: Commitments (target Fund I) | B5: 100000000
A6: Fund term (years) | B6: 10
A7: Investment period (years) | B7: 5 | F7: Management fee on commitments during this period
A8: Successive closings after the first (months) | B8: 24 | F8: Information; flows start at year 1 = year of first closing
A9: Max per company from the fund (% of commitments) | B9: 0.1
A10: Max per company from the fund | B10: =ROUND((CompanyCapPct*Commitments)/IF(ABS(CompanyCapPct*Commitments)<1000000,10000,100000),0)*IF(ABS(CompanyCapPct*Commitments)<1000000,10000,100000) -> 10000000
A11: Max per company with co-investment SPVs | B11: 15000000 | F11: Above the fund's cap: one or several SPVs offered to investors, outside the fund
A12: Europe (EU/EEA, UK, Switzerland), minimum | B12: 0.85 | F12: Information
A13: EuVECA qualifying investments, minimum | B13: 0.7 | F13: Information
A15: Terms
A16: Management fee during the investment period, on commitments | B16: 0.02
A17: Management fee after, on invested capital still held (at cost) | B17: 0.015
A18: Management fee, first-close investors | B18: 0.0175 | F18: Information only: the model keeps the standard fee (prudent)
A19: Set-up cost (year 1) | B19: 400000 | F19: Fund expenses are an estimate pending the EuVECA manager's quote.
A20: Running cost per year (platform, administration, audit) | B20: 350000 | F20: Fund expenses are an estimate pending the EuVECA manager's quote.
A21: Carried interest | B21: 0.2
A22: Hurdle (compounded annually) | B22: 0.08 | F22: European whole-of-fund waterfall
A23: GP catch-up | B23: 1
A24: GP commitment, minimum (% of commitments) | B24: 0.01 | F24: Information
A25: GP commitment, minimum | B25: =ROUND((GPCommitPct*Commitments)/IF(ABS(GPCommitPct*Commitments)<1000000,10000,100000),0)*IF(ABS(GPCommitPct*Commitments)<1000000,10000,100000) -> 1000000
A27: Early liquidity: partial secondary sale of the winners
A28: Share of the position sold | B28: 0.25
A29: Year of the secondary sale | B29: 6 | F29: Applies to every line of these companies that exits after this year
A30: Price, % of the exit value | B30: 0.6
A31: Company 1 sold in part | B31: S-01
A32: Company 2 sold in part | B32: V-01
A34: Cases: cap applied to every exit value, everything else unchanged
A35: Target case, exit value cap | B35: none | F35: Type an amount to cap, or 'none'
A36: Base case, exit value cap | B36: 500000000
A37: Stress case, exit value cap | B37: 250000000
A39: Layer bounds (portfolio construction rules)
B40: Seed | C40: Venture | D40: Growth
A41: Initial ticket, minimum | B41: 100000 | C41: 1500000 | D41: 5000000
A42: Initial ticket, maximum | B42: 1500000 | C42: 5000000 | D42: 10000000
A43: Entry post-money, minimum | B43: 5000000 | C43: 25000000 | D43: 80000000
A44: Entry post-money, maximum | B44: 20000000 | C44: 80000000 | D44: 400000000
A45: Entry stake, minimum | B45: 0.05 | C45: 0.05 | D45: 0.02
A46: Entry stake, maximum | B46: 0.125 | C46: 0.08 | D46: 0.05
A47: Companies (new entries) | B47: 18 | C47: 8 | D47: 3
A48: Growth: direct entries, minimum share of the layer | D48: 0.4
A50: Follow-on reserve policy (expected value)
B51: Seed | C51: Venture
A52: Share of companies raising the next round | B52: 0.4 | C52: 0.5
A53: Next round size | B53: 15000000 | C53: 40000000
A54: Pro-rata stake | B54: 0.06 | C54: 0.065
A55: Bridges | B55: 1000000 | C55: 0

Sheet Lines
A1: Fund simulation — line by line
A2: Seed (S-), Venture (V-) and Growth (G-) lines. A line may group several companies (n): initial and follow-on are line totals. Blue = input, black = formula.
A4: INPUTS | P4: FORMULAS | Y4: CASH-FLOW HELPERS (used by the Cash flows tab)
A5: Deal ID | B5: Layer | C5: Company (exit key) | D5: Companies on the line | E5: Outcome | F5: Kind | G5: Initial tickets (line total) | H5: Entry post-money (per company) | I5: Follow-on (line total) | J5: Entry year | K5: Follow-on year | L5: Exit year | M5: Exit stake (diluted) | N5: Exit value (100%) | O5: Recovery multiple (if no exit value) | P5: Invested | Q5: Invested per company | R5: Entry stake | S5: Proceeds · Target | T5: Proceeds · Base | U5: Proceeds · Stress | V5: MOIC · Target | W5: MOIC · Base | X5: MOIC · Stress | Y5: Target · secondary sale proceeds | Z5: Target · proceeds at exit year | AA5: Target · cost sold in secondary | AB5: Target · cost at exit year | AC5: Base · secondary sale proceeds | AD5: Base · proceeds at exit year | AE5: Base · cost sold in secondary | AF5: Base · cost at exit year | AG5: Stress · secondary sale proceeds | AH5: Stress · proceeds at exit year | AI5: Stress · cost sold in secondary | AJ5: Stress · cost at exit year
A6: S-01 | B6: Seed | C6: S-01 | D6: 1 | E6: Fund returner | F6: new | G6: 1000000 | H6: 8000000 | I6: 2000000 | J6: 1 | K6: 2 | L6: 8 | M6: 0.045 | N6: 1500000000 | P6: =G6+I6 -> 3000000 | Q6: =P6/D6 -> 3000000 | R6: =ROUND(G6/D6/H6,3) -> 0.125 | S6: =IF(ISNUMBER($O6),ROUND(($O6*$P6)/IF(ABS($O6*$P6)<1000000,10000,100000),0)*IF(ABS($O6*$P6)<1000000,10000,100000),ROUND(($M6*IF(ISNUMBER(CapTarget),MIN($N6,CapTarget),$N6))/IF(ABS($M6*IF(ISNUMBER(CapTarget),MIN($N6,CapTarget),$N6))<1000000,10000,100000),0)*IF(ABS($M6*IF(ISNUMBER(CapTarget),MIN($N6,CapTarget),$N6))<1000000,10000,100000)) -> 67500000 | T6: =IF(ISNUMBER($O6),ROUND(($O6*$P6)/IF(ABS($O6*$P6)<1000000,10000,100000),0)*IF(ABS($O6*$P6)<1000000,10000,100000),ROUND(($M6*IF(ISNUMBER(CapBase),MIN($N6,CapBase),$N6))/IF(ABS($M6*IF(ISNUMBER(CapBase),MIN($N6,CapBase),$N6))<1000000,10000,100000),0)*IF(ABS($M6*IF(ISNUMBER(CapBase),MIN($N6,CapBase),$N6))<1000000,10000,100000)) -> 22500000 | U6: =IF(ISNUMBER($O6),ROUND(($O6*$P6)/IF(ABS($O6*$P6)<1000000,10000,100000),0)*IF(ABS($O6*$P6)<1000000,10000,100000),ROUND(($M6*IF(ISNUMBER(CapStress),MIN($N6,CapStress),$N6))/IF(ABS($M6*IF(ISNUMBER(CapStress),MIN($N6,CapStress),$N6))<1000000,10000,100000),0)*IF(ABS($M6*IF(ISNUMBER(CapStress),MIN($N6,CapStress),$N6))<1000000,10000,100000)) -> 11300000 | V6: =ROUND(S6/$P6,1) -> 22.5 | W6: =ROUND(T6/$P6,1) -> 7.5 | X6: =ROUND(U6/$P6,1) -> 3.8 | Y6: =IF(AND(OR($C6=SecCo1,$C6=SecCo2),$L6>SecYear,S6<>0),ROUND((SecShare*SecPrice*S6)/IF(ABS(SecShare*SecPrice*S6)<1000000,10000,100000),0)*IF(ABS(SecShare*SecPrice*S6)<1000000,10000,100000),0) -> 10100000 | Z6: =IF(AND(OR($C6=SecCo1,$C6=SecCo2),$L6>SecYear,S6<>0),ROUND(((1-SecShare)*S6)/IF(ABS((1-SecShare)*S6)<1000000,10000,100000),0)*IF(ABS((1-SecShare)*S6)<1000000,10000,100000),S6) -> 50600000 | AA6: =IF(AND(OR($C6=SecCo1,$C6=SecCo2),$L6>SecYear,S6<>0),SecShare*$P6,0) -> 750000 | AB6: =$P6-AA6 -> 2250000 | AC6: =IF(AND(OR($C6=SecCo1,$C6=SecCo2),$L6>SecYear,T6<>0),ROUND((SecShare*SecPrice*T6)/IF(ABS(SecShare*SecPrice*T6)<1000000,10000,100000),0)*IF(ABS(SecShare*SecPrice*T6)<1000000,10000,100000),0) -> 3400000 | AD6: =IF(AND(OR($C6=SecCo1,$C6=SecCo2),$L6>SecYear,T6<>0),ROUND(((1-SecShare)*T6)/IF(ABS((1-SecShare)*T6)<1000000,10000,100000),0)*IF(ABS((1-SecShare)*T6)<1000000,10000,100000),T6) -> 16900000 | AE6: =IF(AND(OR($C6=SecCo1,$C6=SecCo2),$L6>SecYear,T6<>0),SecShare*$P6,0) -> 750000 | AF6: =$P6-AE6 -> 2250000 | AG6: =IF(AND(OR($C6=SecCo1,$C6=SecCo2),$L6>SecYear,U6<>0),ROUND((SecShare*SecPrice*U6)/IF(ABS(SecShare*SecPrice*U6)<1000000,10000,100000),0)*IF(ABS(SecShare*SecPrice*U6)<1000000,10000,100000),0) -> 1700000 | AH6: =IF(AND(OR($C6=SecCo1,$C6=SecCo2),$L6>SecYear,U6<>0),ROUND(((1-SecShare)*U6)/IF(ABS((1-SecShare)*U6)<1000000,10000,100000),0)*IF(ABS((1-SecShare)*U6)<1000000,10000,100000),U6) -> 8500000 | AI6: =IF(AND(OR($C6=SecCo1,$C6=SecCo2),$L6>SecYear,U6<>0),SecShare*$P6,0) -> 750000 | AJ6: =$P6-AI6 -> 2250000
A7: S-02 | B7: Seed | C7: S-02 | D7: 1 | E7: Breakout | F7: new | G7: 750000 | H7: 8000000 | I7: 1500000 | J7: 1 | K7: 2 | L7: 7 | M7: 0.035 | N7: 600000000 | P7: =G7+I7 -> 2250000 | Q7: =P7/D7 -> 2250000 | R7: =ROUND(G7/D7/H7,3) -> 0.094 | S7: =IF(ISNUMBER($O7),ROUND(($O7*$P7)/IF(ABS($O7*$P7)<1000000,10000,100000),0)*IF(ABS($O7*$P7)<1000000,10000,100000),ROUND(($M7*IF(ISNUMBER(CapTarget),MIN($N7,CapTarget),$N7))/IF(ABS($M7*IF(ISNUMBER(CapTarget),MIN($N7,CapTarget),$N7))<1000000,10000,100000),0)*IF(ABS($M7*IF(ISNUMBER(CapTarget),MIN($N7,CapTarget),$N7))<1000000,10000,100000)) -> 21000000 | T7: =IF(ISNUMBER($O7),ROUND(($O7*$P7)/IF(ABS($O7*$P7)<1000000,10000,100000),0)*IF(ABS($O7*$P7)<1000000,10000,100000),ROUND(($M7*IF(ISNUMBER(CapBase),MIN($N7,CapBase),$N7))/IF(ABS($M7*IF(ISNUMBER(CapBase),MIN($N7,CapBase),$N7))<1000000,10000,100000),0)*IF(ABS($M7*IF(ISNUMBER(CapBase),MIN($N7,CapBase),$N7))<1000000,10000,100000)) -> 17500000 | U7: =IF(ISNUMBER($O7),ROUND(($O7*$P7)/IF(ABS($O7*$P7)<1000000,10000,100000),0)*IF(ABS($O7*$P7)<1000000,10000,100000),ROUND(($M7*IF(ISNUMBER(CapStress),MIN($N7,CapStress),$N7))/IF(ABS($M7*IF(ISNUMBER(CapStress),MIN($N7,CapStress),$N7))<1000000,10000,100000),0)*IF(ABS($M7*IF(ISNUMBER(CapStress),MIN($N7,CapStress),$N7))<1000000,10000,100000)) -> 8800000 | V7: =ROUND(S7/$P7,1) -> 9.3 | W7: =ROUND(T7/$P7,1) -> 7.8 | X7: =ROUND(U7/$P7,1) -> 3.9 | Y7: =IF(AND(OR($C7=SecCo1,$C7=SecCo2),$L7>SecYear,S7<>0),ROUND((SecShare*SecPrice*S7)/IF(ABS(SecShare*SecPrice*S7)<1000000,10000,100000),0)*IF(ABS(SecShare*SecPrice*S7)<1000000,10000,100000),0) -> 0 | Z7: =IF(AND(OR($C7=SecCo1,$C7=SecCo2),$L7>SecYear,S7<>0),ROUND(((1-SecShare)*S7)/IF(ABS((1-SecShare)*S7)<1000000,10000,100000),0)*IF(ABS((1-SecShare)*S7)<1000000,10000,100000),S7) -> 21000000 | AA7: =IF(AND(OR($C7=SecCo1,$C7=SecCo2),$L7>SecYear,S7<>0),SecShare*$P7,0) -> 0 | AB7: =$P7-AA7 -> 2250000 | AC7: =IF(AND(OR($C7=SecCo1,$C7=SecCo2),$L7>SecYear,T7<>0),ROUND((SecShare*SecPrice*T7)/IF(ABS(SecShare*SecPrice*T7)<1000000,10000,100000),0)*IF(ABS(SecShare*SecPrice*T7)<1000000,10000,100000),0) -> 0 | AD7: =IF(AND(OR($C7=SecCo1,$C7=SecCo2),$L7>SecYear,T7<>0),ROUND(((1-SecShare)*T7)/IF(ABS((1-SecShare)*T7)<1000000,10000,100000),0)*IF(ABS((1-SecShare)*T7)<1000000,10000,100000),T7) -> 17500000 | AE7: =IF(AND(OR($C7=SecCo1,$C7=SecCo2),$L7>SecYear,T7<>0),SecShare*$P7,0) -> 0 | AF7: =$P7-AE7 -> 2250000 | AG7: =IF(AND(OR($C7=SecCo1,$C7=SecCo2),$L7>SecYear,U7<>0),ROUND((SecShare*SecPrice*U7)/IF(ABS(SecShare*SecPrice*U7)<1000000,10000,100000),0)*IF(ABS(SecShare*SecPrice*U7)<1000000,10000,100000),0) -> 0 | AH7: =IF(AND(OR($C7=SecCo1,$C7=SecCo2),$L7>SecYear,U7<>0),ROUND(((1-SecShare)*U7)/IF(ABS((1-SecShare)*U7)<1000000,10000,100000),0)*IF(ABS((1-SecShare)*U7)<1000000,10000,100000),U7) -> 8800000 | AI7: =IF(AND(OR($C7=SecCo1,$C7=SecCo2),$L7>SecYear,U7<>0),SecShare*$P7,0) -> 0 | AJ7: =$P7-AI7 -> 2250000
A8: S-03 | B8: Seed | C8: S-03 | D8: 1 | E8: Breakout | F8: new | G8: 750000 | H8: 10000000 | I8: 1000000 | J8: 1 | K8: 3 | L8: 7 | M8: 0.03 | N8: 300000000 | P8: =G8+I8 -> 1750000 | Q8: =P8/D8 -> 1750000 | R8: =ROUND(G8/D8/H8,3) -> 0.075 | S8: =IF(ISNUMBER($O8),ROUND(($O8*$P8)/IF(ABS($O8*$P8)<1000000,10000,100000),0)*IF(ABS($O8*$P8)<1000000,10000,100000),ROUND(($M8*IF(ISNUMBER(CapTarget),MIN($N8,CapTarget),$N8))/IF(ABS($M8*IF(ISNUMBER(CapTarget),MIN($N8,CapTarget),$N8))<1000000,10000,100000),0)*IF(ABS($M8*IF(ISNUMBER(CapTarget),MIN($N8,CapTarget),$N8))<1000000,10000,100000)) -> 9000000 | T8: =IF(ISNUMBER($O8),ROUND(($O8*$P8)/IF(ABS($O8*$P8)<1000000,10000,100000),0)*IF(ABS($O8*$P8)<1000000,10000,100000),ROUND(($M8*IF(ISNUMBER(CapBase),MIN($N8,CapBase),$N8))/IF(ABS($M8*IF(ISNUMBER(CapBase),MIN($N8,CapBase),$N8))<1000000,10000,100000),0)*IF(ABS($M8*IF(ISNUMBER(CapBase),MIN($N8,CapBase),$N8))<1000000,10000,100000)) -> 9000000 | U8: =IF(ISNUMBER($O8),ROUND(($O8*$P8)/IF(ABS($O8*$P8)<1000000,10000,100000),0)*IF(ABS($O8*$P8)<1000000,10000,100000),ROUND(($M8*IF(ISNUMBER(CapStress),MIN($N8,CapStress),$N8))/IF(ABS($M8*IF(ISNUMBER(CapStress),MIN($N8,CapStress),$N8))<1000000,10000,100000),0)*IF(ABS($M8*IF(ISNUMBER(CapStress),MIN($N8,CapStress),$N8))<1000000,10000,100000)) -> 7500000 | V8: =ROUND(S8/$P8,1) -> 5.1 | W8: =ROUND(T8/$P8,1) -> 5.1 | X8: =ROUND(U8/$P8,1) -> 4.3 | Y8: =IF(AND(OR($C8=SecCo1,$C8=SecCo2),$L8>SecYear,S8<>0),ROUND((SecShare*SecPrice*S8)/IF(ABS(SecShare*SecPrice*S8)<1000000,10000,100000),0)*IF(ABS(SecShare*SecPrice*S8)<1000000,10000,100000),0) -> 0 | Z8: =IF(AND(OR($C8=SecCo1,$C8=SecCo2),$L8>SecYear,S8<>0),ROUND(((1-SecShare)*S8)/IF(ABS((1-SecShare)*S8)<1000000,10000,100000),0)*IF(ABS((1-SecShare)*S8)<1000000,10000,100000),S8) -> 9000000 | AA8: =IF(AND(OR($C8=SecCo1,$C8=SecCo2),$L8>SecYear,S8<>0),SecShare*$P8,0) -> 0 | AB8: =$P8-AA8 -> 1750000 | AC8: =IF(AND(OR($C8=SecCo1,$C8=SecCo2),$L8>SecYear,T8<>0),ROUND((SecShare*SecPrice*T8)/IF(ABS(SecShare*SecPrice*T8)<1000000,10000,100000),0)*IF(ABS(SecShare*SecPrice*T8)<1000000,10000,100000),0) -> 0 | AD8: =IF(AND(OR($C8=SecCo1,$C8=SecCo2),$L8>SecYear,T8<>0),ROUND(((1-SecShare)*T8)/IF(ABS((1-SecShare)*T8)<1000000,10000,100000),0)*IF(ABS((1-SecShare)*T8)<1000000,10000,100000),T8) -> 9000000 | AE8: =IF(AND(OR($C8=SecCo1,$C8=SecCo2),$L8>SecYear,T8<>0),SecShare*$P8,0) -> 0 | AF8: =$P8-AE8 -> 1750000 | AG8: =IF(AND(OR($C8=SecCo1,$C8=SecCo2),$L8>SecYear,U8<>0),ROUND((SecShare*SecPrice*U8)/IF(ABS(SecShare*SecPrice*U8)<1000000,10000,100000),0)*IF(ABS(SecShare*SecPrice*U8)<1000000,10000,100000),0) -> 0 | AH8: =IF(AND(OR($C8=SecCo1,$C8=SecCo2),$L8>SecYear,U8<>0),ROUND(((1-SecShare)*U8)/IF(ABS((1-SecShare)*U8)<1000000,10000,100000),0)*IF(ABS((1-SecShare)*U8)<1000000,10000,100000),U8) -> 7500000 | AI8: =IF(AND(OR($C8=SecCo1,$C8=SecCo2),$L8>SecYear,U8<>0),SecShare*$P8,0) -> 0 | AJ8: =$P8-AI8 -> 1750000
A9: S-04 | B9: Seed | C9: S-04 | D9: 1 | E9: Strategic exit | F9: new | G9: 500000 | H9: 8000000 | I9: 500000 | J9: 2 | K9: 3 | L9: 5 | M9: 0.05 | N9: 150000000 | P9: =G9+I9 -> 1000000 | Q9: =P9/D9 -> 1000000 | R9: =ROUND(G9/D9/H9,3) -> 0.063 | S9: =IF(ISNUMBER($O9),ROUND(($O9*$P9)/IF(ABS($O9*$P9)<1000000,10000,100000),0)*IF(ABS($O9*$P9)<1000000,10000,100000),ROUND(($M9*IF(ISNUMBER(CapTarget),MIN($N9,CapTarget),$N9))/IF(ABS($M9*IF(ISNUMBER(CapTarget),MIN($N9,CapTarget),$N9))<1000000,10000,100000),0)*IF(ABS($M9*IF(ISNUMBER(CapTarget),MIN($N9,CapTarget),$N9))<1000000,10000,100000)) -> 7500000 | T9: =IF(ISNUMBER($O9),ROUND(($O9*$P9)/IF(ABS($O9*$P9)<1000000,10000,100000),0)*IF(ABS($O9*$P9)<1000000,10000,100000),ROUND(($M9*IF(ISNUMBER(CapBase),MIN($N9,CapBase),$N9))/IF(ABS($M9*IF(ISNUMBER(CapBase),MIN($N9,CapBase),$N9))<1000000,10000,100000),0)*IF(ABS($M9*IF(ISNUMBER(CapBase),MIN($N9,CapBase),$N9))<1000000,10000,100000)) -> 7500000 | U9: =IF(ISNUMBER($O9),ROUND(($O9*$P9)/IF(ABS($O9*$P9)<1000000,10000,100000),0)*IF(ABS($O9*$P9)<1000000,10000,100000),ROUND(($M9*IF(ISNUMBER(CapStress),MIN($N9,CapStress),$N9))/IF(ABS($M9*IF(ISNUMBER(CapStress),MIN($N9,CapStress),$N9))<1000000,10000,100000),0)*IF(ABS($M9*IF(ISNUMBER(CapStress),MIN($N9,CapStress),$N9))<1000000,10000,100000)) -> 7500000 | V9: =ROUND(S9/$P9,1) -> 7.5 | W9: =ROUND(T9/$P9,1) -> 7.5 | X9: =ROUND(U9/$P9,1) -> 7.5 | Y9: =IF(AND(OR($C9=SecCo1,$C9=SecCo2),$L9>SecYear,S9<>0),ROUND((SecShare*SecPrice*S9)/IF(ABS(SecShare*SecPrice*S9)<1000000,10000,100000),0)*IF(ABS(SecShare*SecPrice*S9)<1000000,10000,100000),0) -> 0 | Z9: =IF(AND(OR($C9=SecCo1,$C9=SecCo2),$L9>SecYear,S9<>0),ROUND(((1-SecShare)*S9)/IF(ABS((1-SecShare)*S9)<1000000,10000,100000),0)*IF(ABS((1-SecShare)*S9)<1000000,10000,100000),S9) -> 7500000 | AA9: =IF(AND(OR($C9=SecCo1,$C9=SecCo2),$L9>SecYear,S9<>0),SecShare*$P9,0) -> 0 | AB9: =$P9-AA9 -> 1000000 | AC9: =IF(AND(OR($C9=SecCo1,$C9=SecCo2),$L9>SecYear,T9<>0),ROUND((SecShare*SecPrice*T9)/IF(ABS(SecShare*SecPrice*T9)<1000000,10000,100000),0)*IF(ABS(SecShare*SecPrice*T9)<1000000,10000,100000),0) -> 0 | AD9: =IF(AND(OR($C9=SecCo1,$C9=SecCo2),$L9>SecYear,T9<>0),ROUND(((1-SecShare)*T9)/IF(ABS((1-SecShare)*T9)<1000000,10000,100000),0)*IF(ABS((1-SecShare)*T9)<1000000,10000,100000),T9) -> 7500000 | AE9: =IF(AND(OR($C9=SecCo1,$C9=SecCo2),$L9>SecYear,T9<>0),SecShare*$P9,0) -> 0 | AF9: =$P9-AE9 -> 1000000 | AG9: =IF(AND(OR($C9=SecCo1,$C9=SecCo2),$L9>SecYear,U9<>0),ROUND((SecShare*SecPrice*U9)/IF(ABS(SecShare*SecPrice*U9)<1000000,10000,100000),0)*IF(ABS(SecShare*SecPrice*U9)<1000000,10000,100000),0) -> 0 | AH9: =IF(AND(OR($C9=SecCo1,$C9=SecCo2),$L9>SecYear,U9<>0),ROUND(((1-SecShare)*U9)/IF(ABS((1-SecShare)*U9)<1000000,10000,100000),0)*IF(ABS((1-SecShare)*U9)<1000000,10000,100000),U9) -> 7500000 | AI9: =IF(AND(OR($C9=SecCo1,$C9=SecCo2),$L9>SecYear,U9<>0),SecShare*$P9,0) -> 0 | AJ9: =$P9-AI9 -> 1000000
A10: S-05 | B10: Seed | C10: S-05 | D10: 1 | E10: Early exit (M&A) | F10: new | G10: 500000 | H10: 8000000 | I10: 500000 | J10: 1 | K10: 2 | L10: 4 | M10: 0.045 | N10: 60000000 | P10: =G10+I10 -> 1000000 | Q10: =P10/D10 -> 1000000 | R10: =ROUND(G10/D10/H10,3) -> 0.063 | S10: =IF(ISNUMBER($O10),ROUND(($O10*$P10)/IF(ABS($O10*$P10)<1000000,10000,100000),0)*IF(ABS($O10*$P10)<1000000,10000,100000),ROUND(($M10*IF(ISNUMBER(CapTarget),MIN($N10,CapTarget),$N10))/IF(ABS($M10*IF(ISNUMBER(CapTarget),MIN($N10,CapTarget),$N10))<1000000,10000,100000),0)*IF(ABS($M10*IF(ISNUMBER(CapTarget),MIN($N10,CapTarget),$N10))<1000000,10000,100000)) -> 2700000 | T10: =IF(ISNUMBER($O10),ROUND(($O10*$P10)/IF(ABS($O10*$P10)<1000000,10000,100000),0)*IF(ABS($O10*$P10)<1000000,10000,100000),ROUND(($M10*IF(ISNUMBER(CapBase),MIN($N10,CapBase),$N10))/IF(ABS($M10*IF(ISNUMBER(CapBase),MIN($N10,CapBase),$N10))<1000000,10000,100000),0)*IF(ABS($M10*IF(ISNUMBER(CapBase),MIN($N10,CapBase),$N10))<1000000,10000,100000)) -> 2700000 | U10: =IF(ISNUMBER($O10),ROUND(($O10*$P10)/IF(ABS($O10*$P10)<1000000,10000,100000),0)*IF(ABS($O10*$P10)<1000000,10000,100000),ROUND(($M10*IF(ISNUMBER(CapStress),MIN($N10,CapStress),$N10))/IF(ABS($M10*IF(ISNUMBER(CapStress),MIN($N10,CapStress),$N10))<1000000,10000,100000),0)*IF(ABS($M10*IF(ISNUMBER(CapStress),MIN($N10,CapStress),$N10))<1000000,10000,100000)) -> 2700000 | V10: =ROUND(S10/$P10,1) -> 2.7 | W10: =ROUND(T10/$P10,1) -> 2.7 | X10: =ROUND(U10/$P10,1) -> 2.7 | Y10: =IF(AND(OR($C10=SecCo1,$C10=SecCo2),$L10>SecYear,S10<>0),ROUND((SecShare*SecPrice*S10)/IF(ABS(SecShare*SecPrice*S10)<1000000,10000,100000),0)*IF(ABS(SecShare*SecPrice*S10)<1000000,10000,100000),0) -> 0 | Z10: =IF(AND(OR($C10=SecCo1,$C10=SecCo2),$L10>SecYear,S10<>0),ROUND(((1-SecShare)*S10)/IF(ABS((1-SecShare)*S10)<1000000,10000,100000),0)*IF(ABS((1-SecShare)*S10)<1000000,10000,100000),S10) -> 2700000 | AA10: =IF(AND(OR($C10=SecCo1,$C10=SecCo2),$L10>SecYear,S10<>0),SecShare*$P10,0) -> 0 | AB10: =$P10-AA10 -> 1000000 | AC10: =IF(AND(OR($C10=SecCo1,$C10=SecCo2),$L10>SecYear,T10<>0),ROUND((SecShare*SecPrice*T10)/IF(ABS(SecShare*SecPrice*T10)<1000000,10000,100000),0)*IF(ABS(SecShare*SecPrice*T10)<1000000,10000,100000),0) -> 0 | AD10: =IF(AND(OR($C10=SecCo1,$C10=SecCo2),$L10>SecYear,T10<>0),ROUND(((1-SecShare)*T10)/IF(ABS((1-SecShare)*T10)<1000000,10000,100000),0)*IF(ABS((1-SecShare)*T10)<1000000,10000,100000),T10) -> 2700000 | AE10: =IF(AND(OR($C10=SecCo1,$C10=SecCo2),$L10>SecYear,T10<>0),SecShare*$P10,0) -> 0 | AF10: =$P10-AE10 -> 1000000 | AG10: =IF(AND(OR($C10=SecCo1,$C10=SecCo2),$L10>SecYear,U10<>0),ROUND((SecShare*SecPrice*U10)/IF(ABS(SecShare*SecPrice*U10)<1000000,10000,100000),0)*IF(ABS(SecShare*SecPrice*U10)<1000000,10000,100000),0) -> 0 | AH10: =IF(AND(OR($C10=SecCo1,$C10=SecCo2),$L10>SecYear,U10<>0),ROUND(((1-SecShare)*U10)/IF(ABS((1-SecShare)*U10)<1000000,10000,100000),0)*IF(ABS((1-SecShare)*U10)<1000000,10000,100000),U10) -> 2700000 | AI10: =IF(AND(OR($C10=SecCo1,$C10=SecCo2),$L10>SecYear,U10<>0),SecShare*$P10,0) -> 0 | AJ10: =$P10-AI10 -> 1000000
A11: S-06 | B11: Seed | C11: S-06 | D11: 1 | E11: Early exit (M&A) | F11: new | G11: 300000 | H11: 6000000 | I11: 0 | J11: 2 | L11: 4 | M11: 0.04 | N11: 40000000 | P11: =G11+I11 -> 300000 | Q11: =P11/D11 -> 300000 | R11: =ROUND(G11/D11/H11,3) -> 0.05 | S11: =IF(ISNUMBER($O11),ROUND(($O11*$P11)/IF(ABS($O11*$P11)<1000000,10000,100000),0)*IF(ABS($O11*$P11)<1000000,10000,100000),ROUND(($M11*IF(ISNUMBER(CapTarget),MIN($N11,CapTarget),$N11))/IF(ABS($M11*IF(ISNUMBER(CapTarget),MIN($N11,CapTarget),$N11))<1000000,10000,100000),0)*IF(ABS($M11*IF(ISNUMBER(CapTarget),MIN($N11,CapTarget),$N11))<1000000,10000,100000)) -> 1600000 | T11: =IF(ISNUMBER($O11),ROUND(($O11*$P11)/IF(ABS($O11*$P11)<1000000,10000,100000),0)*IF(ABS($O11*$P11)<1000000,10000,100000),ROUND(($M11*IF(ISNUMBER(CapBase),MIN($N11,CapBase),$N11))/IF(ABS($M11*IF(ISNUMBER(CapBase),MIN($N11,CapBase),$N11))<1000000,10000,100000),0)*IF(ABS($M11*IF(ISNUMBER(CapBase),MIN($N11,CapBase),$N11))<1000000,10000,100000)) -> 1600000 | U11: =IF(ISNUMBER($O11),ROUND(($O11*$P11)/IF(ABS($O11*$P11)<1000000,10000,100000),0)*IF(ABS($O11*$P11)<1000000,10000,100000),ROUND(($M11*IF(ISNUMBER(CapStress),MIN($N11,CapStress),$N11))/IF(ABS($M11*IF(ISNUMBER(CapStress),MIN($N11,CapStress),$N11))<1000000,10000,100000),0)*IF(ABS($M11*IF(ISNUMBER(CapStress),MIN($N11,CapStress),$N11))<1000000,10000,100000)) -> 1600000 | V11: =ROUND(S11/$P11,1) -> 5.3 | W11: =ROUND(T11/$P11,1) -> 5.3 | X11: =ROUND(U11/$P11,1) -> 5.3 | Y11: =IF(AND(OR($C11=SecCo1,$C11=SecCo2),$L11>SecYear,S11<>0),ROUND((SecShare*SecPrice*S11)/IF(ABS(SecShare*SecPrice*S11)<1000000,10000,100000),0)*IF(ABS(SecShare*SecPrice*S11)<1000000,10000,100000),0) -> 0 | Z11: =IF(AND(OR($C11=SecCo1,$C11=SecCo2),$L11>SecYear,S11<>0),ROUND(((1-SecShare)*S11)/IF(ABS((1-SecShare)*S11)<1000000,10000,100000),0)*IF(ABS((1-SecShare)*S11)<1000000,10000,100000),S11) -> 1600000 | AA11: =IF(AND(OR($C11=SecCo1,$C11=SecCo2),$L11>SecYear,S11<>0),SecShare*$P11,0) -> 0 | AB11: =$P11-AA11 -> 300000 | AC11: =IF(AND(OR($C11=SecCo1,$C11=SecCo2),$L11>SecYear,T11<>0),ROUND((SecShare*SecPrice*T11)/IF(ABS(SecShare*SecPrice*T11)<1000000,10000,100000),0)*IF(ABS(SecShare*SecPrice*T11)<1000000,10000,100000),0) -> 0 | AD11: =IF(AND(OR($C11=SecCo1,$C11=SecCo2),$L11>SecYear,T11<>0),ROUND(((1-SecShare)*T11)/IF(ABS((1-SecShare)*T11)<1000000,10000,100000),0)*IF(ABS((1-SecShare)*T11)<1000000,10000,100000),T11) -> 1600000 | AE11: =IF(AND(OR($C11=SecCo1,$C11=SecCo2),$L11>SecYear,T11<>0),SecShare*$P11,0) -> 0 | AF11: =$P11-AE11 -> 300000 | AG11: =IF(AND(OR($C11=SecCo1,$C11=SecCo2),$L11>SecYear,U11<>0),ROUND((SecShare*SecPrice*U11)/IF(ABS(SecShare*SecPrice*U11)<1000000,10000,100000),0)*IF(ABS(SecShare*SecPrice*U11)<1000000,10000,100000),0) -> 0 | AH11: =IF(AND(OR($C11=SecCo1,$C11=SecCo2),$L11>SecYear,U11<>0),ROUND(((1-SecShare)*U11)/IF(ABS((1-SecShare)*U11)<1000000,10000,100000),0)*IF(ABS((1-SecShare)*U11)<1000000,10000,100000),U11) -> 1600000 | AI11: =IF(AND(OR($C11=SecCo1,$C11=SecCo2),$L11>SecYear,U11<>0),SecShare*$P11,0) -> 0 | AJ11: =$P11-AI11 -> 300000
A12: S-07–09 | B12: Seed | C12: S-07 | D12: 3 | E12: Zombies (×3) | F12: new | G12: 1200000 | H12: 8000000 | I12: 600000 | J12: 2 | K12: 3 | L12: 7 | O12: 0.5 | P12: =G12+I12 -> 1800000 | Q12: =P12/D12 -> 600000 | R12: =ROUND(G12/D12/H12,3) -> 0.05 | S12: =IF(ISNUMBER($O12),ROUND(($O12*$P12)/IF(ABS($O12*$P12)<1000000,10000,100000),0)*IF(ABS($O12*$P12)<1000000,10000,100000),ROUND(($M12*IF(ISNUMBER(CapTarget),MIN($N12,CapTarget),$N12))/IF(ABS($M12*IF(ISNUMBER(CapTarget),MIN($N12,CapTarget),$N12))<1000000,10000,100000),0)*IF(ABS($M12*IF(ISNUMBER(CapTarget),MIN($N12,CapTarget),$N12))<1000000,10000,100000)) -> 900000 | T12: =IF(ISNUMBER($O12),ROUND(($O12*$P12)/IF(ABS($O12*$P12)<1000000,10000,100000),0)*IF(ABS($O12*$P12)<1000000,10000,100000),ROUND(($M12*IF(ISNUMBER(CapBase),MIN($N12,CapBase),$N12))/IF(ABS($M12*IF(ISNUMBER(CapBase),MIN($N12,CapBase),$N12))<1000000,10000,100000),0)*IF(ABS($M12*IF(ISNUMBER(CapBase),MIN($N12,CapBase),$N12))<1000000,10000,100000)) -> 900000 | U12: =IF(ISNUMBER($O12),ROUND(($O12*$P12)/IF(ABS($O12*$P12)<1000000,10000,100000),0)*IF(ABS($O12*$P12)<1000000,10000,100000),ROUND(($M12*IF(ISNUMBER(CapStress),MIN($N12,CapStress),$N12))/IF(ABS($M12*IF(ISNUMBER(CapStress),MIN($N12,CapStress),$N12))<1000000,10000,100000),0)*IF(ABS($M12*IF(ISNUMBER(CapStress),MIN($N12,CapStress),$N12))<1000000,10000,100000)) -> 900000 | V12: =ROUND(S12/$P12,1) -> 0.5 | W12: =ROUND(T12/$P12,1) -> 0.5 | X12: =ROUND(U12/$P12,1) -> 0.5 | Y12: =IF(AND(OR($C12=SecCo1,$C12=SecCo2),$L12>SecYear,S12<>0),ROUND((SecShare*SecPrice*S12)/IF(ABS(SecShare*SecPrice*S12)<1000000,10000,100000),0)*IF(ABS(SecShare*SecPrice*S12)<1000000,10000,100000),0) -> 0 | Z12: =IF(AND(OR($C12=SecCo1,$C12=SecCo2),$L12>SecYear,S12<>0),ROUND(((1-SecShare)*S12)/IF(ABS((1-SecShare)*S12)<1000000,10000,100000),0)*IF(ABS((1-SecShare)*S12)<1000000,10000,100000),S12) -> 900000 | AA12: =IF(AND(OR($C12=SecCo1,$C12=SecCo2),$L12>SecYear,S12<>0),SecShare*$P12,0) -> 0 | AB12: =$P12-AA12 -> 1800000 | AC12: =IF(AND(OR($C12=SecCo1,$C12=SecCo2),$L12>SecYear,T12<>0),ROUND((SecShare*SecPrice*T12)/IF(ABS(SecShare*SecPrice*T12)<1000000,10000,100000),0)*IF(ABS(SecShare*SecPrice*T12)<1000000,10000,100000),0) -> 0 | AD12: =IF(AND(OR($C12=SecCo1,$C12=SecCo2),$L12>SecYear,T12<>0),ROUND(((1-SecShare)*T12)/IF(ABS((1-SecShare)*T12)<1000000,10000,100000),0)*IF(ABS((1-SecShare)*T12)<1000000,10000,100000),T12) -> 900000 | AE12: =IF(AND(OR($C12=SecCo1,$C12=SecCo2),$L12>SecYear,T12<>0),SecShare*$P12,0) -> 0 | AF12: =$P12-AE12 -> 1800000 | AG12: =IF(AND(OR($C12=SecCo1,$C12=SecCo2),$L12>SecYear,U12<>0),ROUND((SecShare*SecPrice*U12)/IF(ABS(SecShare*SecPrice*U12)<1000000,10000,100000),0)*IF(ABS(SecShare*SecPrice*U12)<1000000,10000,100000),0) -> 0 | AH12: =IF(AND(OR($C12=SecCo1,$C12=SecCo2),$L12>SecYear,U12<>0),ROUND(((1-SecShare)*U12)/IF(ABS((1-SecShare)*U12)<1000000,10000,100000),0)*IF(ABS((1-SecShare)*U12)<1000000,10000,100000),U12) -> 900000 | AI12: =IF(AND(OR($C12=SecCo1,$C12=SecCo2),$L12>SecYear,U12<>0),SecShare*$P12,0) -> 0 | AJ12: =$P12-AI12 -> 1800000
A13: S-10–18 | B13: Seed | C13: S-10 | D13: 9 | E13: Losses (×9) | F13: new | G13: 4000000 | H13: 8000000 | I13: 1400000 | J13: 2 | K13: 3 | L13: 5 | O13: 0 | P13: =G13+I13 -> 5400000 | Q13: =P13/D13 -> 600000 | R13: =ROUND(G13/D13/H13,3) -> 0.056 | S13: =IF(ISNUMBER($O13),ROUND(($O13*$P13)/IF(ABS($O13*$P13)<1000000,10000,100000),0)*IF(ABS($O13*$P13)<1000000,10000,100000),ROUND(($M13*IF(ISNUMBER(CapTarget),MIN($N13,CapTarget),$N13))/IF(ABS($M13*IF(ISNUMBER(CapTarget),MIN($N13,CapTarget),$N13))<1000000,10000,100000),0)*IF(ABS($M13*IF(ISNUMBER(CapTarget),MIN($N13,CapTarget),$N13))<1000000,10000,100000)) -> 0 | T13: =IF(ISNUMBER($O13),ROUND(($O13*$P13)/IF(ABS($O13*$P13)<1000000,10000,100000),0)*IF(ABS($O13*$P13)<1000000,10000,100000),ROUND(($M13*IF(ISNUMBER(CapBase),MIN($N13,CapBase),$N13))/IF(ABS($M13*IF(ISNUMBER(CapBase),MIN($N13,CapBase),$N13))<1000000,10000,100000),0)*IF(ABS($M13*IF(ISNUMBER(CapBase),MIN($N13,CapBase),$N13))<1000000,10000,100000)) -> 0 | U13: =IF(ISNUMBER($O13),ROUND(($O13*$P13)/IF(ABS($O13*$P13)<1000000,10000,100000),0)*IF(ABS($O13*$P13)<1000000,10000,100000),ROUND(($M13*IF(ISNUMBER(CapStress),MIN($N13,CapStress),$N13))/IF(ABS($M13*IF(ISNUMBER(CapStress),MIN($N13,CapStress),$N13))<1000000,10000,100000),0)*IF(ABS($M13*IF(ISNUMBER(CapStress),MIN($N13,CapStress),$N13))<1000000,10000,100000)) -> 0 | V13: =ROUND(S13/$P13,1) -> 0 | W13: =ROUND(T13/$P13,1) -> 0 | X13: =ROUND(U13/$P13,1) -> 0 | Y13: =IF(AND(OR($C13=SecCo1,$C13=SecCo2),$L13>SecYear,S13<>0),ROUND((SecShare*SecPrice*S13)/IF(ABS(SecShare*SecPrice*S13)<1000000,10000,100000),0)*IF(ABS(SecShare*SecPrice*S13)<1000000,10000,100000),0) -> 0 | Z13: =IF(AND(OR($C13=SecCo1,$C13=SecCo2),$L13>SecYear,S13<>0),ROUND(((1-SecShare)*S13)/IF(ABS((1-SecShare)*S13)<1000000,10000,100000),0)*IF(ABS((1-SecShare)*S13)<1000000,10000,100000),S13) -> 0 | AA13: =IF(AND(OR($C13=SecCo1,$C13=SecCo2),$L13>SecYear,S13<>0),SecShare*$P13,0) -> 0 | AB13: =$P13-AA13 -> 5400000 | AC13: =IF(AND(OR($C13=SecCo1,$C13=SecCo2),$L13>SecYear,T13<>0),ROUND((SecShare*SecPrice*T13)/IF(ABS(SecShare*SecPrice*T13)<1000000,10000,100000),0)*IF(ABS(SecShare*SecPrice*T13)<1000000,10000,100000),0) -> 0 | AD13: =IF(AND(OR($C13=SecCo1,$C13=SecCo2),$L13>SecYear,T13<>0),ROUND(((1-SecShare)*T13)/IF(ABS((1-SecShare)*T13)<1000000,10000,100000),0)*IF(ABS((1-SecShare)*T13)<1000000,10000,100000),T13) -> 0 | AE13: =IF(AND(OR($C13=SecCo1,$C13=SecCo2),$L13>SecYear,T13<>0),SecShare*$P13,0) -> 0 | AF13: =$P13-AE13 -> 5400000 | AG13: =IF(AND(OR($C13=SecCo1,$C13=SecCo2),$L13>SecYear,U13<>0),ROUND((SecShare*SecPrice*U13)/IF(ABS(SecShare*SecPrice*U13)<1000000,10000,100000),0)*IF(ABS(SecShare*SecPrice*U13)<1000000,10000,100000),0) -> 0 | AH13: =IF(AND(OR($C13=SecCo1,$C13=SecCo2),$L13>SecYear,U13<>0),ROUND(((1-SecShare)*U13)/IF(ABS((1-SecShare)*U13)<1000000,10000,100000),0)*IF(ABS((1-SecShare)*U13)<1000000,10000,100000),U13) -> 0 | AI13: =IF(AND(OR($C13=SecCo1,$C13=SecCo2),$L13>SecYear,U13<>0),SecShare*$P13,0) -> 0 | AJ13: =$P13-AI13 -> 5400000
A14: SUB | E14: (Seed) | G14: =SUM(G6:G13) -> 9000000 | I14: =SUM(I6:I13) -> 7500000 | P14: =SUM(P6:P13) -> 16500000 | S14: =SUM(S6:S13) -> 110200000 | T14: =SUM(T6:T13) -> 61700000 | U14: =SUM(U6:U13) -> 40300000 | V14: =ROUND(S14/P14,1) -> 6.7 | W14: =ROUND(T14/P14,1) -> 3.7 | X14: =ROUND(U14/P14,1) -> 2.4
A15: V-01 | B15: Venture | C15: V-01 | D15: 1 | E15: Anchor | F15: new | G15: 3000000 | H15: 45000000 | I15: 2000000 | J15: 1 | K15: 3 | L15: 8 | M15: 0.045 | N15: 1200000000 | P15: =G15+I15 -> 5000000 | Q15: =P15/D15 -> 5000000 | R15: =ROUND(G15/D15/H15,3) -> 0.067 | S15: =IF(ISNUMBER($O15),ROUND(($O15*$P15)/IF(ABS($O15*$P15)<1000000,10000,100000),0)*IF(ABS($O15*$P15)<1000000,10000,100000),ROUND(($M15*IF(ISNUMBER(CapTarget),MIN($N15,CapTarget),$N15))/IF(ABS($M15*IF(ISNUMBER(CapTarget),MIN($N15,CapTarget),$N15))<1000000,10000,100000),0)*IF(ABS($M15*IF(ISNUMBER(CapTarget),MIN($N15,CapTarget),$N15))<1000000,10000,100000)) -> 54000000 | T15: =IF(ISNUMBER($O15),ROUND(($O15*$P15)/IF(ABS($O15*$P15)<1000000,10000,100000),0)*IF(ABS($O15*$P15)<1000000,10000,100000),ROUND(($M15*IF(ISNUMBER(CapBase),MIN($N15,CapBase),$N15))/IF(ABS($M15*IF(ISNUMBER(CapBase),MIN($N15,CapBase),$N15))<1000000,10000,100000),0)*IF(ABS($M15*IF(ISNUMBER(CapBase),MIN($N15,CapBase),$N15))<1000000,10000,100000)) -> 22500000 | U15: =IF(ISNUMBER($O15),ROUND(($O15*$P15)/IF(ABS($O15*$P15)<1000000,10000,100000),0)*IF(ABS($O15*$P15)<1000000,10000,100000),ROUND(($M15*IF(ISNUMBER(CapStress),MIN($N15,CapStress),$N15))/IF(ABS($M15*IF(ISNUMBER(CapStress),MIN($N15,CapStress),$N15))<1000000,10000,100000),0)*IF(ABS($M15*IF(ISNUMBER(CapStress),MIN($N15,CapStress),$N15))<1000000,10000,100000)) -> 11300000 | V15: =ROUND(S15/$P15,1) -> 10.8 | W15: =ROUND(T15/$P15,1) -> 4.5 | X15: =ROUND(U15/$P15,1) -> 2.3 | Y15: =IF(AND(OR($C15=SecCo1,$C15=SecCo2),$L15>SecYear,S15<>0),ROUND((SecShare*SecPrice*S15)/IF(ABS(SecShare*SecPrice*S15)<1000000,10000,100000),0)*IF(ABS(SecShare*SecPrice*S15)<1000000,10000,100000),0) -> 8100000 | Z15: =IF(AND(OR($C15=SecCo1,$C15=SecCo2),$L15>SecYear,S15<>0),ROUND(((1-SecShare)*S15)/IF(ABS((1-SecShare)*S15)<1000000,10000,100000),0)*IF(ABS((1-SecShare)*S15)<1000000,10000,100000),S15) -> 40500000 | AA15: =IF(AND(OR($C15=SecCo1,$C15=SecCo2),$L15>SecYear,S15<>0),SecShare*$P15,0) -> 1250000 | AB15: =$P15-AA15 -> 3750000 | AC15: =IF(AND(OR($C15=SecCo1,$C15=SecCo2),$L15>SecYear,T15<>0),ROUND((SecShare*SecPrice*T15)/IF(ABS(SecShare*SecPrice*T15)<1000000,10000,100000),0)*IF(ABS(SecShare*SecPrice*T15)<1000000,10000,100000),0) -> 3400000 | AD15: =IF(AND(OR($C15=SecCo1,$C15=SecCo2),$L15>SecYear,T15<>0),ROUND(((1-SecShare)*T15)/IF(ABS((1-SecShare)*T15)<1000000,10000,100000),0)*IF(ABS((1-SecShare)*T15)<1000000,10000,100000),T15) -> 16900000 | AE15: =IF(AND(OR($C15=SecCo1,$C15=SecCo2),$L15>SecYear,T15<>0),SecShare*$P15,0) -> 1250000 | AF15: =$P15-AE15 -> 3750000 | AG15: =IF(AND(OR($C15=SecCo1,$C15=SecCo2),$L15>SecYear,U15<>0),ROUND((SecShare*SecPrice*U15)/IF(ABS(SecShare*SecPrice*U15)<1000000,10000,100000),0)*IF(ABS(SecShare*SecPrice*U15)<1000000,10000,100000),0) -> 1700000 | AH15: =IF(AND(OR($C15=SecCo1,$C15=SecCo2),$L15>SecYear,U15<>0),ROUND(((1-SecShare)*U15)/IF(ABS((1-SecShare)*U15)<1000000,10000,100000),0)*IF(ABS((1-SecShare)*U15)<1000000,10000,100000),U15) -> 8500000 | AI15: =IF(AND(OR($C15=SecCo1,$C15=SecCo2),$L15>SecYear,U15<>0),SecShare*$P15,0) -> 1250000 | AJ15: =$P15-AI15 -> 3750000
A16: V-02 | B16: Venture | C16: V-02 | D16: 1 | E16: Strategic win | F16: new | G16: 3000000 | H16: 45000000 | I16: 2000000 | J16: 1 | K16: 3 | L16: 7 | M16: 0.045 | N16: 600000000 | P16: =G16+I16 -> 5000000 | Q16: =P16/D16 -> 5000000 | R16: =ROUND(G16/D16/H16,3) -> 0.067 | S16: =IF(ISNUMBER($O16),ROUND(($O16*$P16)/IF(ABS($O16*$P16)<1000000,10000,100000),0)*IF(ABS($O16*$P16)<1000000,10000,100000),ROUND(($M16*IF(ISNUMBER(CapTarget),MIN($N16,CapTarget),$N16))/IF(ABS($M16*IF(ISNUMBER(CapTarget),MIN($N16,CapTarget),$N16))<1000000,10000,100000),0)*IF(ABS($M16*IF(ISNUMBER(CapTarget),MIN($N16,CapTarget),$N16))<1000000,10000,100000)) -> 27000000 | T16: =IF(ISNUMBER($O16),ROUND(($O16*$P16)/IF(ABS($O16*$P16)<1000000,10000,100000),0)*IF(ABS($O16*$P16)<1000000,10000,100000),ROUND(($M16*IF(ISNUMBER(CapBase),MIN($N16,CapBase),$N16))/IF(ABS($M16*IF(ISNUMBER(CapBase),MIN($N16,CapBase),$N16))<1000000,10000,100000),0)*IF(ABS($M16*IF(ISNUMBER(CapBase),MIN($N16,CapBase),$N16))<1000000,10000,100000)) -> 22500000 | U16: =IF(ISNUMBER($O16),ROUND(($O16*$P16)/IF(ABS($O16*$P16)<1000000,10000,100000),0)*IF(ABS($O16*$P16)<1000000,10000,100000),ROUND(($M16*IF(ISNUMBER(CapStress),MIN($N16,CapStress),$N16))/IF(ABS($M16*IF(ISNUMBER(CapStress),MIN($N16,CapStress),$N16))<1000000,10000,100000),0)*IF(ABS($M16*IF(ISNUMBER(CapStress),MIN($N16,CapStress),$N16))<1000000,10000,100000)) -> 11300000 | V16: =ROUND(S16/$P16,1) -> 5.4 | W16: =ROUND(T16/$P16,1) -> 4.5 | X16: =ROUND(U16/$P16,1) -> 2.3 | Y16: =IF(AND(OR($C16=SecCo1,$C16=SecCo2),$L16>SecYear,S16<>0),ROUND((SecShare*SecPrice*S16)/IF(ABS(SecShare*SecPrice*S16)<1000000,10000,100000),0)*IF(ABS(SecShare*SecPrice*S16)<1000000,10000,100000),0) -> 0 | Z16: =IF(AND(OR($C16=SecCo1,$C16=SecCo2),$L16>SecYear,S16<>0),ROUND(((1-SecShare)*S16)/IF(ABS((1-SecShare)*S16)<1000000,10000,100000),0)*IF(ABS((1-SecShare)*S16)<1000000,10000,100000),S16) -> 27000000 | AA16: =IF(AND(OR($C16=SecCo1,$C16=SecCo2),$L16>SecYear,S16<>0),SecShare*$P16,0) -> 0 | AB16: =$P16-AA16 -> 5000000 | AC16: =IF(AND(OR($C16=SecCo1,$C16=SecCo2),$L16>SecYear,T16<>0),ROUND((SecShare*SecPrice*T16)/IF(ABS(SecShare*SecPrice*T16)<1000000,10000,100000),0)*IF(ABS(SecShare*SecPrice*T16)<1000000,10000,100000),0) -> 0 | AD16: =IF(AND(OR($C16=SecCo1,$C16=SecCo2),$L16>SecYear,T16<>0),ROUND(((1-SecShare)*T16)/IF(ABS((1-SecShare)*T16)<1000000,10000,100000),0)*IF(ABS((1-SecShare)*T16)<1000000,10000,100000),T16) -> 22500000 | AE16: =IF(AND(OR($C16=SecCo1,$C16=SecCo2),$L16>SecYear,T16<>0),SecShare*$P16,0) -> 0 | AF16: =$P16-AE16 -> 5000000 | AG16: =IF(AND(OR($C16=SecCo1,$C16=SecCo2),$L16>SecYear,U16<>0),ROUND((SecShare*SecPrice*U16)/IF(ABS(SecShare*SecPrice*U16)<1000000,10000,100000),0)*IF(ABS(SecShare*SecPrice*U16)<1000000,10000,100000),0) -> 0 | AH16: =IF(AND(OR($C16=SecCo1,$C16=SecCo2),$L16>SecYear,U16<>0),ROUND(((1-SecShare)*U16)/IF(ABS((1-SecShare)*U16)<1000000,10000,100000),0)*IF(ABS((1-SecShare)*U16)<1000000,10000,100000),U16) -> 11300000 | AI16: =IF(AND(OR($C16=SecCo1,$C16=SecCo2),$L16>SecYear,U16<>0),SecShare*$P16,0) -> 0 | AJ16: =$P16-AI16 -> 5000000
A17: V-03 | B17: Venture | C17: V-03 | D17: 1 | E17: Strategic win | F17: new | G17: 3000000 | H17: 40000000 | I17: 1500000 | J17: 2 | K17: 4 | L17: 6 | M17: 0.045 | N17: 400000000 | P17: =G17+I17 -> 4500000 | Q17: =P17/D17 -> 4500000 | R17: =ROUND(G17/D17/H17,3) -> 0.075 | S17: =IF(ISNUMBER($O17),ROUND(($O17*$P17)/IF(ABS($O17*$P17)<1000000,10000,100000),0)*IF(ABS($O17*$P17)<1000000,10000,100000),ROUND(($M17*IF(ISNUMBER(CapTarget),MIN($N17,CapTarget),$N17))/IF(ABS($M17*IF(ISNUMBER(CapTarget),MIN($N17,CapTarget),$N17))<1000000,10000,100000),0)*IF(ABS($M17*IF(ISNUMBER(CapTarget),MIN($N17,CapTarget),$N17))<1000000,10000,100000)) -> 18000000 | T17: =IF(ISNUMBER($O17),ROUND(($O17*$P17)/IF(ABS($O17*$P17)<1000000,10000,100000),0)*IF(ABS($O17*$P17)<1000000,10000,100000),ROUND(($M17*IF(ISNUMBER(CapBase),MIN($N17,CapBase),$N17))/IF(ABS($M17*IF(ISNUMBER(CapBase),MIN($N17,CapBase),$N17))<1000000,10000,100000),0)*IF(ABS($M17*IF(ISNUMBER(CapBase),MIN($N17,CapBase),$N17))<1000000,10000,100000)) -> 18000000 | U17: =IF(ISNUMBER($O17),ROUND(($O17*$P17)/IF(ABS($O17*$P17)<1000000,10000,100000),0)*IF(ABS($O17*$P17)<1000000,10000,100000),ROUND(($M17*IF(ISNUMBER(CapStress),MIN($N17,CapStress),$N17))/IF(ABS($M17*IF(ISNUMBER(CapStress),MIN($N17,CapStress),$N17))<1000000,10000,100000),0)*IF(ABS($M17*IF(ISNUMBER(CapStress),MIN($N17,CapStress),$N17))<1000000,10000,100000)) -> 11300000 | V17: =ROUND(S17/$P17,1) -> 4 | W17: =ROUND(T17/$P17,1) -> 4 | X17: =ROUND(U17/$P17,1) -> 2.5 | Y17: =IF(AND(OR($C17=SecCo1,$C17=SecCo2),$L17>SecYear,S17<>0),ROUND((SecShare*SecPrice*S17)/IF(ABS(SecShare*SecPrice*S17)<1000000,10000,100000),0)*IF(ABS(SecShare*SecPrice*S17)<1000000,10000,100000),0) -> 0 | Z17: =IF(AND(OR($C17=SecCo1,$C17=SecCo2),$L17>SecYear,S17<>0),ROUND(((1-SecShare)*S17)/IF(ABS((1-SecShare)*S17)<1000000,10000,100000),0)*IF(ABS((1-SecShare)*S17)<1000000,10000,100000),S17) -> 18000000 | AA17: =IF(AND(OR($C17=SecCo1,$C17=SecCo2),$L17>SecYear,S17<>0),SecShare*$P17,0) -> 0 | AB17: =$P17-AA17 -> 4500000 | AC17: =IF(AND(OR($C17=SecCo1,$C17=SecCo2),$L17>SecYear,T17<>0),ROUND((SecShare*SecPrice*T17)/IF(ABS(SecShare*SecPrice*T17)<1000000,10000,100000),0)*IF(ABS(SecShare*SecPrice*T17)<1000000,10000,100000),0) -> 0 | AD17: =IF(AND(OR($C17=SecCo1,$C17=SecCo2),$L17>SecYear,T17<>0),ROUND(((1-SecShare)*T17)/IF(ABS((1-SecShare)*T17)<1000000,10000,100000),0)*IF(ABS((1-SecShare)*T17)<1000000,10000,100000),T17) -> 18000000 | AE17: =IF(AND(OR($C17=SecCo1,$C17=SecCo2),$L17>SecYear,T17<>0),SecShare*$P17,0) -> 0 | AF17: =$P17-AE17 -> 4500000 | AG17: =IF(AND(OR($C17=SecCo1,$C17=SecCo2),$L17>SecYear,U17<>0),ROUND((SecShare*SecPrice*U17)/IF(ABS(SecShare*SecPrice*U17)<1000000,10000,100000),0)*IF(ABS(SecShare*SecPrice*U17)<1000000,10000,100000),0) -> 0 | AH17: =IF(AND(OR($C17=SecCo1,$C17=SecCo2),$L17>SecYear,U17<>0),ROUND(((1-SecShare)*U17)/IF(ABS((1-SecShare)*U17)<1000000,10000,100000),0)*IF(ABS((1-SecShare)*U17)<1000000,10000,100000),U17) -> 11300000 | AI17: =IF(AND(OR($C17=SecCo1,$C17=SecCo2),$L17>SecYear,U17<>0),SecShare*$P17,0) -> 0 | AJ17: =$P17-AI17 -> 4500000
A18: V-04 | B18: Venture | C18: V-04 | D18: 1 | E18: Base hit | F18: new | G18: 3000000 | H18: 45000000 | I18: 1000000 | J18: 2 | K18: 4 | L18: 6 | M18: 0.04 | N18: 250000000 | P18: =G18+I18 -> 4000000 | Q18: =P18/D18 -> 4000000 | R18: =ROUND(G18/D18/H18,3) -> 0.067 | S18: =IF(ISNUMBER($O18),ROUND(($O18*$P18)/IF(ABS($O18*$P18)<1000000,10000,100000),0)*IF(ABS($O18*$P18)<1000000,10000,100000),ROUND(($M18*IF(ISNUMBER(CapTarget),MIN($N18,CapTarget),$N18))/IF(ABS($M18*IF(ISNUMBER(CapTarget),MIN($N18,CapTarget),$N18))<1000000,10000,100000),0)*IF(ABS($M18*IF(ISNUMBER(CapTarget),MIN($N18,CapTarget),$N18))<1000000,10000,100000)) -> 10000000 | T18: =IF(ISNUMBER($O18),ROUND(($O18*$P18)/IF(ABS($O18*$P18)<1000000,10000,100000),0)*IF(ABS($O18*$P18)<1000000,10000,100000),ROUND(($M18*IF(ISNUMBER(CapBase),MIN($N18,CapBase),$N18))/IF(ABS($M18*IF(ISNUMBER(CapBase),MIN($N18,CapBase),$N18))<1000000,10000,100000),0)*IF(ABS($M18*IF(ISNUMBER(CapBase),MIN($N18,CapBase),$N18))<1000000,10000,100000)) -> 10000000 | U18: =IF(ISNUMBER($O18),ROUND(($O18*$P18)/IF(ABS($O18*$P18)<1000000,10000,100000),0)*IF(ABS($O18*$P18)<1000000,10000,100000),ROUND(($M18*IF(ISNUMBER(CapStress),MIN($N18,CapStress),$N18))/IF(ABS($M18*IF(ISNUMBER(CapStress),MIN($N18,CapStress),$N18))<1000000,10000,100000),0)*IF(ABS($M18*IF(ISNUMBER(CapStress),MIN($N18,CapStress),$N18))<1000000,10000,100000)) -> 10000000 | V18: =ROUND(S18/$P18,1) -> 2.5 | W18: =ROUND(T18/$P18,1) -> 2.5 | X18: =ROUND(U18/$P18,1) -> 2.5 | Y18: =IF(AND(OR($C18=SecCo1,$C18=SecCo2),$L18>SecYear,S18<>0),ROUND((SecShare*SecPrice*S18)/IF(ABS(SecShare*SecPrice*S18)<1000000,10000,100000),0)*IF(ABS(SecShare*SecPrice*S18)<1000000,10000,100000),0) -> 0 | Z18: =IF(AND(OR($C18=SecCo1,$C18=SecCo2),$L18>SecYear,S18<>0),ROUND(((1-SecShare)*S18)/IF(ABS((1-SecShare)*S18)<1000000,10000,100000),0)*IF(ABS((1-SecShare)*S18)<1000000,10000,100000),S18) -> 10000000 | AA18: =IF(AND(OR($C18=SecCo1,$C18=SecCo2),$L18>SecYear,S18<>0),SecShare*$P18,0) -> 0 | AB18: =$P18-AA18 -> 4000000 | AC18: =IF(AND(OR($C18=SecCo1,$C18=SecCo2),$L18>SecYear,T18<>0),ROUND((SecShare*SecPrice*T18)/IF(ABS(SecShare*SecPrice*T18)<1000000,10000,100000),0)*IF(ABS(SecShare*SecPrice*T18)<1000000,10000,100000),0) -> 0 | AD18: =IF(AND(OR($C18=SecCo1,$C18=SecCo2),$L18>SecYear,T18<>0),ROUND(((1-SecShare)*T18)/IF(ABS((1-SecShare)*T18)<1000000,10000,100000),0)*IF(ABS((1-SecShare)*T18)<1000000,10000,100000),T18) -> 10000000 | AE18: =IF(AND(OR($C18=SecCo1,$C18=SecCo2),$L18>SecYear,T18<>0),SecShare*$P18,0) -> 0 | AF18: =$P18-AE18 -> 4000000 | AG18: =IF(AND(OR($C18=SecCo1,$C18=SecCo2),$L18>SecYear,U18<>0),ROUND((SecShare*SecPrice*U18)/IF(ABS(SecShare*SecPrice*U18)<1000000,10000,100000),0)*IF(ABS(SecShare*SecPrice*U18)<1000000,10000,100000),0) -> 0 | AH18: =IF(AND(OR($C18=SecCo1,$C18=SecCo2),$L18>SecYear,U18<>0),ROUND(((1-SecShare)*U18)/IF(ABS((1-SecShare)*U18)<1000000,10000,100000),0)*IF(ABS((1-SecShare)*U18)<1000000,10000,100000),U18) -> 10000000 | AI18: =IF(AND(OR($C18=SecCo1,$C18=SecCo2),$L18>SecYear,U18<>0),SecShare*$P18,0) -> 0 | AJ18: =$P18-AI18 -> 4000000
A19: V-05/06 | B19: Venture | C19: V-05 | D19: 2 | E19: Zombies (×2) | F19: new | G19: 6000000 | H19: 40000000 | I19: 1500000 | J19: 3 | K19: 4 | L19: 7 | O19: 0.4 | P19: =G19+I19 -> 7500000 | Q19: =P19/D19 -> 3750000 | R19: =ROUND(G19/D19/H19,3) -> 0.075 | S19: =IF(ISNUMBER($O19),ROUND(($O19*$P19)/IF(ABS($O19*$P19)<1000000,10000,100000),0)*IF(ABS($O19*$P19)<1000000,10000,100000),ROUND(($M19*IF(ISNUMBER(CapTarget),MIN($N19,CapTarget),$N19))/IF(ABS($M19*IF(ISNUMBER(CapTarget),MIN($N19,CapTarget),$N19))<1000000,10000,100000),0)*IF(ABS($M19*IF(ISNUMBER(CapTarget),MIN($N19,CapTarget),$N19))<1000000,10000,100000)) -> 3000000 | T19: =IF(ISNUMBER($O19),ROUND(($O19*$P19)/IF(ABS($O19*$P19)<1000000,10000,100000),0)*IF(ABS($O19*$P19)<1000000,10000,100000),ROUND(($M19*IF(ISNUMBER(CapBase),MIN($N19,CapBase),$N19))/IF(ABS($M19*IF(ISNUMBER(CapBase),MIN($N19,CapBase),$N19))<1000000,10000,100000),0)*IF(ABS($M19*IF(ISNUMBER(CapBase),MIN($N19,CapBase),$N19))<1000000,10000,100000)) -> 3000000 | U19: =IF(ISNUMBER($O19),ROUND(($O19*$P19)/IF(ABS($O19*$P19)<1000000,10000,100000),0)*IF(ABS($O19*$P19)<1000000,10000,100000),ROUND(($M19*IF(ISNUMBER(CapStress),MIN($N19,CapStress),$N19))/IF(ABS($M19*IF(ISNUMBER(CapStress),MIN($N19,CapStress),$N19))<1000000,10000,100000),0)*IF(ABS($M19*IF(ISNUMBER(CapStress),MIN($N19,CapStress),$N19))<1000000,10000,100000)) -> 3000000 | V19: =ROUND(S19/$P19,1) -> 0.4 | W19: =ROUND(T19/$P19,1) -> 0.4 | X19: =ROUND(U19/$P19,1) -> 0.4 | Y19: =IF(AND(OR($C19=SecCo1,$C19=SecCo2),$L19>SecYear,S19<>0),ROUND((SecShare*SecPrice*S19)/IF(ABS(SecShare*SecPrice*S19)<1000000,10000,100000),0)*IF(ABS(SecShare*SecPrice*S19)<1000000,10000,100000),0) -> 0 | Z19: =IF(AND(OR($C19=SecCo1,$C19=SecCo2),$L19>SecYear,S19<>0),ROUND(((1-SecShare)*S19)/IF(ABS((1-SecShare)*S19)<1000000,10000,100000),0)*IF(ABS((1-SecShare)*S19)<1000000,10000,100000),S19) -> 3000000 | AA19: =IF(AND(OR($C19=SecCo1,$C19=SecCo2),$L19>SecYear,S19<>0),SecShare*$P19,0) -> 0 | AB19: =$P19-AA19 -> 7500000 | AC19: =IF(AND(OR($C19=SecCo1,$C19=SecCo2),$L19>SecYear,T19<>0),ROUND((SecShare*SecPrice*T19)/IF(ABS(SecShare*SecPrice*T19)<1000000,10000,100000),0)*IF(ABS(SecShare*SecPrice*T19)<1000000,10000,100000),0) -> 0 | AD19: =IF(AND(OR($C19=SecCo1,$C19=SecCo2),$L19>SecYear,T19<>0),ROUND(((1-SecShare)*T19)/IF(ABS((1-SecShare)*T19)<1000000,10000,100000),0)*IF(ABS((1-SecShare)*T19)<1000000,10000,100000),T19) -> 3000000 | AE19: =IF(AND(OR($C19=SecCo1,$C19=SecCo2),$L19>SecYear,T19<>0),SecShare*$P19,0) -> 0 | AF19: =$P19-AE19 -> 7500000 | AG19: =IF(AND(OR($C19=SecCo1,$C19=SecCo2),$L19>SecYear,U19<>0),ROUND((SecShare*SecPrice*U19)/IF(ABS(SecShare*SecPrice*U19)<1000000,10000,100000),0)*IF(ABS(SecShare*SecPrice*U19)<1000000,10000,100000),0) -> 0 | AH19: =IF(AND(OR($C19=SecCo1,$C19=SecCo2),$L19>SecYear,U19<>0),ROUND(((1-SecShare)*U19)/IF(ABS((1-SecShare)*U19)<1000000,10000,100000),0)*IF(ABS((1-SecShare)*U19)<1000000,10000,100000),U19) -> 3000000 | AI19: =IF(AND(OR($C19=SecCo1,$C19=SecCo2),$L19>SecYear,U19<>0),SecShare*$P19,0) -> 0 | AJ19: =$P19-AI19 -> 7500000
A20: V-07/08 | B20: Venture | C20: V-07 | D20: 2 | E20: Losses (×2) | F20: new | G20: 6000000 | H20: 40000000 | I20: 2400000 | J20: 3 | K20: 4 | L20: 6 | O20: 0 | P20: =G20+I20 -> 8400000 | Q20: =P20/D20 -> 4200000 | R20: =ROUND(G20/D20/H20,3) -> 0.075 | S20: =IF(ISNUMBER($O20),ROUND(($O20*$P20)/IF(ABS($O20*$P20)<1000000,10000,100000),0)*IF(ABS($O20*$P20)<1000000,10000,100000),ROUND(($M20*IF(ISNUMBER(CapTarget),MIN($N20,CapTarget),$N20))/IF(ABS($M20*IF(ISNUMBER(CapTarget),MIN($N20,CapTarget),$N20))<1000000,10000,100000),0)*IF(ABS($M20*IF(ISNUMBER(CapTarget),MIN($N20,CapTarget),$N20))<1000000,10000,100000)) -> 0 | T20: =IF(ISNUMBER($O20),ROUND(($O20*$P20)/IF(ABS($O20*$P20)<1000000,10000,100000),0)*IF(ABS($O20*$P20)<1000000,10000,100000),ROUND(($M20*IF(ISNUMBER(CapBase),MIN($N20,CapBase),$N20))/IF(ABS($M20*IF(ISNUMBER(CapBase),MIN($N20,CapBase),$N20))<1000000,10000,100000),0)*IF(ABS($M20*IF(ISNUMBER(CapBase),MIN($N20,CapBase),$N20))<1000000,10000,100000)) -> 0 | U20: =IF(ISNUMBER($O20),ROUND(($O20*$P20)/IF(ABS($O20*$P20)<1000000,10000,100000),0)*IF(ABS($O20*$P20)<1000000,10000,100000),ROUND(($M20*IF(ISNUMBER(CapStress),MIN($N20,CapStress),$N20))/IF(ABS($M20*IF(ISNUMBER(CapStress),MIN($N20,CapStress),$N20))<1000000,10000,100000),0)*IF(ABS($M20*IF(ISNUMBER(CapStress),MIN($N20,CapStress),$N20))<1000000,10000,100000)) -> 0 | V20: =ROUND(S20/$P20,1) -> 0 | W20: =ROUND(T20/$P20,1) -> 0 | X20: =ROUND(U20/$P20,1) -> 0 | Y20: =IF(AND(OR($C20=SecCo1,$C20=SecCo2),$L20>SecYear,S20<>0),ROUND((SecShare*SecPrice*S20)/IF(ABS(SecShare*SecPrice*S20)<1000000,10000,100000),0)*IF(ABS(SecShare*SecPrice*S20)<1000000,10000,100000),0) -> 0 | Z20: =IF(AND(OR($C20=SecCo1,$C20=SecCo2),$L20>SecYear,S20<>0),ROUND(((1-SecShare)*S20)/IF(ABS((1-SecShare)*S20)<1000000,10000,100000),0)*IF(ABS((1-SecShare)*S20)<1000000,10000,100000),S20) -> 0 | AA20: =IF(AND(OR($C20=SecCo1,$C20=SecCo2),$L20>SecYear,S20<>0),SecShare*$P20,0) -> 0 | AB20: =$P20-AA20 -> 8400000 | AC20: =IF(AND(OR($C20=SecCo1,$C20=SecCo2),$L20>SecYear,T20<>0),ROUND((SecShare*SecPrice*T20)/IF(ABS(SecShare*SecPrice*T20)<1000000,10000,100000),0)*IF(ABS(SecShare*SecPrice*T20)<1000000,10000,100000),0) -> 0 | AD20: =IF(AND(OR($C20=SecCo1,$C20=SecCo2),$L20>SecYear,T20<>0),ROUND(((1-SecShare)*T20)/IF(ABS((1-SecShare)*T20)<1000000,10000,100000),0)*IF(ABS((1-SecShare)*T20)<1000000,10000,100000),T20) -> 0 | AE20: =IF(AND(OR($C20=SecCo1,$C20=SecCo2),$L20>SecYear,T20<>0),SecShare*$P20,0) -> 0 | AF20: =$P20-AE20 -> 8400000 | AG20: =IF(AND(OR($C20=SecCo1,$C20=SecCo2),$L20>SecYear,U20<>0),ROUND((SecShare*SecPrice*U20)/IF(ABS(SecShare*SecPrice*U20)<1000000,10000,100000),0)*IF(ABS(SecShare*SecPrice*U20)<1000000,10000,100000),0) -> 0 | AH20: =IF(AND(OR($C20=SecCo1,$C20=SecCo2),$L20>SecYear,U20<>0),ROUND(((1-SecShare)*U20)/IF(ABS((1-SecShare)*U20)<1000000,10000,100000),0)*IF(ABS((1-SecShare)*U20)<1000000,10000,100000),U20) -> 0 | AI20: =IF(AND(OR($C20=SecCo1,$C20=SecCo2),$L20>SecYear,U20<>0),SecShare*$P20,0) -> 0 | AJ20: =$P20-AI20 -> 8400000
A21: SUB | E21: (Venture) | G21: =SUM(G15:G20) -> 24000000 | I21: =SUM(I15:I20) -> 10400000 | P21: =SUM(P15:P20) -> 34400000 | S21: =SUM(S15:S20) -> 112000000 | T21: =SUM(T15:T20) -> 76000000 | U21: =SUM(U15:U20) -> 46900000 | V21: =ROUND(S21/P21,1) -> 3.3 | W21: =ROUND(T21/P21,1) -> 2.2 | X21: =ROUND(U21/P21,1) -> 1.4
A22: G-01 | B22: Growth | C22: S-01 | D22: 1 | E22: Breakout (S-01) | F22: follow_on | G22: 7000000 | H22: 250000000 | I22: 0 | J22: 3 | L22: 8 | M22: 0.022 | N22: 1500000000 | P22: =G22+I22 -> 7000000 | Q22: =P22/D22 -> 7000000 | R22: =ROUND(G22/D22/H22,3) -> 0.028 | S22: =IF(ISNUMBER($O22),ROUND(($O22*$P22)/IF(ABS($O22*$P22)<1000000,10000,100000),0)*IF(ABS($O22*$P22)<1000000,10000,100000),ROUND(($M22*IF(ISNUMBER(CapTarget),MIN($N22,CapTarget),$N22))/IF(ABS($M22*IF(ISNUMBER(CapTarget),MIN($N22,CapTarget),$N22))<1000000,10000,100000),0)*IF(ABS($M22*IF(ISNUMBER(CapTarget),MIN($N22,CapTarget),$N22))<1000000,10000,100000)) -> 33000000 | T22: =IF(ISNUMBER($O22),ROUND(($O22*$P22)/IF(ABS($O22*$P22)<1000000,10000,100000),0)*IF(ABS($O22*$P22)<1000000,10000,100000),ROUND(($M22*IF(ISNUMBER(CapBase),MIN($N22,CapBase),$N22))/IF(ABS($M22*IF(ISNUMBER(CapBase),MIN($N22,CapBase),$N22))<1000000,10000,100000),0)*IF(ABS($M22*IF(ISNUMBER(CapBase),MIN($N22,CapBase),$N22))<1000000,10000,100000)) -> 11000000 | U22: =IF(ISNUMBER($O22),ROUND(($O22*$P22)/IF(ABS($O22*$P22)<1000000,10000,100000),0)*IF(ABS($O22*$P22)<1000000,10000,100000),ROUND(($M22*IF(ISNUMBER(CapStress),MIN($N22,CapStress),$N22))/IF(ABS($M22*IF(ISNUMBER(CapStress),MIN($N22,CapStress),$N22))<1000000,10000,100000),0)*IF(ABS($M22*IF(ISNUMBER(CapStress),MIN($N22,CapStress),$N22))<1000000,10000,100000)) -> 5500000 | V22: =ROUND(S22/$P22,1) -> 4.7 | W22: =ROUND(T22/$P22,1) -> 1.6 | X22: =ROUND(U22/$P22,1) -> 0.8 | Y22: =IF(AND(OR($C22=SecCo1,$C22=SecCo2),$L22>SecYear,S22<>0),ROUND((SecShare*SecPrice*S22)/IF(ABS(SecShare*SecPrice*S22)<1000000,10000,100000),0)*IF(ABS(SecShare*SecPrice*S22)<1000000,10000,100000),0) -> 5000000 | Z22: =IF(AND(OR($C22=SecCo1,$C22=SecCo2),$L22>SecYear,S22<>0),ROUND(((1-SecShare)*S22)/IF(ABS((1-SecShare)*S22)<1000000,10000,100000),0)*IF(ABS((1-SecShare)*S22)<1000000,10000,100000),S22) -> 24800000 | AA22: =IF(AND(OR($C22=SecCo1,$C22=SecCo2),$L22>SecYear,S22<>0),SecShare*$P22,0) -> 1750000 | AB22: =$P22-AA22 -> 5250000 | AC22: =IF(AND(OR($C22=SecCo1,$C22=SecCo2),$L22>SecYear,T22<>0),ROUND((SecShare*SecPrice*T22)/IF(ABS(SecShare*SecPrice*T22)<1000000,10000,100000),0)*IF(ABS(SecShare*SecPrice*T22)<1000000,10000,100000),0) -> 1700000 | AD22: =IF(AND(OR($C22=SecCo1,$C22=SecCo2),$L22>SecYear,T22<>0),ROUND(((1-SecShare)*T22)/IF(ABS((1-SecShare)*T22)<1000000,10000,100000),0)*IF(ABS((1-SecShare)*T22)<1000000,10000,100000),T22) -> 8300000 | AE22: =IF(AND(OR($C22=SecCo1,$C22=SecCo2),$L22>SecYear,T22<>0),SecShare*$P22,0) -> 1750000 | AF22: =$P22-AE22 -> 5250000 | AG22: =IF(AND(OR($C22=SecCo1,$C22=SecCo2),$L22>SecYear,U22<>0),ROUND((SecShare*SecPrice*U22)/IF(ABS(SecShare*SecPrice*U22)<1000000,10000,100000),0)*IF(ABS(SecShare*SecPrice*U22)<1000000,10000,100000),0) -> 830000 | AH22: =IF(AND(OR($C22=SecCo1,$C22=SecCo2),$L22>SecYear,U22<>0),ROUND(((1-SecShare)*U22)/IF(ABS((1-SecShare)*U22)<1000000,10000,100000),0)*IF(ABS((1-SecShare)*U22)<1000000,10000,100000),U22) -> 4100000 | AI22: =IF(AND(OR($C22=SecCo1,$C22=SecCo2),$L22>SecYear,U22<>0),SecShare*$P22,0) -> 1750000 | AJ22: =$P22-AI22 -> 5250000
A23: G-02 | B23: Growth | C23: V-01 | D23: 1 | E23: Breakout (V-01) | F23: follow_on | G23: 5000000 | H23: 400000000 | I23: 0 | J23: 4 | L23: 8 | M23: 0.01 | N23: 1200000000 | P23: =G23+I23 -> 5000000 | Q23: =P23/D23 -> 5000000 | R23: =ROUND(G23/D23/H23,3) -> 0.013 | S23: =IF(ISNUMBER($O23),ROUND(($O23*$P23)/IF(ABS($O23*$P23)<1000000,10000,100000),0)*IF(ABS($O23*$P23)<1000000,10000,100000),ROUND(($M23*IF(ISNUMBER(CapTarget),MIN($N23,CapTarget),$N23))/IF(ABS($M23*IF(ISNUMBER(CapTarget),MIN($N23,CapTarget),$N23))<1000000,10000,100000),0)*IF(ABS($M23*IF(ISNUMBER(CapTarget),MIN($N23,CapTarget),$N23))<1000000,10000,100000)) -> 12000000 | T23: =IF(ISNUMBER($O23),ROUND(($O23*$P23)/IF(ABS($O23*$P23)<1000000,10000,100000),0)*IF(ABS($O23*$P23)<1000000,10000,100000),ROUND(($M23*IF(ISNUMBER(CapBase),MIN($N23,CapBase),$N23))/IF(ABS($M23*IF(ISNUMBER(CapBase),MIN($N23,CapBase),$N23))<1000000,10000,100000),0)*IF(ABS($M23*IF(ISNUMBER(CapBase),MIN($N23,CapBase),$N23))<1000000,10000,100000)) -> 5000000 | U23: =IF(ISNUMBER($O23),ROUND(($O23*$P23)/IF(ABS($O23*$P23)<1000000,10000,100000),0)*IF(ABS($O23*$P23)<1000000,10000,100000),ROUND(($M23*IF(ISNUMBER(CapStress),MIN($N23,CapStress),$N23))/IF(ABS($M23*IF(ISNUMBER(CapStress),MIN($N23,CapStress),$N23))<1000000,10000,100000),0)*IF(ABS($M23*IF(ISNUMBER(CapStress),MIN($N23,CapStress),$N23))<1000000,10000,100000)) -> 2500000 | V23: =ROUND(S23/$P23,1) -> 2.4 | W23: =ROUND(T23/$P23,1) -> 1 | X23: =ROUND(U23/$P23,1) -> 0.5 | Y23: =IF(AND(OR($C23=SecCo1,$C23=SecCo2),$L23>SecYear,S23<>0),ROUND((SecShare*SecPrice*S23)/IF(ABS(SecShare*SecPrice*S23)<1000000,10000,100000),0)*IF(ABS(SecShare*SecPrice*S23)<1000000,10000,100000),0) -> 1800000 | Z23: =IF(AND(OR($C23=SecCo1,$C23=SecCo2),$L23>SecYear,S23<>0),ROUND(((1-SecShare)*S23)/IF(ABS((1-SecShare)*S23)<1000000,10000,100000),0)*IF(ABS((1-SecShare)*S23)<1000000,10000,100000),S23) -> 9000000 | AA23: =IF(AND(OR($C23=SecCo1,$C23=SecCo2),$L23>SecYear,S23<>0),SecShare*$P23,0) -> 1250000 | AB23: =$P23-AA23 -> 3750000 | AC23: =IF(AND(OR($C23=SecCo1,$C23=SecCo2),$L23>SecYear,T23<>0),ROUND((SecShare*SecPrice*T23)/IF(ABS(SecShare*SecPrice*T23)<1000000,10000,100000),0)*IF(ABS(SecShare*SecPrice*T23)<1000000,10000,100000),0) -> 750000 | AD23: =IF(AND(OR($C23=SecCo1,$C23=SecCo2),$L23>SecYear,T23<>0),ROUND(((1-SecShare)*T23)/IF(ABS((1-SecShare)*T23)<1000000,10000,100000),0)*IF(ABS((1-SecShare)*T23)<1000000,10000,100000),T23) -> 3800000 | AE23: =IF(AND(OR($C23=SecCo1,$C23=SecCo2),$L23>SecYear,T23<>0),SecShare*$P23,0) -> 1250000 | AF23: =$P23-AE23 -> 3750000 | AG23: =IF(AND(OR($C23=SecCo1,$C23=SecCo2),$L23>SecYear,U23<>0),ROUND((SecShare*SecPrice*U23)/IF(ABS(SecShare*SecPrice*U23)<1000000,10000,100000),0)*IF(ABS(SecShare*SecPrice*U23)<1000000,10000,100000),0) -> 380000 | AH23: =IF(AND(OR($C23=SecCo1,$C23=SecCo2),$L23>SecYear,U23<>0),ROUND(((1-SecShare)*U23)/IF(ABS((1-SecShare)*U23)<1000000,10000,100000),0)*IF(ABS((1-SecShare)*U23)<1000000,10000,100000),U23) -> 1900000 | AI23: =IF(AND(OR($C23=SecCo1,$C23=SecCo2),$L23>SecYear,U23<>0),SecShare*$P23,0) -> 1250000 | AJ23: =$P23-AI23 -> 3750000
A24: G-03 | B24: Growth | C24: S-02 | D24: 1 | E24: Breakout (S-02) | F24: follow_on | G24: 5000000 | H24: 150000000 | I24: 0 | J24: 3 | L24: 7 | M24: 0.028 | N24: 600000000 | P24: =G24+I24 -> 5000000 | Q24: =P24/D24 -> 5000000 | R24: =ROUND(G24/D24/H24,3) -> 0.033 | S24: =IF(ISNUMBER($O24),ROUND(($O24*$P24)/IF(ABS($O24*$P24)<1000000,10000,100000),0)*IF(ABS($O24*$P24)<1000000,10000,100000),ROUND(($M24*IF(ISNUMBER(CapTarget),MIN($N24,CapTarget),$N24))/IF(ABS($M24*IF(ISNUMBER(CapTarget),MIN($N24,CapTarget),$N24))<1000000,10000,100000),0)*IF(ABS($M24*IF(ISNUMBER(CapTarget),MIN($N24,CapTarget),$N24))<1000000,10000,100000)) -> 16800000 | T24: =IF(ISNUMBER($O24),ROUND(($O24*$P24)/IF(ABS($O24*$P24)<1000000,10000,100000),0)*IF(ABS($O24*$P24)<1000000,10000,100000),ROUND(($M24*IF(ISNUMBER(CapBase),MIN($N24,CapBase),$N24))/IF(ABS($M24*IF(ISNUMBER(CapBase),MIN($N24,CapBase),$N24))<1000000,10000,100000),0)*IF(ABS($M24*IF(ISNUMBER(CapBase),MIN($N24,CapBase),$N24))<1000000,10000,100000)) -> 14000000 | U24: =IF(ISNUMBER($O24),ROUND(($O24*$P24)/IF(ABS($O24*$P24)<1000000,10000,100000),0)*IF(ABS($O24*$P24)<1000000,10000,100000),ROUND(($M24*IF(ISNUMBER(CapStress),MIN($N24,CapStress),$N24))/IF(ABS($M24*IF(ISNUMBER(CapStress),MIN($N24,CapStress),$N24))<1000000,10000,100000),0)*IF(ABS($M24*IF(ISNUMBER(CapStress),MIN($N24,CapStress),$N24))<1000000,10000,100000)) -> 7000000 | V24: =ROUND(S24/$P24,1) -> 3.4 | W24: =ROUND(T24/$P24,1) -> 2.8 | X24: =ROUND(U24/$P24,1) -> 1.4 | Y24: =IF(AND(OR($C24=SecCo1,$C24=SecCo2),$L24>SecYear,S24<>0),ROUND((SecShare*SecPrice*S24)/IF(ABS(SecShare*SecPrice*S24)<1000000,10000,100000),0)*IF(ABS(SecShare*SecPrice*S24)<1000000,10000,100000),0) -> 0 | Z24: =IF(AND(OR($C24=SecCo1,$C24=SecCo2),$L24>SecYear,S24<>0),ROUND(((1-SecShare)*S24)/IF(ABS((1-SecShare)*S24)<1000000,10000,100000),0)*IF(ABS((1-SecShare)*S24)<1000000,10000,100000),S24) -> 16800000 | AA24: =IF(AND(OR($C24=SecCo1,$C24=SecCo2),$L24>SecYear,S24<>0),SecShare*$P24,0) -> 0 | AB24: =$P24-AA24 -> 5000000 | AC24: =IF(AND(OR($C24=SecCo1,$C24=SecCo2),$L24>SecYear,T24<>0),ROUND((SecShare*SecPrice*T24)/IF(ABS(SecShare*SecPrice*T24)<1000000,10000,100000),0)*IF(ABS(SecShare*SecPrice*T24)<1000000,10000,100000),0) -> 0 | AD24: =IF(AND(OR($C24=SecCo1,$C24=SecCo2),$L24>SecYear,T24<>0),ROUND(((1-SecShare)*T24)/IF(ABS((1-SecShare)*T24)<1000000,10000,100000),0)*IF(ABS((1-SecShare)*T24)<1000000,10000,100000),T24) -> 14000000 | AE24: =IF(AND(OR($C24=SecCo1,$C24=SecCo2),$L24>SecYear,T24<>0),SecShare*$P24,0) -> 0 | AF24: =$P24-AE24 -> 5000000 | AG24: =IF(AND(OR($C24=SecCo1,$C24=SecCo2),$L24>SecYear,U24<>0),ROUND((SecShare*SecPrice*U24)/IF(ABS(SecShare*SecPrice*U24)<1000000,10000,100000),0)*IF(ABS(SecShare*SecPrice*U24)<1000000,10000,100000),0) -> 0 | AH24: =IF(AND(OR($C24=SecCo1,$C24=SecCo2),$L24>SecYear,U24<>0),ROUND(((1-SecShare)*U24)/IF(ABS((1-SecShare)*U24)<1000000,10000,100000),0)*IF(ABS((1-SecShare)*U24)<1000000,10000,100000),U24) -> 7000000 | AI24: =IF(AND(OR($C24=SecCo1,$C24=SecCo2),$L24>SecYear,U24<>0),SecShare*$P24,0) -> 0 | AJ24: =$P24-AI24 -> 5000000
A25: G-07 | B25: Growth | C25: G-07 | D25: 1 | E25: Direct growth entry | F25: new | G25: 6000000 | H25: 250000000 | I25: 0 | J25: 2 | L25: 6 | M25: 0.021 | N25: 1000000000 | P25: =G25+I25 -> 6000000 | Q25: =P25/D25 -> 6000000 | R25: =ROUND(G25/D25/H25,3) -> 0.024 | S25: =IF(ISNUMBER($O25),ROUND(($O25*$P25)/IF(ABS($O25*$P25)<1000000,10000,100000),0)*IF(ABS($O25*$P25)<1000000,10000,100000),ROUND(($M25*IF(ISNUMBER(CapTarget),MIN($N25,CapTarget),$N25))/IF(ABS($M25*IF(ISNUMBER(CapTarget),MIN($N25,CapTarget),$N25))<1000000,10000,100000),0)*IF(ABS($M25*IF(ISNUMBER(CapTarget),MIN($N25,CapTarget),$N25))<1000000,10000,100000)) -> 21000000 | T25: =IF(ISNUMBER($O25),ROUND(($O25*$P25)/IF(ABS($O25*$P25)<1000000,10000,100000),0)*IF(ABS($O25*$P25)<1000000,10000,100000),ROUND(($M25*IF(ISNUMBER(CapBase),MIN($N25,CapBase),$N25))/IF(ABS($M25*IF(ISNUMBER(CapBase),MIN($N25,CapBase),$N25))<1000000,10000,100000),0)*IF(ABS($M25*IF(ISNUMBER(CapBase),MIN($N25,CapBase),$N25))<1000000,10000,100000)) -> 10500000 | U25: =IF(ISNUMBER($O25),ROUND(($O25*$P25)/IF(ABS($O25*$P25)<1000000,10000,100000),0)*IF(ABS($O25*$P25)<1000000,10000,100000),ROUND(($M25*IF(ISNUMBER(CapStress),MIN($N25,CapStress),$N25))/IF(ABS($M25*IF(ISNUMBER(CapStress),MIN($N25,CapStress),$N25))<1000000,10000,100000),0)*IF(ABS($M25*IF(ISNUMBER(CapStress),MIN($N25,CapStress),$N25))<1000000,10000,100000)) -> 5300000 | V25: =ROUND(S25/$P25,1) -> 3.5 | W25: =ROUND(T25/$P25,1) -> 1.8 | X25: =ROUND(U25/$P25,1) -> 0.9 | Y25: =IF(AND(OR($C25=SecCo1,$C25=SecCo2),$L25>SecYear,S25<>0),ROUND((SecShare*SecPrice*S25)/IF(ABS(SecShare*SecPrice*S25)<1000000,10000,100000),0)*IF(ABS(SecShare*SecPrice*S25)<1000000,10000,100000),0) -> 0 | Z25: =IF(AND(OR($C25=SecCo1,$C25=SecCo2),$L25>SecYear,S25<>0),ROUND(((1-SecShare)*S25)/IF(ABS((1-SecShare)*S25)<1000000,10000,100000),0)*IF(ABS((1-SecShare)*S25)<1000000,10000,100000),S25) -> 21000000 | AA25: =IF(AND(OR($C25=SecCo1,$C25=SecCo2),$L25>SecYear,S25<>0),SecShare*$P25,0) -> 0 | AB25: =$P25-AA25 -> 6000000 | AC25: =IF(AND(OR($C25=SecCo1,$C25=SecCo2),$L25>SecYear,T25<>0),ROUND((SecShare*SecPrice*T25)/IF(ABS(SecShare*SecPrice*T25)<1000000,10000,100000),0)*IF(ABS(SecShare*SecPrice*T25)<1000000,10000,100000),0) -> 0 | AD25: =IF(AND(OR($C25=SecCo1,$C25=SecCo2),$L25>SecYear,T25<>0),ROUND(((1-SecShare)*T25)/IF(ABS((1-SecShare)*T25)<1000000,10000,100000),0)*IF(ABS((1-SecShare)*T25)<1000000,10000,100000),T25) -> 10500000 | AE25: =IF(AND(OR($C25=SecCo1,$C25=SecCo2),$L25>SecYear,T25<>0),SecShare*$P25,0) -> 0 | AF25: =$P25-AE25 -> 6000000 | AG25: =IF(AND(OR($C25=SecCo1,$C25=SecCo2),$L25>SecYear,U25<>0),ROUND((SecShare*SecPrice*U25)/IF(ABS(SecShare*SecPrice*U25)<1000000,10000,100000),0)*IF(ABS(SecShare*SecPrice*U25)<1000000,10000,100000),0) -> 0 | AH25: =IF(AND(OR($C25=SecCo1,$C25=SecCo2),$L25>SecYear,U25<>0),ROUND(((1-SecShare)*U25)/IF(ABS((1-SecShare)*U25)<1000000,10000,100000),0)*IF(ABS((1-SecShare)*U25)<1000000,10000,100000),U25) -> 5300000 | AI25: =IF(AND(OR($C25=SecCo1,$C25=SecCo2),$L25>SecYear,U25<>0),SecShare*$P25,0) -> 0 | AJ25: =$P25-AI25 -> 6000000
A26: G-08 | B26: Growth | C26: G-08 | D26: 1 | E26: Direct growth entry | F26: new | G26: 5000000 | H26: 250000000 | I26: 0 | J26: 3 | L26: 7 | M26: 0.017 | N26: 900000000 | P26: =G26+I26 -> 5000000 | Q26: =P26/D26 -> 5000000 | R26: =ROUND(G26/D26/H26,3) -> 0.02 | S26: =IF(ISNUMBER($O26),ROUND(($O26*$P26)/IF(ABS($O26*$P26)<1000000,10000,100000),0)*IF(ABS($O26*$P26)<1000000,10000,100000),ROUND(($M26*IF(ISNUMBER(CapTarget),MIN($N26,CapTarget),$N26))/IF(ABS($M26*IF(ISNUMBER(CapTarget),MIN($N26,CapTarget),$N26))<1000000,10000,100000),0)*IF(ABS($M26*IF(ISNUMBER(CapTarget),MIN($N26,CapTarget),$N26))<1000000,10000,100000)) -> 15300000 | T26: =IF(ISNUMBER($O26),ROUND(($O26*$P26)/IF(ABS($O26*$P26)<1000000,10000,100000),0)*IF(ABS($O26*$P26)<1000000,10000,100000),ROUND(($M26*IF(ISNUMBER(CapBase),MIN($N26,CapBase),$N26))/IF(ABS($M26*IF(ISNUMBER(CapBase),MIN($N26,CapBase),$N26))<1000000,10000,100000),0)*IF(ABS($M26*IF(ISNUMBER(CapBase),MIN($N26,CapBase),$N26))<1000000,10000,100000)) -> 8500000 | U26: =IF(ISNUMBER($O26),ROUND(($O26*$P26)/IF(ABS($O26*$P26)<1000000,10000,100000),0)*IF(ABS($O26*$P26)<1000000,10000,100000),ROUND(($M26*IF(ISNUMBER(CapStress),MIN($N26,CapStress),$N26))/IF(ABS($M26*IF(ISNUMBER(CapStress),MIN($N26,CapStress),$N26))<1000000,10000,100000),0)*IF(ABS($M26*IF(ISNUMBER(CapStress),MIN($N26,CapStress),$N26))<1000000,10000,100000)) -> 4300000 | V26: =ROUND(S26/$P26,1) -> 3.1 | W26: =ROUND(T26/$P26,1) -> 1.7 | X26: =ROUND(U26/$P26,1) -> 0.9 | Y26: =IF(AND(OR($C26=SecCo1,$C26=SecCo2),$L26>SecYear,S26<>0),ROUND((SecShare*SecPrice*S26)/IF(ABS(SecShare*SecPrice*S26)<1000000,10000,100000),0)*IF(ABS(SecShare*SecPrice*S26)<1000000,10000,100000),0) -> 0 | Z26: =IF(AND(OR($C26=SecCo1,$C26=SecCo2),$L26>SecYear,S26<>0),ROUND(((1-SecShare)*S26)/IF(ABS((1-SecShare)*S26)<1000000,10000,100000),0)*IF(ABS((1-SecShare)*S26)<1000000,10000,100000),S26) -> 15300000 | AA26: =IF(AND(OR($C26=SecCo1,$C26=SecCo2),$L26>SecYear,S26<>0),SecShare*$P26,0) -> 0 | AB26: =$P26-AA26 -> 5000000 | AC26: =IF(AND(OR($C26=SecCo1,$C26=SecCo2),$L26>SecYear,T26<>0),ROUND((SecShare*SecPrice*T26)/IF(ABS(SecShare*SecPrice*T26)<1000000,10000,100000),0)*IF(ABS(SecShare*SecPrice*T26)<1000000,10000,100000),0) -> 0 | AD26: =IF(AND(OR($C26=SecCo1,$C26=SecCo2),$L26>SecYear,T26<>0),ROUND(((1-SecShare)*T26)/IF(ABS((1-SecShare)*T26)<1000000,10000,100000),0)*IF(ABS((1-SecShare)*T26)<1000000,10000,100000),T26) -> 8500000 | AE26: =IF(AND(OR($C26=SecCo1,$C26=SecCo2),$L26>SecYear,T26<>0),SecShare*$P26,0) -> 0 | AF26: =$P26-AE26 -> 5000000 | AG26: =IF(AND(OR($C26=SecCo1,$C26=SecCo2),$L26>SecYear,U26<>0),ROUND((SecShare*SecPrice*U26)/IF(ABS(SecShare*SecPrice*U26)<1000000,10000,100000),0)*IF(ABS(SecShare*SecPrice*U26)<1000000,10000,100000),0) -> 0 | AH26: =IF(AND(OR($C26=SecCo1,$C26=SecCo2),$L26>SecYear,U26<>0),ROUND(((1-SecShare)*U26)/IF(ABS((1-SecShare)*U26)<1000000,10000,100000),0)*IF(ABS((1-SecShare)*U26)<1000000,10000,100000),U26) -> 4300000 | AI26: =IF(AND(OR($C26=SecCo1,$C26=SecCo2),$L26>SecYear,U26<>0),SecShare*$P26,0) -> 0 | AJ26: =$P26-AI26 -> 5000000
A27: G-09 | B27: Growth | C27: G-09 | D27: 1 | E27: Downside, preference | F27: new | G27: 5000000 | H27: 200000000 | I27: 0 | J27: 3 | L27: 7 | O27: 0.8 | P27: =G27+I27 -> 5000000 | Q27: =P27/D27 -> 5000000 | R27: =ROUND(G27/D27/H27,3) -> 0.025 | S27: =IF(ISNUMBER($O27),ROUND(($O27*$P27)/IF(ABS($O27*$P27)<1000000,10000,100000),0)*IF(ABS($O27*$P27)<1000000,10000,100000),ROUND(($M27*IF(ISNUMBER(CapTarget),MIN($N27,CapTarget),$N27))/IF(ABS($M27*IF(ISNUMBER(CapTarget),MIN($N27,CapTarget),$N27))<1000000,10000,100000),0)*IF(ABS($M27*IF(ISNUMBER(CapTarget),MIN($N27,CapTarget),$N27))<1000000,10000,100000)) -> 4000000 | T27: =IF(ISNUMBER($O27),ROUND(($O27*$P27)/IF(ABS($O27*$P27)<1000000,10000,100000),0)*IF(ABS($O27*$P27)<1000000,10000,100000),ROUND(($M27*IF(ISNUMBER(CapBase),MIN($N27,CapBase),$N27))/IF(ABS($M27*IF(ISNUMBER(CapBase),MIN($N27,CapBase),$N27))<1000000,10000,100000),0)*IF(ABS($M27*IF(ISNUMBER(CapBase),MIN($N27,CapBase),$N27))<1000000,10000,100000)) -> 4000000 | U27: =IF(ISNUMBER($O27),ROUND(($O27*$P27)/IF(ABS($O27*$P27)<1000000,10000,100000),0)*IF(ABS($O27*$P27)<1000000,10000,100000),ROUND(($M27*IF(ISNUMBER(CapStress),MIN($N27,CapStress),$N27))/IF(ABS($M27*IF(ISNUMBER(CapStress),MIN($N27,CapStress),$N27))<1000000,10000,100000),0)*IF(ABS($M27*IF(ISNUMBER(CapStress),MIN($N27,CapStress),$N27))<1000000,10000,100000)) -> 4000000 | V27: =ROUND(S27/$P27,1) -> 0.8 | W27: =ROUND(T27/$P27,1) -> 0.8 | X27: =ROUND(U27/$P27,1) -> 0.8 | Y27: =IF(AND(OR($C27=SecCo1,$C27=SecCo2),$L27>SecYear,S27<>0),ROUND((SecShare*SecPrice*S27)/IF(ABS(SecShare*SecPrice*S27)<1000000,10000,100000),0)*IF(ABS(SecShare*SecPrice*S27)<1000000,10000,100000),0) -> 0 | Z27: =IF(AND(OR($C27=SecCo1,$C27=SecCo2),$L27>SecYear,S27<>0),ROUND(((1-SecShare)*S27)/IF(ABS((1-SecShare)*S27)<1000000,10000,100000),0)*IF(ABS((1-SecShare)*S27)<1000000,10000,100000),S27) -> 4000000 | AA27: =IF(AND(OR($C27=SecCo1,$C27=SecCo2),$L27>SecYear,S27<>0),SecShare*$P27,0) -> 0 | AB27: =$P27-AA27 -> 5000000 | AC27: =IF(AND(OR($C27=SecCo1,$C27=SecCo2),$L27>SecYear,T27<>0),ROUND((SecShare*SecPrice*T27)/IF(ABS(SecShare*SecPrice*T27)<1000000,10000,100000),0)*IF(ABS(SecShare*SecPrice*T27)<1000000,10000,100000),0) -> 0 | AD27: =IF(AND(OR($C27=SecCo1,$C27=SecCo2),$L27>SecYear,T27<>0),ROUND(((1-SecShare)*T27)/IF(ABS((1-SecShare)*T27)<1000000,10000,100000),0)*IF(ABS((1-SecShare)*T27)<1000000,10000,100000),T27) -> 4000000 | AE27: =IF(AND(OR($C27=SecCo1,$C27=SecCo2),$L27>SecYear,T27<>0),SecShare*$P27,0) -> 0 | AF27: =$P27-AE27 -> 5000000 | AG27: =IF(AND(OR($C27=SecCo1,$C27=SecCo2),$L27>SecYear,U27<>0),ROUND((SecShare*SecPrice*U27)/IF(ABS(SecShare*SecPrice*U27)<1000000,10000,100000),0)*IF(ABS(SecShare*SecPrice*U27)<1000000,10000,100000),0) -> 0 | AH27: =IF(AND(OR($C27=SecCo1,$C27=SecCo2),$L27>SecYear,U27<>0),ROUND(((1-SecShare)*U27)/IF(ABS((1-SecShare)*U27)<1000000,10000,100000),0)*IF(ABS((1-SecShare)*U27)<1000000,10000,100000),U27) -> 4000000 | AI27: =IF(AND(OR($C27=SecCo1,$C27=SecCo2),$L27>SecYear,U27<>0),SecShare*$P27,0) -> 0 | AJ27: =$P27-AI27 -> 5000000
A28: SUB | E28: (Growth) | G28: =SUM(G22:G27) -> 33000000 | I28: =SUM(I22:I27) -> 0 | P28: =SUM(P22:P27) -> 33000000 | S28: =SUM(S22:S27) -> 102100000 | T28: =SUM(T22:T27) -> 53000000 | U28: =SUM(U22:U27) -> 28600000 | V28: =ROUND(S28/P28,1) -> 3.1 | W28: =ROUND(T28/P28,1) -> 1.6 | X28: =ROUND(U28/P28,1) -> 0.9
A29: TOTAL | G29: =G14+G21+G28 -> 66000000 | I29: =I14+I21+I28 -> 17900000 | P29: =P14+P21+P28 -> 83900000 | S29: =S14+S21+S28 -> 324300000 | T29: =T14+T21+T28 -> 190700000 | U29: =U14+U21+U28 -> 115800000 | V29: =ROUND(S29/P29,1) -> 3.9 | W29: =ROUND(T29/P29,1) -> 2.3 | X29: =ROUND(U29/P29,1) -> 1.4
A31: Proceeds = exit stake × exit value (capped in Base and Stress), or recovery multiple × invested; rounded to EUR 10K below EUR 1M and EUR 100K above, before any sum. Proceeds are shown at exit value; the year-6 partial secondary sale is in the helpers and the Cash flows tab.

Sheet Construction
A1: Portfolio construction
A2: Per layer, capital allocation, reserve policy and exposure per company.
A4: Portfolio by layer
A5: Layer | B5: Companies (new entries) | C5: Positions (lines) | D5: Initial tickets | E5: Follow-on | F5: Invested | G5: Of which in our breakouts | H5: Direct entries | I5: Proceeds · Target | J5: Proceeds · Base | K5: Proceeds · Stress | L5: Gross MOIC · Target | M5: Gross MOIC · Base | N5: Gross MOIC · Stress
A6: Seed | B6: =SUMIFS(Lines!$D$6:$D$28,Lines!$B$6:$B$28,"Seed",Lines!$F$6:$F$28,"new") -> 18 | C6: =COUNTIF(Lines!$B$6:$B$28,"Seed") -> 8 | D6: =SUMIF(Lines!$B$6:$B$28,"Seed",Lines!$G$6:$G$28) -> 9000000 | E6: =SUMIF(Lines!$B$6:$B$28,"Seed",Lines!$I$6:$I$28) -> 7500000 | F6: =SUMIF(Lines!$B$6:$B$28,"Seed",Lines!$P$6:$P$28) -> 16500000 | G6: =SUMIFS(Lines!$P$6:$P$28,Lines!$B$6:$B$28,"Seed",Lines!$F$6:$F$28,"follow_on") -> 0 | H6: =ROUND((F6-G6)/F6,2) -> 1 | I6: =SUMIF(Lines!$B$6:$B$28,"Seed",Lines!$S$6:$S$28) -> 110200000 | J6: =SUMIF(Lines!$B$6:$B$28,"Seed",Lines!$T$6:$T$28) -> 61700000 | K6: =SUMIF(Lines!$B$6:$B$28,"Seed",Lines!$U$6:$U$28) -> 40300000 | L6: =ROUND(I6/F6,1) -> 6.7 | M6: =ROUND(J6/F6,1) -> 3.7 | N6: =ROUND(K6/F6,1) -> 2.4
A7: Venture | B7: =SUMIFS(Lines!$D$6:$D$28,Lines!$B$6:$B$28,"Venture",Lines!$F$6:$F$28,"new") -> 8 | C7: =COUNTIF(Lines!$B$6:$B$28,"Venture") -> 6 | D7: =SUMIF(Lines!$B$6:$B$28,"Venture",Lines!$G$6:$G$28) -> 24000000 | E7: =SUMIF(Lines!$B$6:$B$28,"Venture",Lines!$I$6:$I$28) -> 10400000 | F7: =SUMIF(Lines!$B$6:$B$28,"Venture",Lines!$P$6:$P$28) -> 34400000 | G7: =SUMIFS(Lines!$P$6:$P$28,Lines!$B$6:$B$28,"Venture",Lines!$F$6:$F$28,"follow_on") -> 0 | H7: =ROUND((F7-G7)/F7,2) -> 1 | I7: =SUMIF(Lines!$B$6:$B$28,"Venture",Lines!$S$6:$S$28) -> 112000000 | J7: =SUMIF(Lines!$B$6:$B$28,"Venture",Lines!$T$6:$T$28) -> 76000000 | K7: =SUMIF(Lines!$B$6:$B$28,"Venture",Lines!$U$6:$U$28) -> 46900000 | L7: =ROUND(I7/F7,1) -> 3.3 | M7: =ROUND(J7/F7,1) -> 2.2 | N7: =ROUND(K7/F7,1) -> 1.4
A8: Growth | B8: =SUMIFS(Lines!$D$6:$D$28,Lines!$B$6:$B$28,"Growth",Lines!$F$6:$F$28,"new") -> 3 | C8: =COUNTIF(Lines!$B$6:$B$28,"Growth") -> 6 | D8: =SUMIF(Lines!$B$6:$B$28,"Growth",Lines!$G$6:$G$28) -> 33000000 | E8: =SUMIF(Lines!$B$6:$B$28,"Growth",Lines!$I$6:$I$28) -> 0 | F8: =SUMIF(Lines!$B$6:$B$28,"Growth",Lines!$P$6:$P$28) -> 33000000 | G8: =SUMIFS(Lines!$P$6:$P$28,Lines!$B$6:$B$28,"Growth",Lines!$F$6:$F$28,"follow_on") -> 17000000 | H8: =ROUND((F8-G8)/F8,2) -> 0.48 | I8: =SUMIF(Lines!$B$6:$B$28,"Growth",Lines!$S$6:$S$28) -> 102100000 | J8: =SUMIF(Lines!$B$6:$B$28,"Growth",Lines!$T$6:$T$28) -> 53000000 | K8: =SUMIF(Lines!$B$6:$B$28,"Growth",Lines!$U$6:$U$28) -> 28600000 | L8: =ROUND(I8/F8,1) -> 3.1 | M8: =ROUND(J8/F8,1) -> 1.6 | N8: =ROUND(K8/F8,1) -> 0.9
A9: Total | B9: =SUM(B6:B8) -> 29 | C9: =SUM(C6:C8) -> 20 | D9: =SUM(D6:D8) -> 66000000 | E9: =SUM(E6:E8) -> 17900000 | F9: =SUM(F6:F8) -> 83900000 | G9: =SUM(G6:G8) -> 17000000 | H9: =ROUND((F9-G9)/F9,2) -> 0.8 | I9: =SUM(I6:I8) -> 324300000 | J9: =SUM(J6:J8) -> 190700000 | K9: =SUM(K6:K8) -> 115800000 | L9: =ROUND(I9/F9,1) -> 3.9 | M9: =ROUND(J9/F9,1) -> 2.3 | N9: =ROUND(K9/F9,1) -> 1.4
A12: Capital allocation
A13: Seed — invested | B13: =F6 -> 16500000
A14: Venture — invested | B14: =F7 -> 34400000
A15: Growth — invested | B15: =F8 -> 33000000
A16: Invested | B16: =B13+B14+B15 -> 83900000
A17: of which initial tickets in new companies | B17: =SUMIFS(Lines!$G$6:$G$28,Lines!$F$6:$F$28,"new") -> 49000000
A18: of which follow-ons (reserves and our breakouts) | B18: =B16-B17 -> 34900000
A19: follow-on share of invested capital | B19: =ROUND(B18/B16,2) -> 0.42
A20: Management fees (Target case) | B20: ='Cash flows'!$B$43 -> 12100000
A21: Fund expenses, incl. set-up (Target case) | B21: ='Cash flows'!$B$44 -> 3900000
A22: Contingency | B22: =ROUND((Commitments-B16-B20-B21)/IF(ABS(Commitments-B16-B20-B21)<1000000,10000,100000),0)*IF(ABS(Commitments-B16-B20-B21)<1000000,10000,100000) -> 100000
A23: Total commitments | B23: =Commitments -> 100000000
A26: Follow-on reserves vs policy (expected value)
A27: Layer | B27: Companies | C27: Expected follow-on | D27: Modelled follow-on | E27: Gap | F27: Within 5%
A28: Seed | B28: =B6 -> 18 | C28: =ROUND((B28*ResSeed_graduation_pct*ResSeed_pro_rata_pct*ResSeed_next_round+ResSeed_bridges)/IF(ABS(B28*ResSeed_graduation_pct*ResSeed_pro_rata_pct*ResSeed_next_round+ResSeed_bridges)<1000000,10000,100000),0)*IF(ABS(B28*ResSeed_graduation_pct*ResSeed_pro_rata_pct*ResSeed_next_round+ResSeed_bridges)<1000000,10000,100000) -> 7500000 | D28: =E6 -> 7500000 | E28: =D28-C28 -> 0 | F28: =IF(ABS(E28)<=0.05*C28,"OK","CHECK") -> OK
A29: Venture | B29: =B7 -> 8 | C29: =ROUND((B29*ResVenture_graduation_pct*ResVenture_pro_rata_pct*ResVenture_next_round+ResVenture_bridges)/IF(ABS(B29*ResVenture_graduation_pct*ResVenture_pro_rata_pct*ResVenture_next_round+ResVenture_bridges)<1000000,10000,100000),0)*IF(ABS(B29*ResVenture_graduation_pct*ResVenture_pro_rata_pct*ResVenture_next_round+ResVenture_bridges)<1000000,10000,100000) -> 10400000 | D29: =E7 -> 10400000 | E29: =D29-C29 -> 0 | F29: =IF(ABS(E29)<=0.05*C29,"OK","CHECK") -> OK
A32: Exposure per company (all lines, per company) and fund returner
A33: Company | B33: Invested by the fund | C33: Cap from the fund | D33: Within cap | E33: Proceeds · Target (all lines) | F33: SPV top-up to the max per company
A34: S-01 | B34: =ROUND((SUMIF(Lines!$C$6:$C$28,A34,Lines!$Q$6:$Q$28))/IF(ABS(SUMIF(Lines!$C$6:$C$28,A34,Lines!$Q$6:$Q$28))<1000000,10000,100000),0)*IF(ABS(SUMIF(Lines!$C$6:$C$28,A34,Lines!$Q$6:$Q$28))<1000000,10000,100000) -> 10000000 | C34: =CompanyCap -> 10000000 | D34: =IF(SUMIF(Lines!$C$6:$C$28,A34,Lines!$Q$6:$Q$28)<=C34+1,"OK","CHECK") -> OK | E34: =SUMIF(Lines!$C$6:$C$28,A34,Lines!$S$6:$S$28) -> 100500000 | F34: =ROUND((CompanyMaxSPV-SUMIF(Lines!$C$6:$C$28,A34,Lines!$Q$6:$Q$28))/IF(ABS(CompanyMaxSPV-SUMIF(Lines!$C$6:$C$28,A34,Lines!$Q$6:$Q$28))<1000000,10000,100000),0)*IF(ABS(CompanyMaxSPV-SUMIF(Lines!$C$6:$C$28,A34,Lines!$Q$6:$Q$28))<1000000,10000,100000) -> 5000000
A35: S-02 | B35: =ROUND((SUMIF(Lines!$C$6:$C$28,A35,Lines!$Q$6:$Q$28))/IF(ABS(SUMIF(Lines!$C$6:$C$28,A35,Lines!$Q$6:$Q$28))<1000000,10000,100000),0)*IF(ABS(SUMIF(Lines!$C$6:$C$28,A35,Lines!$Q$6:$Q$28))<1000000,10000,100000) -> 7300000 | C35: =CompanyCap -> 10000000 | D35: =IF(SUMIF(Lines!$C$6:$C$28,A35,Lines!$Q$6:$Q$28)<=C35+1,"OK","CHECK") -> OK | E35: =SUMIF(Lines!$C$6:$C$28,A35,Lines!$S$6:$S$28) -> 37800000
A36: S-03 | B36: =ROUND((SUMIF(Lines!$C$6:$C$28,A36,Lines!$Q$6:$Q$28))/IF(ABS(SUMIF(Lines!$C$6:$C$28,A36,Lines!$Q$6:$Q$28))<1000000,10000,100000),0)*IF(ABS(SUMIF(Lines!$C$6:$C$28,A36,Lines!$Q$6:$Q$28))<1000000,10000,100000) -> 1800000 | C36: =CompanyCap -> 10000000 | D36: =IF(SUMIF(Lines!$C$6:$C$28,A36,Lines!$Q$6:$Q$28)<=C36+1,"OK","CHECK") -> OK | E36: =SUMIF(Lines!$C$6:$C$28,A36,Lines!$S$6:$S$28) -> 9000000
A37: S-04 | B37: =ROUND((SUMIF(Lines!$C$6:$C$28,A37,Lines!$Q$6:$Q$28))/IF(ABS(SUMIF(Lines!$C$6:$C$28,A37,Lines!$Q$6:$Q$28))<1000000,10000,100000),0)*IF(ABS(SUMIF(Lines!$C$6:$C$28,A37,Lines!$Q$6:$Q$28))<1000000,10000,100000) -> 1000000 | C37: =CompanyCap -> 10000000 | D37: =IF(SUMIF(Lines!$C$6:$C$28,A37,Lines!$Q$6:$Q$28)<=C37+1,"OK","CHECK") -> OK | E37: =SUMIF(Lines!$C$6:$C$28,A37,Lines!$S$6:$S$28) -> 7500000
A38: S-05 | B38: =ROUND((SUMIF(Lines!$C$6:$C$28,A38,Lines!$Q$6:$Q$28))/IF(ABS(SUMIF(Lines!$C$6:$C$28,A38,Lines!$Q$6:$Q$28))<1000000,10000,100000),0)*IF(ABS(SUMIF(Lines!$C$6:$C$28,A38,Lines!$Q$6:$Q$28))<1000000,10000,100000) -> 1000000 | C38: =CompanyCap -> 10000000 | D38: =IF(SUMIF(Lines!$C$6:$C$28,A38,Lines!$Q$6:$Q$28)<=C38+1,"OK","CHECK") -> OK | E38: =SUMIF(Lines!$C$6:$C$28,A38,Lines!$S$6:$S$28) -> 2700000
A39: S-06 | B39: =ROUND((SUMIF(Lines!$C$6:$C$28,A39,Lines!$Q$6:$Q$28))/IF(ABS(SUMIF(Lines!$C$6:$C$28,A39,Lines!$Q$6:$Q$28))<1000000,10000,100000),0)*IF(ABS(SUMIF(Lines!$C$6:$C$28,A39,Lines!$Q$6:$Q$28))<1000000,10000,100000) -> 300000 | C39: =CompanyCap -> 10000000 | D39: =IF(SUMIF(Lines!$C$6:$C$28,A39,Lines!$Q$6:$Q$28)<=C39+1,"OK","CHECK") -> OK | E39: =SUMIF(Lines!$C$6:$C$28,A39,Lines!$S$6:$S$28) -> 1600000
A40: S-07 | B40: =ROUND((SUMIF(Lines!$C$6:$C$28,A40,Lines!$Q$6:$Q$28))/IF(ABS(SUMIF(Lines!$C$6:$C$28,A40,Lines!$Q$6:$Q$28))<1000000,10000,100000),0)*IF(ABS(SUMIF(Lines!$C$6:$C$28,A40,Lines!$Q$6:$Q$28))<1000000,10000,100000) -> 600000 | C40: =CompanyCap -> 10000000 | D40: =IF(SUMIF(Lines!$C$6:$C$28,A40,Lines!$Q$6:$Q$28)<=C40+1,"OK","CHECK") -> OK | E40: =SUMIF(Lines!$C$6:$C$28,A40,Lines!$S$6:$S$28) -> 900000
A41: S-10 | B41: =ROUND((SUMIF(Lines!$C$6:$C$28,A41,Lines!$Q$6:$Q$28))/IF(ABS(SUMIF(Lines!$C$6:$C$28,A41,Lines!$Q$6:$Q$28))<1000000,10000,100000),0)*IF(ABS(SUMIF(Lines!$C$6:$C$28,A41,Lines!$Q$6:$Q$28))<1000000,10000,100000) -> 600000 | C41: =CompanyCap -> 10000000 | D41: =IF(SUMIF(Lines!$C$6:$C$28,A41,Lines!$Q$6:$Q$28)<=C41+1,"OK","CHECK") -> OK | E41: =SUMIF(Lines!$C$6:$C$28,A41,Lines!$S$6:$S$28) -> 0
A42: V-01 | B42: =ROUND((SUMIF(Lines!$C$6:$C$28,A42,Lines!$Q$6:$Q$28))/IF(ABS(SUMIF(Lines!$C$6:$C$28,A42,Lines!$Q$6:$Q$28))<1000000,10000,100000),0)*IF(ABS(SUMIF(Lines!$C$6:$C$28,A42,Lines!$Q$6:$Q$28))<1000000,10000,100000) -> 10000000 | C42: =CompanyCap -> 10000000 | D42: =IF(SUMIF(Lines!$C$6:$C$28,A42,Lines!$Q$6:$Q$28)<=C42+1,"OK","CHECK") -> OK | E42: =SUMIF(Lines!$C$6:$C$28,A42,Lines!$S$6:$S$28) -> 66000000 | F42: =ROUND((CompanyMaxSPV-SUMIF(Lines!$C$6:$C$28,A42,Lines!$Q$6:$Q$28))/IF(ABS(CompanyMaxSPV-SUMIF(Lines!$C$6:$C$28,A42,Lines!$Q$6:$Q$28))<1000000,10000,100000),0)*IF(ABS(CompanyMaxSPV-SUMIF(Lines!$C$6:$C$28,A42,Lines!$Q$6:$Q$28))<1000000,10000,100000) -> 5000000
A43: V-02 | B43: =ROUND((SUMIF(Lines!$C$6:$C$28,A43,Lines!$Q$6:$Q$28))/IF(ABS(SUMIF(Lines!$C$6:$C$28,A43,Lines!$Q$6:$Q$28))<1000000,10000,100000),0)*IF(ABS(SUMIF(Lines!$C$6:$C$28,A43,Lines!$Q$6:$Q$28))<1000000,10000,100000) -> 5000000 | C43: =CompanyCap -> 10000000 | D43: =IF(SUMIF(Lines!$C$6:$C$28,A43,Lines!$Q$6:$Q$28)<=C43+1,"OK","CHECK") -> OK | E43: =SUMIF(Lines!$C$6:$C$28,A43,Lines!$S$6:$S$28) -> 27000000
A44: V-03 | B44: =ROUND((SUMIF(Lines!$C$6:$C$28,A44,Lines!$Q$6:$Q$28))/IF(ABS(SUMIF(Lines!$C$6:$C$28,A44,Lines!$Q$6:$Q$28))<1000000,10000,100000),0)*IF(ABS(SUMIF(Lines!$C$6:$C$28,A44,Lines!$Q$6:$Q$28))<1000000,10000,100000) -> 4500000 | C44: =CompanyCap -> 10000000 | D44: =IF(SUMIF(Lines!$C$6:$C$28,A44,Lines!$Q$6:$Q$28)<=C44+1,"OK","CHECK") -> OK | E44: =SUMIF(Lines!$C$6:$C$28,A44,Lines!$S$6:$S$28) -> 18000000
A45: V-04 | B45: =ROUND((SUMIF(Lines!$C$6:$C$28,A45,Lines!$Q$6:$Q$28))/IF(ABS(SUMIF(Lines!$C$6:$C$28,A45,Lines!$Q$6:$Q$28))<1000000,10000,100000),0)*IF(ABS(SUMIF(Lines!$C$6:$C$28,A45,Lines!$Q$6:$Q$28))<1000000,10000,100000) -> 4000000 | C45: =CompanyCap -> 10000000 | D45: =IF(SUMIF(Lines!$C$6:$C$28,A45,Lines!$Q$6:$Q$28)<=C45+1,"OK","CHECK") -> OK | E45: =SUMIF(Lines!$C$6:$C$28,A45,Lines!$S$6:$S$28) -> 10000000
A46: V-05 | B46: =ROUND((SUMIF(Lines!$C$6:$C$28,A46,Lines!$Q$6:$Q$28))/IF(ABS(SUMIF(Lines!$C$6:$C$28,A46,Lines!$Q$6:$Q$28))<1000000,10000,100000),0)*IF(ABS(SUMIF(Lines!$C$6:$C$28,A46,Lines!$Q$6:$Q$28))<1000000,10000,100000) -> 3800000 | C46: =CompanyCap -> 10000000 | D46: =IF(SUMIF(Lines!$C$6:$C$28,A46,Lines!$Q$6:$Q$28)<=C46+1,"OK","CHECK") -> OK | E46: =SUMIF(Lines!$C$6:$C$28,A46,Lines!$S$6:$S$28) -> 3000000
A47: V-07 | B47: =ROUND((SUMIF(Lines!$C$6:$C$28,A47,Lines!$Q$6:$Q$28))/IF(ABS(SUMIF(Lines!$C$6:$C$28,A47,Lines!$Q$6:$Q$28))<1000000,10000,100000),0)*IF(ABS(SUMIF(Lines!$C$6:$C$28,A47,Lines!$Q$6:$Q$28))<1000000,10000,100000) -> 4200000 | C47: =CompanyCap -> 10000000 | D47: =IF(SUMIF(Lines!$C$6:$C$28,A47,Lines!$Q$6:$Q$28)<=C47+1,"OK","CHECK") -> OK | E47: =SUMIF(Lines!$C$6:$C$28,A47,Lines!$S$6:$S$28) -> 0
A48: G-07 | B48: =ROUND((SUMIF(Lines!$C$6:$C$28,A48,Lines!$Q$6:$Q$28))/IF(ABS(SUMIF(Lines!$C$6:$C$28,A48,Lines!$Q$6:$Q$28))<1000000,10000,100000),0)*IF(ABS(SUMIF(Lines!$C$6:$C$28,A48,Lines!$Q$6:$Q$28))<1000000,10000,100000) -> 6000000 | C48: =CompanyCap -> 10000000 | D48: =IF(SUMIF(Lines!$C$6:$C$28,A48,Lines!$Q$6:$Q$28)<=C48+1,"OK","CHECK") -> OK | E48: =SUMIF(Lines!$C$6:$C$28,A48,Lines!$S$6:$S$28) -> 21000000 | F48: =ROUND((CompanyMaxSPV-SUMIF(Lines!$C$6:$C$28,A48,Lines!$Q$6:$Q$28))/IF(ABS(CompanyMaxSPV-SUMIF(Lines!$C$6:$C$28,A48,Lines!$Q$6:$Q$28))<1000000,10000,100000),0)*IF(ABS(CompanyMaxSPV-SUMIF(Lines!$C$6:$C$28,A48,Lines!$Q$6:$Q$28))<1000000,10000,100000) -> 9000000
A49: G-08 | B49: =ROUND((SUMIF(Lines!$C$6:$C$28,A49,Lines!$Q$6:$Q$28))/IF(ABS(SUMIF(Lines!$C$6:$C$28,A49,Lines!$Q$6:$Q$28))<1000000,10000,100000),0)*IF(ABS(SUMIF(Lines!$C$6:$C$28,A49,Lines!$Q$6:$Q$28))<1000000,10000,100000) -> 5000000 | C49: =CompanyCap -> 10000000 | D49: =IF(SUMIF(Lines!$C$6:$C$28,A49,Lines!$Q$6:$Q$28)<=C49+1,"OK","CHECK") -> OK | E49: =SUMIF(Lines!$C$6:$C$28,A49,Lines!$S$6:$S$28) -> 15300000
A50: G-09 | B50: =ROUND((SUMIF(Lines!$C$6:$C$28,A50,Lines!$Q$6:$Q$28))/IF(ABS(SUMIF(Lines!$C$6:$C$28,A50,Lines!$Q$6:$Q$28))<1000000,10000,100000),0)*IF(ABS(SUMIF(Lines!$C$6:$C$28,A50,Lines!$Q$6:$Q$28))<1000000,10000,100000) -> 5000000 | C50: =CompanyCap -> 10000000 | D50: =IF(SUMIF(Lines!$C$6:$C$28,A50,Lines!$Q$6:$Q$28)<=C50+1,"OK","CHECK") -> OK | E50: =SUMIF(Lines!$C$6:$C$28,A50,Lines!$S$6:$S$28) -> 4000000
A51: SPV top-ups, total (outside the fund) | F51: =SUM(F34:F50) -> 19000000
A53: Fund returner (largest proceeds, Target) | B53: =INDEX(A34:A50,MATCH(MAX(E34:E50),E34:E50,0)) -> S-01
A54: its proceeds, all lines | B54: =MAX(E34:E50) -> 100500000
A55: multiple of the fund | B55: =ROUND(B54/Commitments,1) -> 1

Sheet Cash flows
A1: Cash flows — yearly, per case
A2: Year 1 = year of the first closing; all flows at year end. Columns after the horizon stay at zero. Base and Stress cap every exit value; everything else is unchanged.
A4: Horizon (last exit year) | B4: =MAX(Lines!$L$6:$L$28) -> 8
A5: Running costs of the years after the horizon (set aside from the last distribution) | B5: =RunningCost*MAX(0,TermYears-Horizon) -> 700000
A7: Euros | B7: Total | C7: 1 | D7: 2 | E7: 3 | F7: 4 | G7: 5 | H7: 6 | I7: 7 | J7: 8 | K7: 9 | L7: 10
A9: TARGET CASE — exit values uncapped
A10: Investments (initial tickets and follow-ons) | B10: =SUM(C10:L10) -> 83900000 | C10: =SUMIFS(Lines!$G$6:$G$28,Lines!$J$6:$J$28,C$7)+SUMIFS(Lines!$I$6:$I$28,Lines!$K$6:$K$28,C$7) -> 9000000 | D10: =SUMIFS(Lines!$G$6:$G$28,Lines!$J$6:$J$28,D$7)+SUMIFS(Lines!$I$6:$I$28,Lines!$K$6:$K$28,D$7) -> 22000000 | E10: =SUMIFS(Lines!$G$6:$G$28,Lines!$J$6:$J$28,E$7)+SUMIFS(Lines!$I$6:$I$28,Lines!$K$6:$K$28,E$7) -> 41500000 | F10: =SUMIFS(Lines!$G$6:$G$28,Lines!$J$6:$J$28,F$7)+SUMIFS(Lines!$I$6:$I$28,Lines!$K$6:$K$28,F$7) -> 11400000 | G10: =SUMIFS(Lines!$G$6:$G$28,Lines!$J$6:$J$28,G$7)+SUMIFS(Lines!$I$6:$I$28,Lines!$K$6:$K$28,G$7) -> 0 | H10: =SUMIFS(Lines!$G$6:$G$28,Lines!$J$6:$J$28,H$7)+SUMIFS(Lines!$I$6:$I$28,Lines!$K$6:$K$28,H$7) -> 0 | I10: =SUMIFS(Lines!$G$6:$G$28,Lines!$J$6:$J$28,I$7)+SUMIFS(Lines!$I$6:$I$28,Lines!$K$6:$K$28,I$7) -> 0 | J10: =SUMIFS(Lines!$G$6:$G$28,Lines!$J$6:$J$28,J$7)+SUMIFS(Lines!$I$6:$I$28,Lines!$K$6:$K$28,J$7) -> 0 | ... L10: =SUMIFS(Lines!$G$6:$G$28,Lines!$J$6:$J$28,L$7)+SUMIFS(Lines!$I$6:$I$28,Lines!$K$6:$K$28,L$7) -> 0
A11: Exit proceeds received, incl. the partial secondary sale | B11: =SUM(C11:L11) -> 307700000 | C11: =SUMIFS(Lines!$Z$6:$Z$28,Lines!$L$6:$L$28,C$7)+IF(C$7=SecYear,SUM(Lines!$Y$6:$Y$28),0) -> 0 | D11: =SUMIFS(Lines!$Z$6:$Z$28,Lines!$L$6:$L$28,D$7)+IF(D$7=SecYear,SUM(Lines!$Y$6:$Y$28),0) -> 0 | E11: =SUMIFS(Lines!$Z$6:$Z$28,Lines!$L$6:$L$28,E$7)+IF(E$7=SecYear,SUM(Lines!$Y$6:$Y$28),0) -> 0 | F11: =SUMIFS(Lines!$Z$6:$Z$28,Lines!$L$6:$L$28,F$7)+IF(F$7=SecYear,SUM(Lines!$Y$6:$Y$28),0) -> 4300000 | G11: =SUMIFS(Lines!$Z$6:$Z$28,Lines!$L$6:$L$28,G$7)+IF(G$7=SecYear,SUM(Lines!$Y$6:$Y$28),0) -> 7500000 | H11: =SUMIFS(Lines!$Z$6:$Z$28,Lines!$L$6:$L$28,H$7)+IF(H$7=SecYear,SUM(Lines!$Y$6:$Y$28),0) -> 74000000 | I11: =SUMIFS(Lines!$Z$6:$Z$28,Lines!$L$6:$L$28,I$7)+IF(I$7=SecYear,SUM(Lines!$Y$6:$Y$28),0) -> 97000000 | J11: =SUMIFS(Lines!$Z$6:$Z$28,Lines!$L$6:$L$28,J$7)+IF(J$7=SecYear,SUM(Lines!$Y$6:$Y$28),0) -> 124900000 | ... L11: =SUMIFS(Lines!$Z$6:$Z$28,Lines!$L$6:$L$28,L$7)+IF(L$7=SecYear,SUM(Lines!$Y$6:$Y$28),0) -> 0
A12: Running costs of the years after the horizon, set aside | B12: =SUM(C12:L12) -> -700000 | C12: =IF(C$7=Horizon,-TailCost,0) -> 0 | D12: =IF(D$7=Horizon,-TailCost,0) -> 0 | E12: =IF(E$7=Horizon,-TailCost,0) -> 0 | F12: =IF(F$7=Horizon,-TailCost,0) -> 0 | G12: =IF(G$7=Horizon,-TailCost,0) -> 0 | H12: =IF(H$7=Horizon,-TailCost,0) -> 0 | I12: =IF(I$7=Horizon,-TailCost,0) -> 0 | J12: =IF(J$7=Horizon,-TailCost,0) -> -700000 | ... L12: =IF(L$7=Horizon,-TailCost,0) -> 0
A13: Distributable proceeds | B13: =SUM(C13:L13) -> 307000000 | C13: =C11+C12 -> 0 | D13: =D11+D12 -> 0 | E13: =E11+E12 -> 0 | F13: =F11+F12 -> 4300000 | G13: =G11+G12 -> 7500000 | H13: =H11+H12 -> 74000000 | I13: =I11+I12 -> 97000000 | J13: =J11+J12 -> 124200000 | ... L13: =L11+L12 -> 0
A14: Cost of the positions sold | B14: =SUM(C14:L14) -> 83900000 | C14: =SUMIFS(Lines!$AB$6:$AB$28,Lines!$L$6:$L$28,C$7)+IF(C$7=SecYear,SUM(Lines!$AA$6:$AA$28),0) -> 0 | D14: =SUMIFS(Lines!$AB$6:$AB$28,Lines!$L$6:$L$28,D$7)+IF(D$7=SecYear,SUM(Lines!$AA$6:$AA$28),0) -> 0 | E14: =SUMIFS(Lines!$AB$6:$AB$28,Lines!$L$6:$L$28,E$7)+IF(E$7=SecYear,SUM(Lines!$AA$6:$AA$28),0) -> 0 | F14: =SUMIFS(Lines!$AB$6:$AB$28,Lines!$L$6:$L$28,F$7)+IF(F$7=SecYear,SUM(Lines!$AA$6:$AA$28),0) -> 1300000 | G14: =SUMIFS(Lines!$AB$6:$AB$28,Lines!$L$6:$L$28,G$7)+IF(G$7=SecYear,SUM(Lines!$AA$6:$AA$28),0) -> 6400000 | H14: =SUMIFS(Lines!$AB$6:$AB$28,Lines!$L$6:$L$28,H$7)+IF(H$7=SecYear,SUM(Lines!$AA$6:$AA$28),0) -> 27900000 | I14: =SUMIFS(Lines!$AB$6:$AB$28,Lines!$L$6:$L$28,I$7)+IF(I$7=SecYear,SUM(Lines!$AA$6:$AA$28),0) -> 33300000 | J14: =SUMIFS(Lines!$AB$6:$AB$28,Lines!$L$6:$L$28,J$7)+IF(J$7=SecYear,SUM(Lines!$AA$6:$AA$28),0) -> 15000000 | ... L14: =SUMIFS(Lines!$AB$6:$AB$28,Lines!$L$6:$L$28,L$7)+IF(L$7=SecYear,SUM(Lines!$AA$6:$AA$28),0) -> 0
A15: Net invested capital at cost, end of year | C15: =C10-C14 -> 9000000 | D15: =C15+D10-D14 -> 31000000 | E15: =D15+E10-E14 -> 72500000 | F15: =E15+F10-F14 -> 82600000 | G15: =F15+G10-G14 -> 76200000 | H15: =G15+H10-H14 -> 48300000 | I15: =H15+I10-I14 -> 15000000 | J15: =I15+J10-J14 -> 0 | K15: =J15+K10-K14 -> 0 | L15: =K15+L10-L14 -> 0
A16: Management fees | B16: =SUM(C16:L16) -> 12092500 | C16: =IF(C$7>Horizon,0,IF(C$7<=IPYears,FeeIP*Commitments,FeePost*MAX(0,0))) -> 2000000 | D16: =IF(D$7>Horizon,0,IF(D$7<=IPYears,FeeIP*Commitments,FeePost*MAX(C15,0))) -> 2000000 | E16: =IF(E$7>Horizon,0,IF(E$7<=IPYears,FeeIP*Commitments,FeePost*MAX(D15,0))) -> 2000000 | F16: =IF(F$7>Horizon,0,IF(F$7<=IPYears,FeeIP*Commitments,FeePost*MAX(E15,0))) -> 2000000 | G16: =IF(G$7>Horizon,0,IF(G$7<=IPYears,FeeIP*Commitments,FeePost*MAX(F15,0))) -> 2000000 | H16: =IF(H$7>Horizon,0,IF(H$7<=IPYears,FeeIP*Commitments,FeePost*MAX(G15,0))) -> 1143000 | I16: =IF(I$7>Horizon,0,IF(I$7<=IPYears,FeeIP*Commitments,FeePost*MAX(H15,0))) -> 724500 | J16: =IF(J$7>Horizon,0,IF(J$7<=IPYears,FeeIP*Commitments,FeePost*MAX(I15,0))) -> 225000 | K16: =IF(K$7>Horizon,0,IF(K$7<=IPYears,FeeIP*Commitments,FeePost*MAX(J15,0))) -> 0 | L16: =IF(L$7>Horizon,0,IF(L$7<=IPYears,FeeIP*Commitments,FeePost*MAX(K15,0))) -> 0
A17: Fund expenses | B17: =SUM(C17:L17) -> 3200000 | C17: =IF(C$7>Horizon,0,RunningCost+IF(C$7=1,SetupCost,0)) -> 750000 | D17: =IF(D$7>Horizon,0,RunningCost+IF(D$7=1,SetupCost,0)) -> 350000 | E17: =IF(E$7>Horizon,0,RunningCost+IF(E$7=1,SetupCost,0)) -> 350000 | F17: =IF(F$7>Horizon,0,RunningCost+IF(F$7=1,SetupCost,0)) -> 350000 | G17: =IF(G$7>Horizon,0,RunningCost+IF(G$7=1,SetupCost,0)) -> 350000 | H17: =IF(H$7>Horizon,0,RunningCost+IF(H$7=1,SetupCost,0)) -> 350000 | I17: =IF(I$7>Horizon,0,RunningCost+IF(I$7=1,SetupCost,0)) -> 350000 | J17: =IF(J$7>Horizon,0,RunningCost+IF(J$7=1,SetupCost,0)) -> 350000 | ... L17: =IF(L$7>Horizon,0,RunningCost+IF(L$7=1,SetupCost,0)) -> 0
A18: Capital calls | B18: =SUM(C18:L18) -> 99192500 | C18: =C10+C16+C17 -> 11750000 | D18: =D10+D16+D17 -> 24350000 | E18: =E10+E16+E17 -> 43850000 | F18: =F10+F16+F17 -> 13750000 | G18: =G10+G16+G17 -> 2350000 | H18: =H10+H16+H17 -> 1493000 | I18: =I10+I16+I17 -> 1074500 | J18: =J10+J16+J17 -> 575000 | ... L18: =L10+L16+L17 -> 0
A20: Hurdle balance before distribution (capital + 8% compounded) | C20: =C18 -> 11750000 | D20: =C22*(1+Hurdle)+D18 -> 37040000 | E20: =D22*(1+Hurdle)+E18 -> 83853200 | F20: =E22*(1+Hurdle)+F18 -> 104311456 | G20: =F22*(1+Hurdle)+G18 -> 1.1036237e+08 | H20: =G22*(1+Hurdle)+H18 -> 1.1258436e+08 | I20: =H22*(1+Hurdle)+I18 -> 42745611 | J20: =I22*(1+Hurdle)+J18 -> 575000 | K20: =J22*(1+Hurdle)+K18 -> 0 | L20: =K22*(1+Hurdle)+L18 -> 0
A21: 1. Return of capital and preferred return to LPs | B21: =SUM(C21:L21) -> 1.2912061e+08 | C21: =MIN(C13,C20) -> 0 | D21: =MIN(D13,D20) -> 0 | E21: =MIN(E13,E20) -> 0 | F21: =MIN(F13,F20) -> 4300000 | G21: =MIN(G13,G20) -> 7500000 | H21: =MIN(H13,H20) -> 74000000 | I21: =MIN(I13,I20) -> 42745611 | J21: =MIN(J13,J20) -> 575000 | ... L21: =MIN(L13,L20) -> 0
A22: Hurdle balance after distribution | C22: =C20-C21 -> 11750000 | D22: =D20-D21 -> 37040000 | E22: =E20-E21 -> 83853200 | F22: =F20-F21 -> 100011456 | G22: =G20-G21 -> 1.0286237e+08 | H22: =H20-H21 -> 38584362 | I22: =I20-I21 -> 0 | J22: =J20-J21 -> 0 | ... L22: =L20-L21 -> 0
A23: Cumulative contributions | C23: =C18 -> 11750000 | D23: =C23+D18 -> 36100000 | E23: =D23+E18 -> 79950000 | F23: =E23+F18 -> 93700000 | G23: =F23+G18 -> 96050000 | H23: =G23+H18 -> 97543000 | I23: =H23+I18 -> 98617500 | J23: =I23+J18 -> 99192500 | K23: =J23+K18 -> 99192500 | L23: =K23+L18 -> 99192500
A24: Remaining after step 1 | C24: =C13-C21 -> 0 | D24: =D13-D21 -> 0 | E24: =E13-E21 -> 0 | F24: =F13-F21 -> 0 | G24: =G13-G21 -> 0 | H24: =H13-H21 -> 0 | I24: =I13-I21 -> 54254389 | J24: =J13-J21 -> 123625000 | ... L24: =L13-L21 -> 0
A25: Cumulative paid out after step 1 | C25: =C21 -> 0 | D25: =C30+D21 -> 0 | E25: =D30+E21 -> 0 | F25: =E30+F21 -> 4300000 | G25: =F30+G21 -> 11800000 | H25: =G30+H21 -> 85800000 | I25: =H30+I21 -> 1.2854561e+08 | J25: =I30+J21 -> 1.83375e+08 | K25: =J30+K21 -> 307000000 | L25: =K30+L21 -> 307000000
A26: 2. GP catch-up | B26: =SUM(C26:L26) -> 7482027.8 | C26: =IF(C24>0,MIN(C24,MAX(0,(Carry*(C25-C23)-0)/(1-Carry)))*CatchUp,0) -> 0 | D26: =IF(D24>0,MIN(D24,MAX(0,(Carry*(D25-D23)-C31)/(1-Carry)))*CatchUp,0) -> 0 | E26: =IF(E24>0,MIN(E24,MAX(0,(Carry*(E25-E23)-D31)/(1-Carry)))*CatchUp,0) -> 0 | F26: =IF(F24>0,MIN(F24,MAX(0,(Carry*(F25-F23)-E31)/(1-Carry)))*CatchUp,0) -> 0 | G26: =IF(G24>0,MIN(G24,MAX(0,(Carry*(G25-G23)-F31)/(1-Carry)))*CatchUp,0) -> 0 | H26: =IF(H24>0,MIN(H24,MAX(0,(Carry*(H25-H23)-G31)/(1-Carry)))*CatchUp,0) -> 0 | I26: =IF(I24>0,MIN(I24,MAX(0,(Carry*(I25-I23)-H31)/(1-Carry)))*CatchUp,0) -> 7482027.8 | J26: =IF(J24>0,MIN(J24,MAX(0,(Carry*(J25-J23)-I31)/(1-Carry)))*CatchUp,0) -> 9.3132257e-09 | K26: =IF(K24>0,MIN(K24,MAX(0,(Carry*(K25-K23)-J31)/(1-Carry)))*CatchUp,0) -> 0 | L26: =IF(L24>0,MIN(L24,MAX(0,(Carry*(L25-L23)-K31)/(1-Carry)))*CatchUp,0) -> 0
A27: Remaining after step 2 | C27: =C24-C26 -> 0 | D27: =D24-D26 -> 0 | E27: =E24-E26 -> 0 | F27: =F24-F26 -> 0 | G27: =G24-G26 -> 0 | H27: =H24-H26 -> 0 | I27: =I24-I26 -> 46772361 | J27: =J24-J26 -> 1.23625e+08 | ... L27: =L24-L26 -> 0
A28: 3. Split: to LPs | B28: =SUM(C28:L28) -> 1.3631789e+08 | C28: =IF(C27>0,(1-Carry)*C27,0) -> 0 | D28: =IF(D27>0,(1-Carry)*D27,0) -> 0 | E28: =IF(E27>0,(1-Carry)*E27,0) -> 0 | F28: =IF(F27>0,(1-Carry)*F27,0) -> 0 | G28: =IF(G27>0,(1-Carry)*G27,0) -> 0 | H28: =IF(H27>0,(1-Carry)*H27,0) -> 0 | I28: =IF(I27>0,(1-Carry)*I27,0) -> 37417889 | J28: =IF(J27>0,(1-Carry)*J27,0) -> 98900000 | ... L28: =IF(L27>0,(1-Carry)*L27,0) -> 0
A29: 3. Split: carried interest to the GP | B29: =SUM(C29:L29) -> 34079472 | C29: =IF(C27>0,Carry*C27,0) -> 0 | D29: =IF(D27>0,Carry*D27,0) -> 0 | E29: =IF(E27>0,Carry*E27,0) -> 0 | F29: =IF(F27>0,Carry*F27,0) -> 0 | G29: =IF(G27>0,Carry*G27,0) -> 0 | H29: =IF(H27>0,Carry*H27,0) -> 0 | I29: =IF(I27>0,Carry*I27,0) -> 9354472.2 | J29: =IF(J27>0,Carry*J27,0) -> 24725000 | ... L29: =IF(L27>0,Carry*L27,0) -> 0
A30: Cumulative paid out | C30: =C25+C26+IF(C27>0,C27,0) -> 0 | D30: =D25+D26+IF(D27>0,D27,0) -> 0 | E30: =E25+E26+IF(E27>0,E27,0) -> 0 | F30: =F25+F26+IF(F27>0,F27,0) -> 4300000 | G30: =G25+G26+IF(G27>0,G27,0) -> 11800000 | H30: =H25+H26+IF(H27>0,H27,0) -> 85800000 | I30: =I25+I26+IF(I27>0,I27,0) -> 1.828e+08 | J30: =J25+J26+IF(J27>0,J27,0) -> 307000000 | ... L30: =L25+L26+IF(L27>0,L27,0) -> 307000000
A31: Cumulative carried interest | C31: =C26+C29 -> 0 | D31: =C31+D26+D29 -> 0 | E31: =D31+E26+E29 -> 0 | F31: =E31+F26+F29 -> 0 | G31: =F31+G26+G29 -> 0 | H31: =G31+H26+H29 -> 0 | I31: =H31+I26+I29 -> 16836500 | J31: =I31+J26+J29 -> 41561500 | K31: =J31+K26+K29 -> 41561500 | L31: =K31+L26+L29 -> 41561500
A33: LP distributions | B33: =SUM(C33:L33) -> 265438500 | C33: =C21+C28 -> 0 | D33: =D21+D28 -> 0 | E33: =E21+E28 -> 0 | F33: =F21+F28 -> 4300000 | G33: =G21+G28 -> 7500000 | H33: =H21+H28 -> 74000000 | I33: =I21+I28 -> 80163500 | J33: =J21+J28 -> 99475000 | ... L33: =L21+L28 -> 0
A34: GP carried interest | B34: =SUM(C34:L34) -> 41561500 | C34: =C26+C29 -> 0 | D34: =D26+D29 -> 0 | E34: =E26+E29 -> 0 | F34: =F26+F29 -> 0 | G34: =G26+G29 -> 0 | H34: =H26+H29 -> 0 | I34: =I26+I29 -> 16836500 | J34: =J26+J29 -> 24725000 | ... L34: =L26+L29 -> 0
A35: Net LP cash flow (distributions − calls) | B35: =SUM(C35:L35) -> 166246000 | C35: =C33-C18 -> -11750000 | D35: =D33-D18 -> -24350000 | E35: =E33-E18 -> -43850000 | F35: =F33-F18 -> -9450000 | G35: =G33-G18 -> 5150000 | H35: =H33-H18 -> 72507000 | I35: =I33-I18 -> 79089000 | J35: =J33-J18 -> 98900000 | ... L35: =L33-L18 -> 0
A36: Gross fund cash flow (exit proceeds − investments) | B36: =SUM(C36:L36) -> 223800000 | C36: =C11-C10 -> -9000000 | D36: =D11-D10 -> -22000000 | E36: =E11-E10 -> -41500000 | F36: =F11-F10 -> -7100000 | G36: =G11-G10 -> 7500000 | H36: =H11-H10 -> 74000000 | I36: =I11-I10 -> 97000000 | J36: =J11-J10 -> 124900000 | ... L36: =L11-L10 -> 0
A38: Outputs — Target case
A39: Gross exit value | B39: =Lines!S29 -> 324300000
A40: Realised (exit proceeds incl. secondary) | B40: =ROUND((SUM(C11:L11))/IF(ABS(SUM(C11:L11))<1000000,10000,100000),0)*IF(ABS(SUM(C11:L11))<1000000,10000,100000) -> 307700000
A41: Secondary discount | B41: =B39-B40 -> 16600000
A42: Paid-in capital | B42: =ROUND((SUM(C18:L18))/IF(ABS(SUM(C18:L18))<1000000,10000,100000),0)*IF(ABS(SUM(C18:L18))<1000000,10000,100000) -> 99200000
A43: Management fees | B43: =ROUND((SUM(C16:L16))/IF(ABS(SUM(C16:L16))<1000000,10000,100000),0)*IF(ABS(SUM(C16:L16))<1000000,10000,100000) -> 12100000
A44: Fund expenses | B44: =ROUND((SUM(C17:L17)+TailCost)/IF(ABS(SUM(C17:L17)+TailCost)<1000000,10000,100000),0)*IF(ABS(SUM(C17:L17)+TailCost)<1000000,10000,100000) -> 3900000
A45: LP distributions | B45: =ROUND((SUM(C33:L33))/IF(ABS(SUM(C33:L33))<1000000,10000,100000),0)*IF(ABS(SUM(C33:L33))<1000000,10000,100000) -> 265400000
A46: Carried interest | B46: =ROUND((SUM(C34:L34))/IF(ABS(SUM(C34:L34))<1000000,10000,100000),0)*IF(ABS(SUM(C34:L34))<1000000,10000,100000) -> 41600000
A47: Net TVPI | B47: =ROUND(SUM(C33:L33)/SUM(C18:L18),1) -> 2.7
A48: Net IRR | B48: =ROUND(IRR(C35:L35),2) -> 0.26
A49: Gross IRR | B49: =ROUND(IRR(C36:L36),2) -> 0.34
A50: Net DPI by year 6 | B50: =ROUND(SUM(C33:H33)/SUM(C18:H18),1) -> 0.9
A51: GP clawback (must be zero) | B51: =MAX(0,L31-Carry*MAX(0,L30-L23)) -> 7.4505806e-09
A54: BASE CASE — every exit value capped (Assumptions)
A55: Investments (initial tickets and follow-ons) | B55: =SUM(C55:L55) -> 83900000 | C55: =SUMIFS(Lines!$G$6:$G$28,Lines!$J$6:$J$28,C$7)+SUMIFS(Lines!$I$6:$I$28,Lines!$K$6:$K$28,C$7) -> 9000000 | D55: =SUMIFS(Lines!$G$6:$G$28,Lines!$J$6:$J$28,D$7)+SUMIFS(Lines!$I$6:$I$28,Lines!$K$6:$K$28,D$7) -> 22000000 | E55: =SUMIFS(Lines!$G$6:$G$28,Lines!$J$6:$J$28,E$7)+SUMIFS(Lines!$I$6:$I$28,Lines!$K$6:$K$28,E$7) -> 41500000 | F55: =SUMIFS(Lines!$G$6:$G$28,Lines!$J$6:$J$28,F$7)+SUMIFS(Lines!$I$6:$I$28,Lines!$K$6:$K$28,F$7) -> 11400000 | G55: =SUMIFS(Lines!$G$6:$G$28,Lines!$J$6:$J$28,G$7)+SUMIFS(Lines!$I$6:$I$28,Lines!$K$6:$K$28,G$7) -> 0 | H55: =SUMIFS(Lines!$G$6:$G$28,Lines!$J$6:$J$28,H$7)+SUMIFS(Lines!$I$6:$I$28,Lines!$K$6:$K$28,H$7) -> 0 | I55: =SUMIFS(Lines!$G$6:$G$28,Lines!$J$6:$J$28,I$7)+SUMIFS(Lines!$I$6:$I$28,Lines!$K$6:$K$28,I$7) -> 0 | J55: =SUMIFS(Lines!$G$6:$G$28,Lines!$J$6:$J$28,J$7)+SUMIFS(Lines!$I$6:$I$28,Lines!$K$6:$K$28,J$7) -> 0 | ... L55: =SUMIFS(Lines!$G$6:$G$28,Lines!$J$6:$J$28,L$7)+SUMIFS(Lines!$I$6:$I$28,Lines!$K$6:$K$28,L$7) -> 0
A56: Exit proceeds received, incl. the partial secondary sale | B56: =SUM(C56:L56) -> 184850000 | C56: =SUMIFS(Lines!$AD$6:$AD$28,Lines!$L$6:$L$28,C$7)+IF(C$7=SecYear,SUM(Lines!$AC$6:$AC$28),0) -> 0 | D56: =SUMIFS(Lines!$AD$6:$AD$28,Lines!$L$6:$L$28,D$7)+IF(D$7=SecYear,SUM(Lines!$AC$6:$AC$28),0) -> 0 | E56: =SUMIFS(Lines!$AD$6:$AD$28,Lines!$L$6:$L$28,E$7)+IF(E$7=SecYear,SUM(Lines!$AC$6:$AC$28),0) -> 0 | F56: =SUMIFS(Lines!$AD$6:$AD$28,Lines!$L$6:$L$28,F$7)+IF(F$7=SecYear,SUM(Lines!$AC$6:$AC$28),0) -> 4300000 | G56: =SUMIFS(Lines!$AD$6:$AD$28,Lines!$L$6:$L$28,G$7)+IF(G$7=SecYear,SUM(Lines!$AC$6:$AC$28),0) -> 7500000 | H56: =SUMIFS(Lines!$AD$6:$AD$28,Lines!$L$6:$L$28,H$7)+IF(H$7=SecYear,SUM(Lines!$AC$6:$AC$28),0) -> 47750000 | I56: =SUMIFS(Lines!$AD$6:$AD$28,Lines!$L$6:$L$28,I$7)+IF(I$7=SecYear,SUM(Lines!$AC$6:$AC$28),0) -> 79400000 | J56: =SUMIFS(Lines!$AD$6:$AD$28,Lines!$L$6:$L$28,J$7)+IF(J$7=SecYear,SUM(Lines!$AC$6:$AC$28),0) -> 45900000 | ... L56: =SUMIFS(Lines!$AD$6:$AD$28,Lines!$L$6:$L$28,L$7)+IF(L$7=SecYear,SUM(Lines!$AC$6:$AC$28),0) -> 0
A57: Running costs of the years after the horizon, set aside | B57: =SUM(C57:L57) -> -700000 | C57: =IF(C$7=Horizon,-TailCost,0) -> 0 | D57: =IF(D$7=Horizon,-TailCost,0) -> 0 | E57: =IF(E$7=Horizon,-TailCost,0) -> 0 | F57: =IF(F$7=Horizon,-TailCost,0) -> 0 | G57: =IF(G$7=Horizon,-TailCost,0) -> 0 | H57: =IF(H$7=Horizon,-TailCost,0) -> 0 | I57: =IF(I$7=Horizon,-TailCost,0) -> 0 | J57: =IF(J$7=Horizon,-TailCost,0) -> -700000 | ... L57: =IF(L$7=Horizon,-TailCost,0) -> 0
A58: Distributable proceeds | B58: =SUM(C58:L58) -> 184150000 | C58: =C56+C57 -> 0 | D58: =D56+D57 -> 0 | E58: =E56+E57 -> 0 | F58: =F56+F57 -> 4300000 | G58: =G56+G57 -> 7500000 | H58: =H56+H57 -> 47750000 | I58: =I56+I57 -> 79400000 | J58: =J56+J57 -> 45200000 | ... L58: =L56+L57 -> 0
A59: Cost of the positions sold | B59: =SUM(C59:L59) -> 83900000 | C59: =SUMIFS(Lines!$AF$6:$AF$28,Lines!$L$6:$L$28,C$7)+IF(C$7=SecYear,SUM(Lines!$AE$6:$AE$28),0) -> 0 | D59: =SUMIFS(Lines!$AF$6:$AF$28,Lines!$L$6:$L$28,D$7)+IF(D$7=SecYear,SUM(Lines!$AE$6:$AE$28),0) -> 0 | E59: =SUMIFS(Lines!$AF$6:$AF$28,Lines!$L$6:$L$28,E$7)+IF(E$7=SecYear,SUM(Lines!$AE$6:$AE$28),0) -> 0 | F59: =SUMIFS(Lines!$AF$6:$AF$28,Lines!$L$6:$L$28,F$7)+IF(F$7=SecYear,SUM(Lines!$AE$6:$AE$28),0) -> 1300000 | G59: =SUMIFS(Lines!$AF$6:$AF$28,Lines!$L$6:$L$28,G$7)+IF(G$7=SecYear,SUM(Lines!$AE$6:$AE$28),0) -> 6400000 | H59: =SUMIFS(Lines!$AF$6:$AF$28,Lines!$L$6:$L$28,H$7)+IF(H$7=SecYear,SUM(Lines!$AE$6:$AE$28),0) -> 27900000 | I59: =SUMIFS(Lines!$AF$6:$AF$28,Lines!$L$6:$L$28,I$7)+IF(I$7=SecYear,SUM(Lines!$AE$6:$AE$28),0) -> 33300000 | J59: =SUMIFS(Lines!$AF$6:$AF$28,Lines!$L$6:$L$28,J$7)+IF(J$7=SecYear,SUM(Lines!$AE$6:$AE$28),0) -> 15000000 | ... L59: =SUMIFS(Lines!$AF$6:$AF$28,Lines!$L$6:$L$28,L$7)+IF(L$7=SecYear,SUM(Lines!$AE$6:$AE$28),0) -> 0
A60: Net invested capital at cost, end of year | C60: =C55-C59 -> 9000000 | D60: =C60+D55-D59 -> 31000000 | E60: =D60+E55-E59 -> 72500000 | F60: =E60+F55-F59 -> 82600000 | G60: =F60+G55-G59 -> 76200000 | H60: =G60+H55-H59 -> 48300000 | I60: =H60+I55-I59 -> 15000000 | J60: =I60+J55-J59 -> 0 | K60: =J60+K55-K59 -> 0 | L60: =K60+L55-L59 -> 0
A61: Management fees | B61: =SUM(C61:L61) -> 12092500 | C61: =IF(C$7>Horizon,0,IF(C$7<=IPYears,FeeIP*Commitments,FeePost*MAX(0,0))) -> 2000000 | D61: =IF(D$7>Horizon,0,IF(D$7<=IPYears,FeeIP*Commitments,FeePost*MAX(C60,0))) -> 2000000 | E61: =IF(E$7>Horizon,0,IF(E$7<=IPYears,FeeIP*Commitments,FeePost*MAX(D60,0))) -> 2000000 | F61: =IF(F$7>Horizon,0,IF(F$7<=IPYears,FeeIP*Commitments,FeePost*MAX(E60,0))) -> 2000000 | G61: =IF(G$7>Horizon,0,IF(G$7<=IPYears,FeeIP*Commitments,FeePost*MAX(F60,0))) -> 2000000 | H61: =IF(H$7>Horizon,0,IF(H$7<=IPYears,FeeIP*Commitments,FeePost*MAX(G60,0))) -> 1143000 | I61: =IF(I$7>Horizon,0,IF(I$7<=IPYears,FeeIP*Commitments,FeePost*MAX(H60,0))) -> 724500 | J61: =IF(J$7>Horizon,0,IF(J$7<=IPYears,FeeIP*Commitments,FeePost*MAX(I60,0))) -> 225000 | K61: =IF(K$7>Horizon,0,IF(K$7<=IPYears,FeeIP*Commitments,FeePost*MAX(J60,0))) -> 0 | L61: =IF(L$7>Horizon,0,IF(L$7<=IPYears,FeeIP*Commitments,FeePost*MAX(K60,0))) -> 0
A62: Fund expenses | B62: =SUM(C62:L62) -> 3200000 | C62: =IF(C$7>Horizon,0,RunningCost+IF(C$7=1,SetupCost,0)) -> 750000 | D62: =IF(D$7>Horizon,0,RunningCost+IF(D$7=1,SetupCost,0)) -> 350000 | E62: =IF(E$7>Horizon,0,RunningCost+IF(E$7=1,SetupCost,0)) -> 350000 | F62: =IF(F$7>Horizon,0,RunningCost+IF(F$7=1,SetupCost,0)) -> 350000 | G62: =IF(G$7>Horizon,0,RunningCost+IF(G$7=1,SetupCost,0)) -> 350000 | H62: =IF(H$7>Horizon,0,RunningCost+IF(H$7=1,SetupCost,0)) -> 350000 | I62: =IF(I$7>Horizon,0,RunningCost+IF(I$7=1,SetupCost,0)) -> 350000 | J62: =IF(J$7>Horizon,0,RunningCost+IF(J$7=1,SetupCost,0)) -> 350000 | ... L62: =IF(L$7>Horizon,0,RunningCost+IF(L$7=1,SetupCost,0)) -> 0
A63: Capital calls | B63: =SUM(C63:L63) -> 99192500 | C63: =C55+C61+C62 -> 11750000 | D63: =D55+D61+D62 -> 24350000 | E63: =E55+E61+E62 -> 43850000 | F63: =F55+F61+F62 -> 13750000 | G63: =G55+G61+G62 -> 2350000 | H63: =H55+H61+H62 -> 1493000 | I63: =I55+I61+I62 -> 1074500 | J63: =J55+J61+J62 -> 575000 | ... L63: =L55+L61+L62 -> 0
A65: Hurdle balance before distribution (capital + 8% compounded) | C65: =C63 -> 11750000 | D65: =C67*(1+Hurdle)+D63 -> 37040000 | E65: =D67*(1+Hurdle)+E63 -> 83853200 | F65: =E67*(1+Hurdle)+F63 -> 104311456 | G65: =F67*(1+Hurdle)+G63 -> 1.1036237e+08 | H65: =G67*(1+Hurdle)+H63 -> 1.1258436e+08 | I65: =H67*(1+Hurdle)+I63 -> 71095611 | J65: =I67*(1+Hurdle)+J63 -> 575000 | K65: =J67*(1+Hurdle)+K63 -> 0 | L65: =K67*(1+Hurdle)+L63 -> 0
A66: 1. Return of capital and preferred return to LPs | B66: =SUM(C66:L66) -> 1.3122061e+08 | C66: =MIN(C58,C65) -> 0 | D66: =MIN(D58,D65) -> 0 | E66: =MIN(E58,E65) -> 0 | F66: =MIN(F58,F65) -> 4300000 | G66: =MIN(G58,G65) -> 7500000 | H66: =MIN(H58,H65) -> 47750000 | I66: =MIN(I58,I65) -> 71095611 | J66: =MIN(J58,J65) -> 575000 | ... L66: =MIN(L58,L65) -> 0
A67: Hurdle balance after distribution | C67: =C65-C66 -> 11750000 | D67: =D65-D66 -> 37040000 | E67: =E65-E66 -> 83853200 | F67: =F65-F66 -> 100011456 | G67: =G65-G66 -> 1.0286237e+08 | H67: =H65-H66 -> 64834362 | I67: =I65-I66 -> 0 | J67: =J65-J66 -> 0 | ... L67: =L65-L66 -> 0
A68: Cumulative contributions | C68: =C63 -> 11750000 | D68: =C68+D63 -> 36100000 | E68: =D68+E63 -> 79950000 | F68: =E68+F63 -> 93700000 | G68: =F68+G63 -> 96050000 | H68: =G68+H63 -> 97543000 | I68: =H68+I63 -> 98617500 | J68: =I68+J63 -> 99192500 | K68: =J68+K63 -> 99192500 | L68: =K68+L63 -> 99192500
A69: Remaining after step 1 | C69: =C58-C66 -> 0 | D69: =D58-D66 -> 0 | E69: =E58-E66 -> 0 | F69: =F58-F66 -> 0 | G69: =G58-G66 -> 0 | H69: =H58-H66 -> 0 | I69: =I58-I66 -> 8304388.7 | J69: =J58-J66 -> 44625000 | ... L69: =L58-L66 -> 0
A70: Cumulative paid out after step 1 | C70: =C66 -> 0 | D70: =C75+D66 -> 0 | E70: =D75+E66 -> 0 | F70: =E75+F66 -> 4300000 | G70: =F75+G66 -> 11800000 | H70: =G75+H66 -> 59550000 | I70: =H75+I66 -> 1.3064561e+08 | J70: =I75+J66 -> 139525000 | K70: =J75+K66 -> 184150000 | L70: =K75+L66 -> 184150000
A71: 2. GP catch-up | B71: =SUM(C71:L71) -> 8007027.8 | C71: =IF(C69>0,MIN(C69,MAX(0,(Carry*(C70-C68)-0)/(1-Carry)))*CatchUp,0) -> 0 | D71: =IF(D69>0,MIN(D69,MAX(0,(Carry*(D70-D68)-C76)/(1-Carry)))*CatchUp,0) -> 0 | E71: =IF(E69>0,MIN(E69,MAX(0,(Carry*(E70-E68)-D76)/(1-Carry)))*CatchUp,0) -> 0 | F71: =IF(F69>0,MIN(F69,MAX(0,(Carry*(F70-F68)-E76)/(1-Carry)))*CatchUp,0) -> 0 | G71: =IF(G69>0,MIN(G69,MAX(0,(Carry*(G70-G68)-F76)/(1-Carry)))*CatchUp,0) -> 0 | H71: =IF(H69>0,MIN(H69,MAX(0,(Carry*(H70-H68)-G76)/(1-Carry)))*CatchUp,0) -> 0 | I71: =IF(I69>0,MIN(I69,MAX(0,(Carry*(I70-I68)-H76)/(1-Carry)))*CatchUp,0) -> 8007027.8 | J71: =IF(J69>0,MIN(J69,MAX(0,(Carry*(J70-J68)-I76)/(1-Carry)))*CatchUp,0) -> 0 | K71: =IF(K69>0,MIN(K69,MAX(0,(Carry*(K70-K68)-J76)/(1-Carry)))*CatchUp,0) -> 0 | L71: =IF(L69>0,MIN(L69,MAX(0,(Carry*(L70-L68)-K76)/(1-Carry)))*CatchUp,0) -> 0
A72: Remaining after step 2 | C72: =C69-C71 -> 0 | D72: =D69-D71 -> 0 | E72: =E69-E71 -> 0 | F72: =F69-F71 -> 0 | G72: =G69-G71 -> 0 | H72: =H69-H71 -> 0 | I72: =I69-I71 -> 297360.92 | J72: =J69-J71 -> 44625000 | ... L72: =L69-L71 -> 0
A73: 3. Split: to LPs | B73: =SUM(C73:L73) -> 35937889 | C73: =IF(C72>0,(1-Carry)*C72,0) -> 0 | D73: =IF(D72>0,(1-Carry)*D72,0) -> 0 | E73: =IF(E72>0,(1-Carry)*E72,0) -> 0 | F73: =IF(F72>0,(1-Carry)*F72,0) -> 0 | G73: =IF(G72>0,(1-Carry)*G72,0) -> 0 | H73: =IF(H72>0,(1-Carry)*H72,0) -> 0 | I73: =IF(I72>0,(1-Carry)*I72,0) -> 237888.74 | J73: =IF(J72>0,(1-Carry)*J72,0) -> 35700000 | ... L73: =IF(L72>0,(1-Carry)*L72,0) -> 0
A74: 3. Split: carried interest to the GP | B74: =SUM(C74:L74) -> 8984472.2 | C74: =IF(C72>0,Carry*C72,0) -> 0 | D74: =IF(D72>0,Carry*D72,0) -> 0 | E74: =IF(E72>0,Carry*E72,0) -> 0 | F74: =IF(F72>0,Carry*F72,0) -> 0 | G74: =IF(G72>0,Carry*G72,0) -> 0 | H74: =IF(H72>0,Carry*H72,0) -> 0 | I74: =IF(I72>0,Carry*I72,0) -> 59472.185 | J74: =IF(J72>0,Carry*J72,0) -> 8925000 | ... L74: =IF(L72>0,Carry*L72,0) -> 0
A75: Cumulative paid out | C75: =C70+C71+IF(C72>0,C72,0) -> 0 | D75: =D70+D71+IF(D72>0,D72,0) -> 0 | E75: =E70+E71+IF(E72>0,E72,0) -> 0 | F75: =F70+F71+IF(F72>0,F72,0) -> 4300000 | G75: =G70+G71+IF(G72>0,G72,0) -> 11800000 | H75: =H70+H71+IF(H72>0,H72,0) -> 59550000 | I75: =I70+I71+IF(I72>0,I72,0) -> 138950000 | J75: =J70+J71+IF(J72>0,J72,0) -> 184150000 | ... L75: =L70+L71+IF(L72>0,L72,0) -> 184150000
A76: Cumulative carried interest | C76: =C71+C74 -> 0 | D76: =C76+D71+D74 -> 0 | E76: =D76+E71+E74 -> 0 | F76: =E76+F71+F74 -> 0 | G76: =F76+G71+G74 -> 0 | H76: =G76+H71+H74 -> 0 | I76: =H76+I71+I74 -> 8066500 | J76: =I76+J71+J74 -> 16991500 | K76: =J76+K71+K74 -> 16991500 | L76: =K76+L71+L74 -> 16991500
A78: LP distributions | B78: =SUM(C78:L78) -> 167158500 | C78: =C66+C73 -> 0 | D78: =D66+D73 -> 0 | E78: =E66+E73 -> 0 | F78: =F66+F73 -> 4300000 | G78: =G66+G73 -> 7500000 | H78: =H66+H73 -> 47750000 | I78: =I66+I73 -> 71333500 | J78: =J66+J73 -> 36275000 | ... L78: =L66+L73 -> 0
A79: GP carried interest | B79: =SUM(C79:L79) -> 16991500 | C79: =C71+C74 -> 0 | D79: =D71+D74 -> 0 | E79: =E71+E74 -> 0 | F79: =F71+F74 -> 0 | G79: =G71+G74 -> 0 | H79: =H71+H74 -> 0 | I79: =I71+I74 -> 8066500 | J79: =J71+J74 -> 8925000 | ... L79: =L71+L74 -> 0
A80: Net LP cash flow (distributions − calls) | B80: =SUM(C80:L80) -> 67966000 | C80: =C78-C63 -> -11750000 | D80: =D78-D63 -> -24350000 | E80: =E78-E63 -> -43850000 | F80: =F78-F63 -> -9450000 | G80: =G78-G63 -> 5150000 | H80: =H78-H63 -> 46257000 | I80: =I78-I63 -> 70259000 | J80: =J78-J63 -> 35700000 | ... L80: =L78-L63 -> 0
A81: Gross fund cash flow (exit proceeds − investments) | B81: =SUM(C81:L81) -> 100950000 | C81: =C56-C55 -> -9000000 | D81: =D56-D55 -> -22000000 | E81: =E56-E55 -> -41500000 | F81: =F56-F55 -> -7100000 | G81: =G56-G55 -> 7500000 | H81: =H56-H55 -> 47750000 | I81: =I56-I55 -> 79400000 | J81: =J56-J55 -> 45900000 | ... L81: =L56-L55 -> 0
A83: Outputs — Base case
A84: Gross exit value | B84: =Lines!T29 -> 190700000
A85: Realised (exit proceeds incl. secondary) | B85: =ROUND((SUM(C56:L56))/IF(ABS(SUM(C56:L56))<1000000,10000,100000),0)*IF(ABS(SUM(C56:L56))<1000000,10000,100000) -> 184900000
A86: Secondary discount | B86: =B84-B85 -> 5800000
A87: Paid-in capital | B87: =ROUND((SUM(C63:L63))/IF(ABS(SUM(C63:L63))<1000000,10000,100000),0)*IF(ABS(SUM(C63:L63))<1000000,10000,100000) -> 99200000
A88: Management fees | B88: =ROUND((SUM(C61:L61))/IF(ABS(SUM(C61:L61))<1000000,10000,100000),0)*IF(ABS(SUM(C61:L61))<1000000,10000,100000) -> 12100000
A89: Fund expenses | B89: =ROUND((SUM(C62:L62)+TailCost)/IF(ABS(SUM(C62:L62)+TailCost)<1000000,10000,100000),0)*IF(ABS(SUM(C62:L62)+TailCost)<1000000,10000,100000) -> 3900000
A90: LP distributions | B90: =ROUND((SUM(C78:L78))/IF(ABS(SUM(C78:L78))<1000000,10000,100000),0)*IF(ABS(SUM(C78:L78))<1000000,10000,100000) -> 167200000
A91: Carried interest | B91: =ROUND((SUM(C79:L79))/IF(ABS(SUM(C79:L79))<1000000,10000,100000),0)*IF(ABS(SUM(C79:L79))<1000000,10000,100000) -> 17000000
A92: Net TVPI | B92: =ROUND(SUM(C78:L78)/SUM(C63:L63),1) -> 1.7
A93: Net IRR | B93: =ROUND(IRR(C80:L80),2) -> 0.14
A94: Gross IRR | B94: =ROUND(IRR(C81:L81),2) -> 0.21
A95: Net DPI by year 6 | B95: =ROUND(SUM(C78:H78)/SUM(C63:H63),1) -> 0.6
A96: GP clawback (must be zero) | B96: =MAX(0,L76-Carry*MAX(0,L75-L68)) -> 0
A99: STRESS CASE — every exit value capped lower (Assumptions)
A100: Investments (initial tickets and follow-ons) | B100: =SUM(C100:L100) -> 83900000 | C100: =SUMIFS(Lines!$G$6:$G$28,Lines!$J$6:$J$28,C$7)+SUMIFS(Lines!$I$6:$I$28,Lines!$K$6:$K$28,C$7) -> 9000000 | D100: =SUMIFS(Lines!$G$6:$G$28,Lines!$J$6:$J$28,D$7)+SUMIFS(Lines!$I$6:$I$28,Lines!$K$6:$K$28,D$7) -> 22000000 | E100: =SUMIFS(Lines!$G$6:$G$28,Lines!$J$6:$J$28,E$7)+SUMIFS(Lines!$I$6:$I$28,Lines!$K$6:$K$28,E$7) -> 41500000 | F100: =SUMIFS(Lines!$G$6:$G$28,Lines!$J$6:$J$28,F$7)+SUMIFS(Lines!$I$6:$I$28,Lines!$K$6:$K$28,F$7) -> 11400000 | G100: =SUMIFS(Lines!$G$6:$G$28,Lines!$J$6:$J$28,G$7)+SUMIFS(Lines!$I$6:$I$28,Lines!$K$6:$K$28,G$7) -> 0 | H100: =SUMIFS(Lines!$G$6:$G$28,Lines!$J$6:$J$28,H$7)+SUMIFS(Lines!$I$6:$I$28,Lines!$K$6:$K$28,H$7) -> 0 | I100: =SUMIFS(Lines!$G$6:$G$28,Lines!$J$6:$J$28,I$7)+SUMIFS(Lines!$I$6:$I$28,Lines!$K$6:$K$28,I$7) -> 0 | J100: =SUMIFS(Lines!$G$6:$G$28,Lines!$J$6:$J$28,J$7)+SUMIFS(Lines!$I$6:$I$28,Lines!$K$6:$K$28,J$7) -> 0 | ... L100: =SUMIFS(Lines!$G$6:$G$28,Lines!$J$6:$J$28,L$7)+SUMIFS(Lines!$I$6:$I$28,Lines!$K$6:$K$28,L$7) -> 0
A101: Exit proceeds received, incl. the partial secondary sale | B101: =SUM(C101:L101) -> 112810000 | C101: =SUMIFS(Lines!$AH$6:$AH$28,Lines!$L$6:$L$28,C$7)+IF(C$7=SecYear,SUM(Lines!$AG$6:$AG$28),0) -> 0 | D101: =SUMIFS(Lines!$AH$6:$AH$28,Lines!$L$6:$L$28,D$7)+IF(D$7=SecYear,SUM(Lines!$AG$6:$AG$28),0) -> 0 | E101: =SUMIFS(Lines!$AH$6:$AH$28,Lines!$L$6:$L$28,E$7)+IF(E$7=SecYear,SUM(Lines!$AG$6:$AG$28),0) -> 0 | F101: =SUMIFS(Lines!$AH$6:$AH$28,Lines!$L$6:$L$28,F$7)+IF(F$7=SecYear,SUM(Lines!$AG$6:$AG$28),0) -> 4300000 | G101: =SUMIFS(Lines!$AH$6:$AH$28,Lines!$L$6:$L$28,G$7)+IF(G$7=SecYear,SUM(Lines!$AG$6:$AG$28),0) -> 7500000 | H101: =SUMIFS(Lines!$AH$6:$AH$28,Lines!$L$6:$L$28,H$7)+IF(H$7=SecYear,SUM(Lines!$AG$6:$AG$28),0) -> 31210000 | I101: =SUMIFS(Lines!$AH$6:$AH$28,Lines!$L$6:$L$28,I$7)+IF(I$7=SecYear,SUM(Lines!$AG$6:$AG$28),0) -> 46800000 | J101: =SUMIFS(Lines!$AH$6:$AH$28,Lines!$L$6:$L$28,J$7)+IF(J$7=SecYear,SUM(Lines!$AG$6:$AG$28),0) -> 23000000 | ... L101: =SUMIFS(Lines!$AH$6:$AH$28,Lines!$L$6:$L$28,L$7)+IF(L$7=SecYear,SUM(Lines!$AG$6:$AG$28),0) -> 0
A102: Running costs of the years after the horizon, set aside | B102: =SUM(C102:L102) -> -700000 | C102: =IF(C$7=Horizon,-TailCost,0) -> 0 | D102: =IF(D$7=Horizon,-TailCost,0) -> 0 | E102: =IF(E$7=Horizon,-TailCost,0) -> 0 | F102: =IF(F$7=Horizon,-TailCost,0) -> 0 | G102: =IF(G$7=Horizon,-TailCost,0) -> 0 | H102: =IF(H$7=Horizon,-TailCost,0) -> 0 | I102: =IF(I$7=Horizon,-TailCost,0) -> 0 | J102: =IF(J$7=Horizon,-TailCost,0) -> -700000 | ... L102: =IF(L$7=Horizon,-TailCost,0) -> 0
A103: Distributable proceeds | B103: =SUM(C103:L103) -> 112110000 | C103: =C101+C102 -> 0 | D103: =D101+D102 -> 0 | E103: =E101+E102 -> 0 | F103: =F101+F102 -> 4300000 | G103: =G101+G102 -> 7500000 | H103: =H101+H102 -> 31210000 | I103: =I101+I102 -> 46800000 | J103: =J101+J102 -> 22300000 | ... L103: =L101+L102 -> 0
A104: Cost of the positions sold | B104: =SUM(C104:L104) -> 83900000 | C104: =SUMIFS(Lines!$AJ$6:$AJ$28,Lines!$L$6:$L$28,C$7)+IF(C$7=SecYear,SUM(Lines!$AI$6:$AI$28),0) -> 0 | D104: =SUMIFS(Lines!$AJ$6:$AJ$28,Lines!$L$6:$L$28,D$7)+IF(D$7=SecYear,SUM(Lines!$AI$6:$AI$28),0) -> 0 | E104: =SUMIFS(Lines!$AJ$6:$AJ$28,Lines!$L$6:$L$28,E$7)+IF(E$7=SecYear,SUM(Lines!$AI$6:$AI$28),0) -> 0 | F104: =SUMIFS(Lines!$AJ$6:$AJ$28,Lines!$L$6:$L$28,F$7)+IF(F$7=SecYear,SUM(Lines!$AI$6:$AI$28),0) -> 1300000 | G104: =SUMIFS(Lines!$AJ$6:$AJ$28,Lines!$L$6:$L$28,G$7)+IF(G$7=SecYear,SUM(Lines!$AI$6:$AI$28),0) -> 6400000 | H104: =SUMIFS(Lines!$AJ$6:$AJ$28,Lines!$L$6:$L$28,H$7)+IF(H$7=SecYear,SUM(Lines!$AI$6:$AI$28),0) -> 27900000 | I104: =SUMIFS(Lines!$AJ$6:$AJ$28,Lines!$L$6:$L$28,I$7)+IF(I$7=SecYear,SUM(Lines!$AI$6:$AI$28),0) -> 33300000 | J104: =SUMIFS(Lines!$AJ$6:$AJ$28,Lines!$L$6:$L$28,J$7)+IF(J$7=SecYear,SUM(Lines!$AI$6:$AI$28),0) -> 15000000 | ... L104: =SUMIFS(Lines!$AJ$6:$AJ$28,Lines!$L$6:$L$28,L$7)+IF(L$7=SecYear,SUM(Lines!$AI$6:$AI$28),0) -> 0
A105: Net invested capital at cost, end of year | C105: =C100-C104 -> 9000000 | D105: =C105+D100-D104 -> 31000000 | E105: =D105+E100-E104 -> 72500000 | F105: =E105+F100-F104 -> 82600000 | G105: =F105+G100-G104 -> 76200000 | H105: =G105+H100-H104 -> 48300000 | I105: =H105+I100-I104 -> 15000000 | J105: =I105+J100-J104 -> 0 | K105: =J105+K100-K104 -> 0 | L105: =K105+L100-L104 -> 0
A106: Management fees | B106: =SUM(C106:L106) -> 12092500 | C106: =IF(C$7>Horizon,0,IF(C$7<=IPYears,FeeIP*Commitments,FeePost*MAX(0,0))) -> 2000000 | D106: =IF(D$7>Horizon,0,IF(D$7<=IPYears,FeeIP*Commitments,FeePost*MAX(C105,0))) -> 2000000 | E106: =IF(E$7>Horizon,0,IF(E$7<=IPYears,FeeIP*Commitments,FeePost*MAX(D105,0))) -> 2000000 | F106: =IF(F$7>Horizon,0,IF(F$7<=IPYears,FeeIP*Commitments,FeePost*MAX(E105,0))) -> 2000000 | G106: =IF(G$7>Horizon,0,IF(G$7<=IPYears,FeeIP*Commitments,FeePost*MAX(F105,0))) -> 2000000 | H106: =IF(H$7>Horizon,0,IF(H$7<=IPYears,FeeIP*Commitments,FeePost*MAX(G105,0))) -> 1143000 | I106: =IF(I$7>Horizon,0,IF(I$7<=IPYears,FeeIP*Commitments,FeePost*MAX(H105,0))) -> 724500 | J106: =IF(J$7>Horizon,0,IF(J$7<=IPYears,FeeIP*Commitments,FeePost*MAX(I105,0))) -> 225000 | K106: =IF(K$7>Horizon,0,IF(K$7<=IPYears,FeeIP*Commitments,FeePost*MAX(J105,0))) -> 0 | L106: =IF(L$7>Horizon,0,IF(L$7<=IPYears,FeeIP*Commitments,FeePost*MAX(K105,0))) -> 0
A107: Fund expenses | B107: =SUM(C107:L107) -> 3200000 | C107: =IF(C$7>Horizon,0,RunningCost+IF(C$7=1,SetupCost,0)) -> 750000 | D107: =IF(D$7>Horizon,0,RunningCost+IF(D$7=1,SetupCost,0)) -> 350000 | E107: =IF(E$7>Horizon,0,RunningCost+IF(E$7=1,SetupCost,0)) -> 350000 | F107: =IF(F$7>Horizon,0,RunningCost+IF(F$7=1,SetupCost,0)) -> 350000 | G107: =IF(G$7>Horizon,0,RunningCost+IF(G$7=1,SetupCost,0)) -> 350000 | H107: =IF(H$7>Horizon,0,RunningCost+IF(H$7=1,SetupCost,0)) -> 350000 | I107: =IF(I$7>Horizon,0,RunningCost+IF(I$7=1,SetupCost,0)) -> 350000 | J107: =IF(J$7>Horizon,0,RunningCost+IF(J$7=1,SetupCost,0)) -> 350000 | ... L107: =IF(L$7>Horizon,0,RunningCost+IF(L$7=1,SetupCost,0)) -> 0
A108: Capital calls | B108: =SUM(C108:L108) -> 99192500 | C108: =C100+C106+C107 -> 11750000 | D108: =D100+D106+D107 -> 24350000 | E108: =E100+E106+E107 -> 43850000 | F108: =F100+F106+F107 -> 13750000 | G108: =G100+G106+G107 -> 2350000 | H108: =H100+H106+H107 -> 1493000 | I108: =I100+I106+I107 -> 1074500 | J108: =J100+J106+J107 -> 575000 | ... L108: =L100+L106+L107 -> 0
A110: Hurdle balance before distribution (capital + 8% compounded) | C110: =C108 -> 11750000 | D110: =C112*(1+Hurdle)+D108 -> 37040000 | E110: =D112*(1+Hurdle)+E108 -> 83853200 | F110: =E112*(1+Hurdle)+F108 -> 104311456 | G110: =F112*(1+Hurdle)+G108 -> 1.1036237e+08 | H110: =G112*(1+Hurdle)+H108 -> 1.1258436e+08 | I110: =H112*(1+Hurdle)+I108 -> 88958811 | J110: =I112*(1+Hurdle)+J108 -> 46106516 | K110: =J112*(1+Hurdle)+K108 -> 25711037 | L110: =K112*(1+Hurdle)+L108 -> 27767920
A111: 1. Return of capital and preferred return to LPs | B111: =SUM(C111:L111) -> 112110000 | C111: =MIN(C103,C110) -> 0 | D111: =MIN(D103,D110) -> 0 | E111: =MIN(E103,E110) -> 0 | F111: =MIN(F103,F110) -> 4300000 | G111: =MIN(G103,G110) -> 7500000 | H111: =MIN(H103,H110) -> 31210000 | I111: =MIN(I103,I110) -> 46800000 | J111: =MIN(J103,J110) -> 22300000 | ... L111: =MIN(L103,L110) -> 0
A112: Hurdle balance after distribution | C112: =C110-C111 -> 11750000 | D112: =D110-D111 -> 37040000 | E112: =E110-E111 -> 83853200 | F112: =F110-F111 -> 100011456 | G112: =G110-G111 -> 1.0286237e+08 | H112: =H110-H111 -> 81374362 | I112: =I110-I111 -> 42158811 | J112: =J110-J111 -> 23806516 | ... L112: =L110-L111 -> 27767920
A113: Cumulative contributions | C113: =C108 -> 11750000 | D113: =C113+D108 -> 36100000 | E113: =D113+E108 -> 79950000 | F113: =E113+F108 -> 93700000 | G113: =F113+G108 -> 96050000 | H113: =G113+H108 -> 97543000 | I113: =H113+I108 -> 98617500 | J113: =I113+J108 -> 99192500 | K113: =J113+K108 -> 99192500 | L113: =K113+L108 -> 99192500
A114: Remaining after step 1 | C114: =C103-C111 -> 0 | D114: =D103-D111 -> 0 | E114: =E103-E111 -> 0 | F114: =F103-F111 -> 0 | G114: =G103-G111 -> 0 | H114: =H103-H111 -> 0 | I114: =I103-I111 -> 0 | J114: =J103-J111 -> 0 | ... L114: =L103-L111 -> 0
...

Sheet Performance
A1: Fund performance — target returns, built line by line
A2: Net of fees, expenses and carried interest. The table shown on profund.vc/pitch.
A4: Metric | B4: Target | C4: Base | D4: Stress
A5: Fund size | B5: =Commitments -> 100000000 | C5: =Commitments -> 100000000 | D5: =Commitments -> 100000000
A6: Gross exit value | B6: ='Cash flows'!$B$39 -> 324300000 | C6: ='Cash flows'!$B$84 -> 190700000 | D6: ='Cash flows'!$B$129 -> 115800000
A7: Year-6 secondary discount | B7: ='Cash flows'!$B$41 -> 16600000 | C7: ='Cash flows'!$B$86 -> 5800000 | D7: ='Cash flows'!$B$131 -> 3000000
A8: Net TVPI | B8: ='Cash flows'!$B$47 -> 2.7 | C8: ='Cash flows'!$B$92 -> 1.7 | D8: ='Cash flows'!$B$137 -> 1.1
A9: Net IRR | B9: ='Cash flows'!$B$48 -> 0.26 | C9: ='Cash flows'!$B$93 -> 0.14 | D9: ='Cash flows'!$B$138 -> 0.03
A10: Net DPI by year 6 | B10: ='Cash flows'!$B$50 -> 0.9 | C10: ='Cash flows'!$B$95 -> 0.6 | D10: ='Cash flows'!$B$140 -> 0.4
A11: Gross MOIC · Seed | B11: =Construction!$L$6 -> 6.7 | C11: =Construction!$M$6 -> 3.7 | D11: =Construction!$N$6 -> 2.4
A12: Gross MOIC · Venture | B12: =Construction!$L$7 -> 3.3 | C12: =Construction!$M$7 -> 2.2 | D12: =Construction!$N$7 -> 1.4
A13: Gross MOIC · Growth | B13: =Construction!$L$8 -> 3.1 | C13: =Construction!$M$8 -> 1.6 | D13: =Construction!$N$8 -> 0.9
A15: More outputs
A16: Paid-in capital | B16: ='Cash flows'!$B$42 -> 99200000 | C16: ='Cash flows'!$B$87 -> 99200000 | D16: ='Cash flows'!$B$132 -> 99200000
A17: LP distributions | B17: ='Cash flows'!$B$45 -> 265400000 | C17: ='Cash flows'!$B$90 -> 167200000 | D17: ='Cash flows'!$B$135 -> 112100000
A18: Carried interest | B18: ='Cash flows'!$B$46 -> 41600000 | C18: ='Cash flows'!$B$91 -> 17000000 | D18: ='Cash flows'!$B$136 -> 0
A19: Gross IRR | B19: ='Cash flows'!$B$49 -> 0.34 | C19: ='Cash flows'!$B$94 -> 0.21 | D19: ='Cash flows'!$B$139 -> 0.08
A21: Net = after management fees (on commitments during the investment period, then on invested capital), fund expenses and carried interest (European whole-of-fund waterfall with a hurdle and GP catch-up), before tax. The Target case assumes one fund returner and a partial secondary sale of the two largest winners (see Assumptions). Base and Stress cap every exit value; everything else is unchanged. Targets are model outputs, not a forecast or a guarantee.
A27: All projections, targets, simulated portfolios, and return figures (IRR/DPI/MOIC) are indicative, hypothetical, and illustrative; actual results may differ materially.

Sheet Checks
A1: Checks — this workbook vs the Python model
A2: Every output recalculated here is compared with the published model, scripts/fund_model.py (src/data/fund.json): change an input and these checks turn red by design.
A4: =IF(COUNTIF(Checks!$E$7:$E$271,"CHECK")=0,"ALL CHECKS PASS","CHECK FAILED") -> ALL CHECKS PASS | B4: =COUNTIF(Checks!$E$7:$E$271,"OK") -> 263
A6: Check | B6: This workbook | C6: Python model (fund.json) | D6: Difference | E6: Status
A7: Target · Gross exit value | B7: ='Cash flows'!$B$39 -> 324300000 | C7: 324300000 | D7: =B7-C7 -> 0 | E7: =IF(ABS(D7)<0.000001,"OK","CHECK") -> OK
A8: Target · Realised (exit proceeds incl. secondary) | B8: ='Cash flows'!$B$40 -> 307700000 | C8: 307700000 | D8: =B8-C8 -> 0 | E8: =IF(ABS(D8)<0.000001,"OK","CHECK") -> OK
A9: Target · Secondary discount | B9: ='Cash flows'!$B$41 -> 16600000 | C9: 16600000 | D9: =B9-C9 -> 0 | E9: =IF(ABS(D9)<0.000001,"OK","CHECK") -> OK
A10: Target · Paid-in capital | B10: ='Cash flows'!$B$42 -> 99200000 | C10: 99200000 | D10: =B10-C10 -> 0 | E10: =IF(ABS(D10)<0.000001,"OK","CHECK") -> OK
A11: Target · Management fees | B11: ='Cash flows'!$B$43 -> 12100000 | C11: 12100000 | D11: =B11-C11 -> 0 | E11: =IF(ABS(D11)<0.000001,"OK","CHECK") -> OK
A12: Target · Fund expenses | B12: ='Cash flows'!$B$44 -> 3900000 | C12: 3900000 | D12: =B12-C12 -> 0 | E12: =IF(ABS(D12)<0.000001,"OK","CHECK") -> OK
A13: Target · LP distributions | B13: ='Cash flows'!$B$45 -> 265400000 | C13: 265400000 | D13: =B13-C13 -> 0 | E13: =IF(ABS(D13)<0.000001,"OK","CHECK") -> OK
A14: Target · Carried interest | B14: ='Cash flows'!$B$46 -> 41600000 | C14: 41600000 | D14: =B14-C14 -> 0 | E14: =IF(ABS(D14)<0.000001,"OK","CHECK") -> OK
A15: Target · Net TVPI | B15: ='Cash flows'!$B$47 -> 2.7 | C15: 2.7 | D15: =B15-C15 -> 0 | E15: =IF(ABS(D15)<0.000001,"OK","CHECK") -> OK
A16: Target · Net IRR | B16: ='Cash flows'!$B$48 -> 0.26 | C16: 0.26 | D16: =B16-C16 -> 0 | E16: =IF(ABS(D16)<0.000001,"OK","CHECK") -> OK
A17: Target · Gross IRR | B17: ='Cash flows'!$B$49 -> 0.34 | C17: 0.34 | D17: =B17-C17 -> 0 | E17: =IF(ABS(D17)<0.000001,"OK","CHECK") -> OK
A18: Target · Net DPI by year 6 | B18: ='Cash flows'!$B$50 -> 0.9 | C18: 0.9 | D18: =B18-C18 -> 0 | E18: =IF(ABS(D18)<0.000001,"OK","CHECK") -> OK
A19: Target · capital calls, year 1 (rounded) | B19: =ROUND(('Cash flows'!$C$18)/IF(ABS('Cash flows'!$C$18)<1000000,10000,100000),0)*IF(ABS('Cash flows'!$C$18)<1000000,10000,100000) -> 11800000 | C19: 11800000 | D19: =B19-C19 -> 0 | E19: =IF(ABS(D19)<0.000001,"OK","CHECK") -> OK
A20: Target · capital calls, year 2 (rounded) | B20: =ROUND(('Cash flows'!$D$18)/IF(ABS('Cash flows'!$D$18)<1000000,10000,100000),0)*IF(ABS('Cash flows'!$D$18)<1000000,10000,100000) -> 24400000 | C20: 24400000 | D20: =B20-C20 -> 0 | E20: =IF(ABS(D20)<0.000001,"OK","CHECK") -> OK
A21: Target · capital calls, year 3 (rounded) | B21: =ROUND(('Cash flows'!$E$18)/IF(ABS('Cash flows'!$E$18)<1000000,10000,100000),0)*IF(ABS('Cash flows'!$E$18)<1000000,10000,100000) -> 43900000 | C21: 43900000 | D21: =B21-C21 -> 0 | E21: =IF(ABS(D21)<0.000001,"OK","CHECK") -> OK
A22: Target · capital calls, year 4 (rounded) | B22: =ROUND(('Cash flows'!$F$18)/IF(ABS('Cash flows'!$F$18)<1000000,10000,100000),0)*IF(ABS('Cash flows'!$F$18)<1000000,10000,100000) -> 13800000 | C22: 13800000 | D22: =B22-C22 -> 0 | E22: =IF(ABS(D22)<0.000001,"OK","CHECK") -> OK
A23: Target · capital calls, year 5 (rounded) | B23: =ROUND(('Cash flows'!$G$18)/IF(ABS('Cash flows'!$G$18)<1000000,10000,100000),0)*IF(ABS('Cash flows'!$G$18)<1000000,10000,100000) -> 2400000 | C23: 2400000 | D23: =B23-C23 -> 0 | E23: =IF(ABS(D23)<0.000001,"OK","CHECK") -> OK
A24: Target · capital calls, year 6 (rounded) | B24: =ROUND(('Cash flows'!$H$18)/IF(ABS('Cash flows'!$H$18)<1000000,10000,100000),0)*IF(ABS('Cash flows'!$H$18)<1000000,10000,100000) -> 1500000 | C24: 1500000 | D24: =B24-C24 -> 0 | E24: =IF(ABS(D24)<0.000001,"OK","CHECK") -> OK
A25: Target · capital calls, year 7 (rounded) | B25: =ROUND(('Cash flows'!$I$18)/IF(ABS('Cash flows'!$I$18)<1000000,10000,100000),0)*IF(ABS('Cash flows'!$I$18)<1000000,10000,100000) -> 1100000 | C25: 1100000 | D25: =B25-C25 -> 0 | E25: =IF(ABS(D25)<0.000001,"OK","CHECK") -> OK
A26: Target · capital calls, year 8 (rounded) | B26: =ROUND(('Cash flows'!$J$18)/IF(ABS('Cash flows'!$J$18)<1000000,10000,100000),0)*IF(ABS('Cash flows'!$J$18)<1000000,10000,100000) -> 580000 | C26: 580000 | D26: =B26-C26 -> 0 | E26: =IF(ABS(D26)<0.000001,"OK","CHECK") -> OK
A27: Target · distributions, year 1 (rounded) | B27: =ROUND(('Cash flows'!$C$13)/IF(ABS('Cash flows'!$C$13)<1000000,10000,100000),0)*IF(ABS('Cash flows'!$C$13)<1000000,10000,100000) -> 0 | C27: 0 | D27: =B27-C27 -> 0 | E27: =IF(ABS(D27)<0.000001,"OK","CHECK") -> OK
A28: Target · distributions, year 2 (rounded) | B28: =ROUND(('Cash flows'!$D$13)/IF(ABS('Cash flows'!$D$13)<1000000,10000,100000),0)*IF(ABS('Cash flows'!$D$13)<1000000,10000,100000) -> 0 | C28: 0 | D28: =B28-C28 -> 0 | E28: =IF(ABS(D28)<0.000001,"OK","CHECK") -> OK
A29: Target · distributions, year 3 (rounded) | B29: =ROUND(('Cash flows'!$E$13)/IF(ABS('Cash flows'!$E$13)<1000000,10000,100000),0)*IF(ABS('Cash flows'!$E$13)<1000000,10000,100000) -> 0 | C29: 0 | D29: =B29-C29 -> 0 | E29: =IF(ABS(D29)<0.000001,"OK","CHECK") -> OK
A30: Target · distributions, year 4 (rounded) | B30: =ROUND(('Cash flows'!$F$13)/IF(ABS('Cash flows'!$F$13)<1000000,10000,100000),0)*IF(ABS('Cash flows'!$F$13)<1000000,10000,100000) -> 4300000 | C30: 4300000 | D30: =B30-C30 -> 0 | E30: =IF(ABS(D30)<0.000001,"OK","CHECK") -> OK
A31: Target · distributions, year 5 (rounded) | B31: =ROUND(('Cash flows'!$G$13)/IF(ABS('Cash flows'!$G$13)<1000000,10000,100000),0)*IF(ABS('Cash flows'!$G$13)<1000000,10000,100000) -> 7500000 | C31: 7500000 | D31: =B31-C31 -> 0 | E31: =IF(ABS(D31)<0.000001,"OK","CHECK") -> OK
A32: Target · distributions, year 6 (rounded) | B32: =ROUND(('Cash flows'!$H$13)/IF(ABS('Cash flows'!$H$13)<1000000,10000,100000),0)*IF(ABS('Cash flows'!$H$13)<1000000,10000,100000) -> 74000000 | C32: 74000000 | D32: =B32-C32 -> 0 | E32: =IF(ABS(D32)<0.000001,"OK","CHECK") -> OK
A33: Target · distributions, year 7 (rounded) | B33: =ROUND(('Cash flows'!$I$13)/IF(ABS('Cash flows'!$I$13)<1000000,10000,100000),0)*IF(ABS('Cash flows'!$I$13)<1000000,10000,100000) -> 97000000 | C33: 97000000 | D33: =B33-C33 -> 0 | E33: =IF(ABS(D33)<0.000001,"OK","CHECK") -> OK
A34: Target · distributions, year 8 (rounded) | B34: =ROUND(('Cash flows'!$J$13)/IF(ABS('Cash flows'!$J$13)<1000000,10000,100000),0)*IF(ABS('Cash flows'!$J$13)<1000000,10000,100000) -> 124200000 | C34: 124200000 | D34: =B34-C34 -> 0 | E34: =IF(ABS(D34)<0.000001,"OK","CHECK") -> OK
A35: Target · LP distributions, year 1 (rounded) | B35: =ROUND(('Cash flows'!$C$33)/IF(ABS('Cash flows'!$C$33)<1000000,10000,100000),0)*IF(ABS('Cash flows'!$C$33)<1000000,10000,100000) -> 0 | C35: 0 | D35: =B35-C35 -> 0 | E35: =IF(ABS(D35)<0.000001,"OK","CHECK") -> OK
A36: Target · LP distributions, year 2 (rounded) | B36: =ROUND(('Cash flows'!$D$33)/IF(ABS('Cash flows'!$D$33)<1000000,10000,100000),0)*IF(ABS('Cash flows'!$D$33)<1000000,10000,100000) -> 0 | C36: 0 | D36: =B36-C36 -> 0 | E36: =IF(ABS(D36)<0.000001,"OK","CHECK") -> OK
A37: Target · LP distributions, year 3 (rounded) | B37: =ROUND(('Cash flows'!$E$33)/IF(ABS('Cash flows'!$E$33)<1000000,10000,100000),0)*IF(ABS('Cash flows'!$E$33)<1000000,10000,100000) -> 0 | C37: 0 | D37: =B37-C37 -> 0 | E37: =IF(ABS(D37)<0.000001,"OK","CHECK") -> OK
A38: Target · LP distributions, year 4 (rounded) | B38: =ROUND(('Cash flows'!$F$33)/IF(ABS('Cash flows'!$F$33)<1000000,10000,100000),0)*IF(ABS('Cash flows'!$F$33)<1000000,10000,100000) -> 4300000 | C38: 4300000 | D38: =B38-C38 -> 0 | E38: =IF(ABS(D38)<0.000001,"OK","CHECK") -> OK
A39: Target · LP distributions, year 5 (rounded) | B39: =ROUND(('Cash flows'!$G$33)/IF(ABS('Cash flows'!$G$33)<1000000,10000,100000),0)*IF(ABS('Cash flows'!$G$33)<1000000,10000,100000) -> 7500000 | C39: 7500000 | D39: =B39-C39 -> 0 | E39: =IF(ABS(D39)<0.000001,"OK","CHECK") -> OK
A40: Target · LP distributions, year 6 (rounded) | B40: =ROUND(('Cash flows'!$H$33)/IF(ABS('Cash flows'!$H$33)<1000000,10000,100000),0)*IF(ABS('Cash flows'!$H$33)<1000000,10000,100000) -> 74000000 | C40: 74000000 | D40: =B40-C40 -> 0 | E40: =IF(ABS(D40)<0.000001,"OK","CHECK") -> OK
A41: Target · LP distributions, year 7 (rounded) | B41: =ROUND(('Cash flows'!$I$33)/IF(ABS('Cash flows'!$I$33)<1000000,10000,100000),0)*IF(ABS('Cash flows'!$I$33)<1000000,10000,100000) -> 80200000 | C41: 80200000 | D41: =B41-C41 -> 0 | E41: =IF(ABS(D41)<0.000001,"OK","CHECK") -> OK
A42: Target · LP distributions, year 8 (rounded) | B42: =ROUND(('Cash flows'!$J$33)/IF(ABS('Cash flows'!$J$33)<1000000,10000,100000),0)*IF(ABS('Cash flows'!$J$33)<1000000,10000,100000) -> 99500000 | C42: 99500000 | D42: =B42-C42 -> 0 | E42: =IF(ABS(D42)<0.000001,"OK","CHECK") -> OK
A43: Target · carried interest, year 1 (rounded) | B43: =ROUND(('Cash flows'!$C$34)/IF(ABS('Cash flows'!$C$34)<1000000,10000,100000),0)*IF(ABS('Cash flows'!$C$34)<1000000,10000,100000) -> 0 | C43: 0 | D43: =B43-C43 -> 0 | E43: =IF(ABS(D43)<0.000001,"OK","CHECK") -> OK
A44: Target · carried interest, year 2 (rounded) | B44: =ROUND(('Cash flows'!$D$34)/IF(ABS('Cash flows'!$D$34)<1000000,10000,100000),0)*IF(ABS('Cash flows'!$D$34)<1000000,10000,100000) -> 0 | C44: 0 | D44: =B44-C44 -> 0 | E44: =IF(ABS(D44)<0.000001,"OK","CHECK") -> OK
A45: Target · carried interest, year 3 (rounded) | B45: =ROUND(('Cash flows'!$E$34)/IF(ABS('Cash flows'!$E$34)<1000000,10000,100000),0)*IF(ABS('Cash flows'!$E$34)<1000000,10000,100000) -> 0 | C45: 0 | D45: =B45-C45 -> 0 | E45: =IF(ABS(D45)<0.000001,"OK","CHECK") -> OK
A46: Target · carried interest, year 4 (rounded) | B46: =ROUND(('Cash flows'!$F$34)/IF(ABS('Cash flows'!$F$34)<1000000,10000,100000),0)*IF(ABS('Cash flows'!$F$34)<1000000,10000,100000) -> 0 | C46: 0 | D46: =B46-C46 -> 0 | E46: =IF(ABS(D46)<0.000001,"OK","CHECK") -> OK
A47: Target · carried interest, year 5 (rounded) | B47: =ROUND(('Cash flows'!$G$34)/IF(ABS('Cash flows'!$G$34)<1000000,10000,100000),0)*IF(ABS('Cash flows'!$G$34)<1000000,10000,100000) -> 0 | C47: 0 | D47: =B47-C47 -> 0 | E47: =IF(ABS(D47)<0.000001,"OK","CHECK") -> OK
A48: Target · carried interest, year 6 (rounded) | B48: =ROUND(('Cash flows'!$H$34)/IF(ABS('Cash flows'!$H$34)<1000000,10000,100000),0)*IF(ABS('Cash flows'!$H$34)<1000000,10000,100000) -> 0 | C48: 0 | D48: =B48-C48 -> 0 | E48: =IF(ABS(D48)<0.000001,"OK","CHECK") -> OK
A49: Target · carried interest, year 7 (rounded) | B49: =ROUND(('Cash flows'!$I$34)/IF(ABS('Cash flows'!$I$34)<1000000,10000,100000),0)*IF(ABS('Cash flows'!$I$34)<1000000,10000,100000) -> 16800000 | C49: 16800000 | D49: =B49-C49 -> 0 | E49: =IF(ABS(D49)<0.000001,"OK","CHECK") -> OK
A50: Target · carried interest, year 8 (rounded) | B50: =ROUND(('Cash flows'!$J$34)/IF(ABS('Cash flows'!$J$34)<1000000,10000,100000),0)*IF(ABS('Cash flows'!$J$34)<1000000,10000,100000) -> 24700000 | C50: 24700000 | D50: =B50-C50 -> 0 | E50: =IF(ABS(D50)<0.000001,"OK","CHECK") -> OK
A51: Base · Gross exit value | B51: ='Cash flows'!$B$84 -> 190700000 | C51: 190700000 | D51: =B51-C51 -> 0 | E51: =IF(ABS(D51)<0.000001,"OK","CHECK") -> OK
A52: Base · Realised (exit proceeds incl. secondary) | B52: ='Cash flows'!$B$85 -> 184900000 | C52: 184900000 | D52: =B52-C52 -> 0 | E52: =IF(ABS(D52)<0.000001,"OK","CHECK") -> OK
A53: Base · Secondary discount | B53: ='Cash flows'!$B$86 -> 5800000 | C53: 5800000 | D53: =B53-C53 -> 0 | E53: =IF(ABS(D53)<0.000001,"OK","CHECK") -> OK
A54: Base · Paid-in capital | B54: ='Cash flows'!$B$87 -> 99200000 | C54: 99200000 | D54: =B54-C54 -> 0 | E54: =IF(ABS(D54)<0.000001,"OK","CHECK") -> OK
A55: Base · Management fees | B55: ='Cash flows'!$B$88 -> 12100000 | C55: 12100000 | D55: =B55-C55 -> 0 | E55: =IF(ABS(D55)<0.000001,"OK","CHECK") -> OK
A56: Base · Fund expenses | B56: ='Cash flows'!$B$89 -> 3900000 | C56: 3900000 | D56: =B56-C56 -> 0 | E56: =IF(ABS(D56)<0.000001,"OK","CHECK") -> OK
A57: Base · LP distributions | B57: ='Cash flows'!$B$90 -> 167200000 | C57: 167200000 | D57: =B57-C57 -> 0 | E57: =IF(ABS(D57)<0.000001,"OK","CHECK") -> OK
A58: Base · Carried interest | B58: ='Cash flows'!$B$91 -> 17000000 | C58: 17000000 | D58: =B58-C58 -> 0 | E58: =IF(ABS(D58)<0.000001,"OK","CHECK") -> OK
A59: Base · Net TVPI | B59: ='Cash flows'!$B$92 -> 1.7 | C59: 1.7 | D59: =B59-C59 -> 0 | E59: =IF(ABS(D59)<0.000001,"OK","CHECK") -> OK
A60: Base · Net IRR | B60: ='Cash flows'!$B$93 -> 0.14 | C60: 0.14 | D60: =B60-C60 -> 0 | E60: =IF(ABS(D60)<0.000001,"OK","CHECK") -> OK
A61: Base · Gross IRR | B61: ='Cash flows'!$B$94 -> 0.21 | C61: 0.21 | D61: =B61-C61 -> 0 | E61: =IF(ABS(D61)<0.000001,"OK","CHECK") -> OK
A62: Base · Net DPI by year 6 | B62: ='Cash flows'!$B$95 -> 0.6 | C62: 0.6 | D62: =B62-C62 -> 0 | E62: =IF(ABS(D62)<0.000001,"OK","CHECK") -> OK
A63: Base · capital calls, year 1 (rounded) | B63: =ROUND(('Cash flows'!$C$63)/IF(ABS('Cash flows'!$C$63)<1000000,10000,100000),0)*IF(ABS('Cash flows'!$C$63)<1000000,10000,100000) -> 11800000 | C63: 11800000 | D63: =B63-C63 -> 0 | E63: =IF(ABS(D63)<0.000001,"OK","CHECK") -> OK
A64: Base · capital calls, year 2 (rounded) | B64: =ROUND(('Cash flows'!$D$63)/IF(ABS('Cash flows'!$D$63)<1000000,10000,100000),0)*IF(ABS('Cash flows'!$D$63)<1000000,10000,100000) -> 24400000 | C64: 24400000 | D64: =B64-C64 -> 0 | E64: =IF(ABS(D64)<0.000001,"OK","CHECK") -> OK
A65: Base · capital calls, year 3 (rounded) | B65: =ROUND(('Cash flows'!$E$63)/IF(ABS('Cash flows'!$E$63)<1000000,10000,100000),0)*IF(ABS('Cash flows'!$E$63)<1000000,10000,100000) -> 43900000 | C65: 43900000 | D65: =B65-C65 -> 0 | E65: =IF(ABS(D65)<0.000001,"OK","CHECK") -> OK
A66: Base · capital calls, year 4 (rounded) | B66: =ROUND(('Cash flows'!$F$63)/IF(ABS('Cash flows'!$F$63)<1000000,10000,100000),0)*IF(ABS('Cash flows'!$F$63)<1000000,10000,100000) -> 13800000 | C66: 13800000 | D66: =B66-C66 -> 0 | E66: =IF(ABS(D66)<0.000001,"OK","CHECK") -> OK
A67: Base · capital calls, year 5 (rounded) | B67: =ROUND(('Cash flows'!$G$63)/IF(ABS('Cash flows'!$G$63)<1000000,10000,100000),0)*IF(ABS('Cash flows'!$G$63)<1000000,10000,100000) -> 2400000 | C67: 2400000 | D67: =B67-C67 -> 0 | E67: =IF(ABS(D67)<0.000001,"OK","CHECK") -> OK
A68: Base · capital calls, year 6 (rounded) | B68: =ROUND(('Cash flows'!$H$63)/IF(ABS('Cash flows'!$H$63)<1000000,10000,100000),0)*IF(ABS('Cash flows'!$H$63)<1000000,10000,100000) -> 1500000 | C68: 1500000 | D68: =B68-C68 -> 0 | E68: =IF(ABS(D68)<0.000001,"OK","CHECK") -> OK
A69: Base · capital calls, year 7 (rounded) | B69: =ROUND(('Cash flows'!$I$63)/IF(ABS('Cash flows'!$I$63)<1000000,10000,100000),0)*IF(ABS('Cash flows'!$I$63)<1000000,10000,100000) -> 1100000 | C69: 1100000 | D69: =B69-C69 -> 0 | E69: =IF(ABS(D69)<0.000001,"OK","CHECK") -> OK
A70: Base · capital calls, year 8 (rounded) | B70: =ROUND(('Cash flows'!$J$63)/IF(ABS('Cash flows'!$J$63)<1000000,10000,100000),0)*IF(ABS('Cash flows'!$J$63)<1000000,10000,100000) -> 580000 | C70: 580000 | D70: =B70-C70 -> 0 | E70: =IF(ABS(D70)<0.000001,"OK","CHECK") -> OK
A71: Base · distributions, year 1 (rounded) | B71: =ROUND(('Cash flows'!$C$58)/IF(ABS('Cash flows'!$C$58)<1000000,10000,100000),0)*IF(ABS('Cash flows'!$C$58)<1000000,10000,100000) -> 0 | C71: 0 | D71: =B71-C71 -> 0 | E71: =IF(ABS(D71)<0.000001,"OK","CHECK") -> OK
A72: Base · distributions, year 2 (rounded) | B72: =ROUND(('Cash flows'!$D$58)/IF(ABS('Cash flows'!$D$58)<1000000,10000,100000),0)*IF(ABS('Cash flows'!$D$58)<1000000,10000,100000) -> 0 | C72: 0 | D72: =B72-C72 -> 0 | E72: =IF(ABS(D72)<0.000001,"OK","CHECK") -> OK
A73: Base · distributions, year 3 (rounded) | B73: =ROUND(('Cash flows'!$E$58)/IF(ABS('Cash flows'!$E$58)<1000000,10000,100000),0)*IF(ABS('Cash flows'!$E$58)<1000000,10000,100000) -> 0 | C73: 0 | D73: =B73-C73 -> 0 | E73: =IF(ABS(D73)<0.000001,"OK","CHECK") -> OK
A74: Base · distributions, year 4 (rounded) | B74: =ROUND(('Cash flows'!$F$58)/IF(ABS('Cash flows'!$F$58)<1000000,10000,100000),0)*IF(ABS('Cash flows'!$F$58)<1000000,10000,100000) -> 4300000 | C74: 4300000 | D74: =B74-C74 -> 0 | E74: =IF(ABS(D74)<0.000001,"OK","CHECK") -> OK
A75: Base · distributions, year 5 (rounded) | B75: =ROUND(('Cash flows'!$G$58)/IF(ABS('Cash flows'!$G$58)<1000000,10000,100000),0)*IF(ABS('Cash flows'!$G$58)<1000000,10000,100000) -> 7500000 | C75: 7500000 | D75: =B75-C75 -> 0 | E75: =IF(ABS(D75)<0.000001,"OK","CHECK") -> OK
A76: Base · distributions, year 6 (rounded) | B76: =ROUND(('Cash flows'!$H$58)/IF(ABS('Cash flows'!$H$58)<1000000,10000,100000),0)*IF(ABS('Cash flows'!$H$58)<1000000,10000,100000) -> 47800000 | C76: 47800000 | D76: =B76-C76 -> 0 | E76: =IF(ABS(D76)<0.000001,"OK","CHECK") -> OK
A77: Base · distributions, year 7 (rounded) | B77: =ROUND(('Cash flows'!$I$58)/IF(ABS('Cash flows'!$I$58)<1000000,10000,100000),0)*IF(ABS('Cash flows'!$I$58)<1000000,10000,100000) -> 79400000 | C77: 79400000 | D77: =B77-C77 -> 0 | E77: =IF(ABS(D77)<0.000001,"OK","CHECK") -> OK
A78: Base · distributions, year 8 (rounded) | B78: =ROUND(('Cash flows'!$J$58)/IF(ABS('Cash flows'!$J$58)<1000000,10000,100000),0)*IF(ABS('Cash flows'!$J$58)<1000000,10000,100000) -> 45200000 | C78: 45200000 | D78: =B78-C78 -> 0 | E78: =IF(ABS(D78)<0.000001,"OK","CHECK") -> OK
A79: Base · LP distributions, year 1 (rounded) | B79: =ROUND(('Cash flows'!$C$78)/IF(ABS('Cash flows'!$C$78)<1000000,10000,100000),0)*IF(ABS('Cash flows'!$C$78)<1000000,10000,100000) -> 0 | C79: 0 | D79: =B79-C79 -> 0 | E79: =IF(ABS(D79)<0.000001,"OK","CHECK") -> OK
A80: Base · LP distributions, year 2 (rounded) | B80: =ROUND(('Cash flows'!$D$78)/IF(ABS('Cash flows'!$D$78)<1000000,10000,100000),0)*IF(ABS('Cash flows'!$D$78)<1000000,10000,100000) -> 0 | C80: 0 | D80: =B80-C80 -> 0 | E80: =IF(ABS(D80)<0.000001,"OK","CHECK") -> OK
A81: Base · LP distributions, year 3 (rounded) | B81: =ROUND(('Cash flows'!$E$78)/IF(ABS('Cash flows'!$E$78)<1000000,10000,100000),0)*IF(ABS('Cash flows'!$E$78)<1000000,10000,100000) -> 0 | C81: 0 | D81: =B81-C81 -> 0 | E81: =IF(ABS(D81)<0.000001,"OK","CHECK") -> OK
A82: Base · LP distributions, year 4 (rounded) | B82: =ROUND(('Cash flows'!$F$78)/IF(ABS('Cash flows'!$F$78)<1000000,10000,100000),0)*IF(ABS('Cash flows'!$F$78)<1000000,10000,100000) -> 4300000 | C82: 4300000 | D82: =B82-C82 -> 0 | E82: =IF(ABS(D82)<0.000001,"OK","CHECK") -> OK
A83: Base · LP distributions, year 5 (rounded) | B83: =ROUND(('Cash flows'!$G$78)/IF(ABS('Cash flows'!$G$78)<1000000,10000,100000),0)*IF(ABS('Cash flows'!$G$78)<1000000,10000,100000) -> 7500000 | C83: 7500000 | D83: =B83-C83 -> 0 | E83: =IF(ABS(D83)<0.000001,"OK","CHECK") -> OK
A84: Base · LP distributions, year 6 (rounded) | B84: =ROUND(('Cash flows'!$H$78)/IF(ABS('Cash flows'!$H$78)<1000000,10000,100000),0)*IF(ABS('Cash flows'!$H$78)<1000000,10000,100000) -> 47800000 | C84: 47800000 | D84: =B84-C84 -> 0 | E84: =IF(ABS(D84)<0.000001,"OK","CHECK") -> OK
A85: Base · LP distributions, year 7 (rounded) | B85: =ROUND(('Cash flows'!$I$78)/IF(ABS('Cash flows'!$I$78)<1000000,10000,100000),0)*IF(ABS('Cash flows'!$I$78)<1000000,10000,100000) -> 71300000 | C85: 71300000 | D85: =B85-C85 -> 0 | E85: =IF(ABS(D85)<0.000001,"OK","CHECK") -> OK
A86: Base · LP distributions, year 8 (rounded) | B86: =ROUND(('Cash flows'!$J$78)/IF(ABS('Cash flows'!$J$78)<1000000,10000,100000),0)*IF(ABS('Cash flows'!$J$78)<1000000,10000,100000) -> 36300000 | C86: 36300000 | D86: =B86-C86 -> 0 | E86: =IF(ABS(D86)<0.000001,"OK","CHECK") -> OK
A87: Base · carried interest, year 1 (rounded) | B87: =ROUND(('Cash flows'!$C$79)/IF(ABS('Cash flows'!$C$79)<1000000,10000,100000),0)*IF(ABS('Cash flows'!$C$79)<1000000,10000,100000) -> 0 | C87: 0 | D87: =B87-C87 -> 0 | E87: =IF(ABS(D87)<0.000001,"OK","CHECK") -> OK
A88: Base · carried interest, year 2 (rounded) | B88: =ROUND(('Cash flows'!$D$79)/IF(ABS('Cash flows'!$D$79)<1000000,10000,100000),0)*IF(ABS('Cash flows'!$D$79)<1000000,10000,100000) -> 0 | C88: 0 | D88: =B88-C88 -> 0 | E88: =IF(ABS(D88)<0.000001,"OK","CHECK") -> OK
A89: Base · carried interest, year 3 (rounded) | B89: =ROUND(('Cash flows'!$E$79)/IF(ABS('Cash flows'!$E$79)<1000000,10000,100000),0)*IF(ABS('Cash flows'!$E$79)<1000000,10000,100000) -> 0 | C89: 0 | D89: =B89-C89 -> 0 | E89: =IF(ABS(D89)<0.000001,"OK","CHECK") -> OK
A90: Base · carried interest, year 4 (rounded) | B90: =ROUND(('Cash flows'!$F$79)/IF(ABS('Cash flows'!$F$79)<1000000,10000,100000),0)*IF(ABS('Cash flows'!$F$79)<1000000,10000,100000) -> 0 | C90: 0 | D90: =B90-C90 -> 0 | E90: =IF(ABS(D90)<0.000001,"OK","CHECK") -> OK
A91: Base · carried interest, year 5 (rounded) | B91: =ROUND(('Cash flows'!$G$79)/IF(ABS('Cash flows'!$G$79)<1000000,10000,100000),0)*IF(ABS('Cash flows'!$G$79)<1000000,10000,100000) -> 0 | C91: 0 | D91: =B91-C91 -> 0 | E91: =IF(ABS(D91)<0.000001,"OK","CHECK") -> OK
A92: Base · carried interest, year 6 (rounded) | B92: =ROUND(('Cash flows'!$H$79)/IF(ABS('Cash flows'!$H$79)<1000000,10000,100000),0)*IF(ABS('Cash flows'!$H$79)<1000000,10000,100000) -> 0 | C92: 0 | D92: =B92-C92 -> 0 | E92: =IF(ABS(D92)<0.000001,"OK","CHECK") -> OK
A93: Base · carried interest, year 7 (rounded) | B93: =ROUND(('Cash flows'!$I$79)/IF(ABS('Cash flows'!$I$79)<1000000,10000,100000),0)*IF(ABS('Cash flows'!$I$79)<1000000,10000,100000) -> 8100000 | C93: 8100000 | D93: =B93-C93 -> 0 | E93: =IF(ABS(D93)<0.000001,"OK","CHECK") -> OK
A94: Base · carried interest, year 8 (rounded) | B94: =ROUND(('Cash flows'!$J$79)/IF(ABS('Cash flows'!$J$79)<1000000,10000,100000),0)*IF(ABS('Cash flows'!$J$79)<1000000,10000,100000) -> 8900000 | C94: 8900000 | D94: =B94-C94 -> 0 | E94: =IF(ABS(D94)<0.000001,"OK","CHECK") -> OK
A95: Stress · Gross exit value | B95: ='Cash flows'!$B$129 -> 115800000 | C95: 115800000 | D95: =B95-C95 -> 0 | E95: =IF(ABS(D95)<0.000001,"OK","CHECK") -> OK
A96: Stress · Realised (exit proceeds incl. secondary) | B96: ='Cash flows'!$B$130 -> 112800000 | C96: 112800000 | D96: =B96-C96 -> 0 | E96: =IF(ABS(D96)<0.000001,"OK","CHECK") -> OK
A97: Stress · Secondary discount | B97: ='Cash flows'!$B$131 -> 3000000 | C97: 3000000 | D97: =B97-C97 -> 0 | E97: =IF(ABS(D97)<0.000001,"OK","CHECK") -> OK
A98: Stress · Paid-in capital | B98: ='Cash flows'!$B$132 -> 99200000 | C98: 99200000 | D98: =B98-C98 -> 0 | E98: =IF(ABS(D98)<0.000001,"OK","CHECK") -> OK
A99: Stress · Management fees | B99: ='Cash flows'!$B$133 -> 12100000 | C99: 12100000 | D99: =B99-C99 -> 0 | E99: =IF(ABS(D99)<0.000001,"OK","CHECK") -> OK
A100: Stress · Fund expenses | B100: ='Cash flows'!$B$134 -> 3900000 | C100: 3900000 | D100: =B100-C100 -> 0 | E100: =IF(ABS(D100)<0.000001,"OK","CHECK") -> OK
A101: Stress · LP distributions | B101: ='Cash flows'!$B$135 -> 112100000 | C101: 112100000 | D101: =B101-C101 -> 0 | E101: =IF(ABS(D101)<0.000001,"OK","CHECK") -> OK
A102: Stress · Carried interest | B102: ='Cash flows'!$B$136 -> 0 | C102: 0 | D102: =B102-C102 -> 0 | E102: =IF(ABS(D102)<0.000001,"OK","CHECK") -> OK
...
